Workbook

Sheet JAN
A1: January | B1: Monthly Regular Bills | C1: 46023 | D1: =C1+1 -> 46024 | E1: =D1+1 -> 46025 | F1: =E1+1 -> 46026 | G1: =F1+1 -> 46027 | H1: =G1+1 -> 46028 | I1: =H1+1 -> 46029 | J1: =I1+1 -> 46030 | K1: =J1+1 -> 46031 | ... AG1: =AF1+1 -> 46053 | AH1: TOTALS | AI1: SPENDING PLAN | AJ1: DIFFERENCE
A2: INCOME
A3: Main Job | AH3: =sum(B3:AG3) -> 0 | AI3: ='TOTALS&AVERAGES'!N3 | AJ3: =AI3-AH3 -> 0
A4: B Job | AH4: =sum(B4:AG4) -> 0 | AI4: ='TOTALS&AVERAGES'!N4 | AJ4: =AI4-AH4 -> 0
A5: Bonuses | AH5: =sum(B5:AG5) -> 0 | AI5: ='TOTALS&AVERAGES'!N5 | AJ5: =AI5-AH5 -> 0
A6: Gifts/Discounts | AH6: =sum(B6:AG6) -> 0 | AI6: ='TOTALS&AVERAGES'!N6 | AJ6: =AI6-AH6 -> 0
A7: Reimbursement | AH7: =sum(B7:AG7) -> 0 | AI7: ='TOTALS&AVERAGES'!N7 | AJ7: =AI7-AH7 -> 0
A8: Government Assistance | AH8: =sum(B8:AG8) -> 0 | AI8: ='TOTALS&AVERAGES'!N8 | AJ8: =AI8-AH8 -> 0
A9: Side Hustles | AH9: =sum(B9:AG9) -> 0 | AI9: ='TOTALS&AVERAGES'!N9 | AJ9: =AI9-AH9 -> 0
A10: Interest/Rewards | AH10: =sum(B10:AG10) -> 0 | AI10: ='TOTALS&AVERAGES'!N10 | AJ10: =AI10-AH10 -> 0
A11: VA Benefits | AH11: =sum(B11:AG11) -> 0 | AI11: ='TOTALS&AVERAGES'!N11 | AJ11: =AI11-AH11 -> 0
A12: Asset Cash Out | AH12: =sum(B12:AG12) -> 0 | AI12: ='TOTALS&AVERAGES'!N12 | AJ12: =AI12-AH12 -> 0
A13: Fed Tax Refund | AH13: =sum(B13:AG13) -> 0 | AI13: ='TOTALS&AVERAGES'!N13 | AJ13: =AI13-AH13 -> 0
A14: State Tax Refund | AH14: =sum(B14:AG14) -> 0 | AI14: ='TOTALS&AVERAGES'!N14 | AJ14: =AI14-AH14 -> 0
A15: TOTAL INCOME BEFORE TAXES | B15: =SUM(C3:AG14) -> 0 | C15: =SUM(C3:C14) -> 0 | D15: =SUM(D3:D14) -> 0 | E15: =SUM(E3:E14) -> 0 | F15: =SUM(F3:F14) -> 0 | G15: =SUM(G3:G14) -> 0 | H15: =SUM(H3:H14) -> 0 | I15: =SUM(I3:I14) -> 0 | J15: =SUM(J3:J14) -> 0 | ... AJ15: =SUM(AJ3:AJ14) -> 0
A16: EXPENSES BY D.A. CATEGORIES | B16: MONTHLY REGULAR BILLS
A17: SPIRITUAL | B17: =SUM(B18:B26) -> 0 | C17: =SUM(C18:C26) -> 0 | D17: =SUM(D18:D26) -> 0 | E17: =SUM(E18:E26) -> 0 | F17: =SUM(F18:F26) -> 0 | G17: =SUM(G18:G26) -> 0 | H17: =SUM(H18:H26) -> 0 | I17: =SUM(I18:I26) -> 0 | ... AJ17: =SUM(AJ18:AJ26) -> 0
A18: Tithing/Church Donation | AH18: =sum(B18:AG18) -> 0 | AI18: ='TOTALS&AVERAGES'!N18 | AJ18: =AI18-AH18 -> 0
A19: Books | AH19: =sum(B19:AG19) -> 0 | AI19: ='TOTALS&AVERAGES'!N19 | AJ19: =AI19-AH19 -> 0
A20: Charity | AH20: =sum(B20:AG20) -> 0 | AI20: ='TOTALS&AVERAGES'!N20 | AJ20: =AI20-AH20 -> 0
A21: Workshops | AH21: =sum(B21:AG21) -> 0 | AI21: ='TOTALS&AVERAGES'!N21 | AJ21: =AI21-AH21 -> 0
A22: Generosity | AH22: =sum(B22:AG22) -> 0 | AI22: ='TOTALS&AVERAGES'!N22 | AJ22: =AI22-AH22 -> 0
A23: Retreats / Seminars | AH23: =sum(B23:AG23) -> 0 | AI23: ='TOTALS&AVERAGES'!N23 | AJ23: =AI23-AH23 -> 0
A24: 7TH TRADITION / FELLOWSHIP/ PRG | AH24: =sum(B24:AG24) -> 0 | AI24: ='TOTALS&AVERAGES'!N24 | AJ24: =AI24-AH24 -> 0
A25: Conferences | AH25: =sum(B25:AG25) -> 0 | AI25: ='TOTALS&AVERAGES'!N25 | AJ25: =AI25-AH25 -> 0
A26: Career Investment | AH26: =sum(B26:AG26) -> 0 | AI26: ='TOTALS&AVERAGES'!N26 | AJ26: =AI26-AH26 -> 0
A27: Needs | B27: =SUM(B28:B43) -> 0 | C27: =SUM(C28:C43) -> 0 | D27: =SUM(D28:D43) -> 0 | E27: =SUM(E28:E43) -> 0 | F27: =SUM(F28:F43) -> 0 | G27: =SUM(G28:G43) -> 0 | H27: =SUM(H28:H43) -> 0 | I27: =SUM(I28:I43) -> 0 | ... AJ27: =SUM(AJ28:AJ43) -> 0
A28: Groceries | AH28: =sum(B28:AG28) -> 0 | AI28: ='TOTALS&AVERAGES'!N28 | AJ28: =AI28-AH28 -> 0
A29: Rent/Mortage | B29: 1st | AH29: =sum(B29:AG29) -> 0 | AI29: ='TOTALS&AVERAGES'!N29 | AJ29: =AI29-AH29 -> 0
A30: Cell Phone | B30: 20th | AH30: =sum(B30:AG30) -> 0 | AI30: ='TOTALS&AVERAGES'!N30 | AJ30: =AI30-AH30 -> 0
A31: Laundry/Cleaners | B31: * | AH31: =sum(B31:AG31) -> 0 | AI31: ='TOTALS&AVERAGES'!N31 | AJ31: =AI31-AH31 -> 0
A32: Car Fuel | B32: * | AH32: =sum(B32:AG32) -> 0 | AI32: ='TOTALS&AVERAGES'!N32 | AJ32: =AI32-AH32 -> 0
A33: Car Insurance | B33: * | AH33: =sum(B33:AG33) -> 0 | AI33: ='TOTALS&AVERAGES'!N33 | AJ33: =AI33-AH33 -> 0
A34: Home Items | B34: * | AH34: =sum(B34:AG34) -> 0 | AI34: ='TOTALS&AVERAGES'!N34 | AJ34: =AI34-AH34 -> 0
A35: Internet | AH35: =sum(B35:AG35) -> 0 | AI35: ='TOTALS&AVERAGES'!N35 | AJ35: =AI35-AH35 -> 0
A36: Electricity | B36: * | AH36: =sum(B36:AG36) -> 0 | AI36: ='TOTALS&AVERAGES'!N36 | AJ36: =AI36-AH36 -> 0
A37: Card Fees | AH37: =sum(B37:AG37) -> 0 | AI37: ='TOTALS&AVERAGES'!N37 | AJ37: =AI37-AH37 -> 0
A38: Moving | AH38: =sum(B38:AG38) -> 0 | AI38: ='TOTALS&AVERAGES'!N38 | AJ38: =AI38-AH38 -> 0
A39: Toiletries | B39: * | AH39: =sum(B39:AG39) -> 0 | AI39: ='TOTALS&AVERAGES'!N39 | AJ39: =AI39-AH39 -> 0
A40: Storage | B40: * | AH40: =sum(B40:AG40) -> 0 | AI40: ='TOTALS&AVERAGES'!N40 | AJ40: =AI40-AH40 -> 0
A41: MTA/Public Transportation | B41: * | AH41: =sum(B41:AG41) -> 0 | AI41: ='TOTALS&AVERAGES'!N41 | AJ41: =AI41-AH41 -> 0
A42: Health Care | AH42: =sum(B42:AG42) -> 0 | AI42: ='TOTALS&AVERAGES'!N42 | AJ42: =AI42-AH42 -> 0
A43: Repairs | AH43: =sum(B43:AG43) -> 0 | AI43: ='TOTALS&AVERAGES'!N43 | AJ43: =AI43-AH43 -> 0
A44: Wants | B44: =SUM(B45:B52) -> 0 | C44: =SUM(C45:C52) -> 0 | D44: =SUM(D45:D52) -> 0 | E44: =SUM(E45:E52) -> 0 | F44: =SUM(F45:F52) -> 0 | G44: =SUM(G45:G52) -> 0 | H44: =SUM(H45:H52) -> 0 | I44: =SUM(I45:I52) -> 0 | ... AJ44: =SUM(AJ45:AJ52) -> 0
A45: Clothes | AH45: =sum(B45:AG45) -> 0 | AI45: ='TOTALS&AVERAGES'!N45 | AJ45: =AI45-AH45 -> 0
A46: Haircuts | AH46: =sum(B46:AG46) -> 0 | AI46: ='TOTALS&AVERAGES'!N46 | AJ46: =AI46-AH46 -> 0
A47: Dining Out/Take out/Events | AH47: =sum(B47:AG47) -> 0 | AI47: ='TOTALS&AVERAGES'!N47 | AJ47: =AI47-AH47 -> 0
A48: Gym Membership | AH48: =sum(B48:AG48) -> 0 | AI48: ='TOTALS&AVERAGES'!N48 | AJ48: =AI48-AH48 -> 0
A49: Subscriptions Zoom/Paramount/Club Free/News Subsription | B49: Zoom- 11th Para- 23rd Club- 28th | AH49: =sum(B49:AG49) -> 0 | AI49: ='TOTALS&AVERAGES'!N49 | AJ49: =AI49-AH49 -> 0
A50: Snacks | AH50: =sum(B50:AG50) -> 0 | AI50: ='TOTALS&AVERAGES'!N50 | AJ50: =AI50-AH50 -> 0
A51: Vacations/Trip to see Brother Bryant/Trip to NM/Trip to San Antonio | AH51: =sum(B51:AG51) -> 0 | AI51: ='TOTALS&AVERAGES'!N51 | AJ51: =AI51-AH51 -> 0
A52: Other/Misc | AH52: =sum(B52:AG52) -> 0 | AI52: ='TOTALS&AVERAGES'!N52 | AJ52: =AI52-AH52 -> 0
A53: Savings | B53: =SUM(B54:B67) -> 0 | C53: =SUM(C54:C67) -> 0 | D53: =SUM(D54:D67) -> 0 | E53: =SUM(E54:E67) -> 0 | F53: =SUM(F54:F67) -> 0 | G53: =SUM(G54:G67) -> 0 | H53: =SUM(H54:H67) -> 0 | I53: =SUM(I54:I67) -> 0 | ... AJ53: =SUM(AJ54:AJ67) -> 0
A54: High yield Savings | B54: * | AH54: =sum(B54:AG54) -> 0 | AI54: ='TOTALS&AVERAGES'!N54 | AJ54: =AI54-AH54 -> 0
A55: Emergency Fund | B55: * | AH55: =sum(B55:AG55) -> 0 | AI55: ='TOTALS&AVERAGES'!N55 | AJ55: =AI55-AH55 -> 0
A56: Stocks/Index Fund | B56: * | AH56: =sum(B56:AG56) -> 0 | AI56: ='TOTALS&AVERAGES'!N56 | AJ56: =AI56-AH56 -> 0
A57: Real Estate | AH57: =sum(B57:AG57) -> 0 | AI57: ='TOTALS&AVERAGES'!N57 | AJ57: =AI57-AH57 -> 0
A58: Extra Debt Payment | AH58: =sum(B58:AG58) -> 0 | AI58: ='TOTALS&AVERAGES'!N58 | AJ58: =AI58-AH58 -> 0
A59: Gold | AH59: =sum(B59:AG59) -> 0 | AI59: ='TOTALS&AVERAGES'!N59 | AJ59: =AI59-AH59 -> 0
A60: Retirement/Roth IRA | AH60: =sum(B60:AG60) -> 0 | AI60: ='TOTALS&AVERAGES'!N60 | AJ60: =AI60-AH60 -> 0
A61: Annuities | AH61: =sum(B61:AG61) -> 0 | AI61: ='TOTALS&AVERAGES'!N61 | AJ61: =AI61-AH61 -> 0
A62: Life Insurance | AH62: =sum(B62:AG62) -> 0 | AI62: ='TOTALS&AVERAGES'!N62 | AJ62: =AI62-AH62 -> 0
A63: Watch | AH63: =sum(B63:AG63) -> 0 | AI63: ='TOTALS&AVERAGES'!N63 | AJ63: =AI63-AH63 -> 0
A64: CD | AH64: =sum(B64:AG64) -> 0 | AI64: ='TOTALS&AVERAGES'!N64 | AJ64: =AI64-AH64 -> 0
A65: Taxes Savings | AH65: =sum(B65:AG65) -> 0 | AI65: ='TOTALS&AVERAGES'!N65 | AJ65: =AI65-AH65 -> 0
A66: HSA | AH66: =sum(B66:AG66) -> 0 | AI66: ='TOTALS&AVERAGES'!N66 | AJ66: =AI66-AH66 -> 0
A67: - | AH67: =sum(B67:AG67) -> 0 | AI67: ='TOTALS&AVERAGES'!N67 | AJ67: =AI67-AH67 -> 0
A68: Debts | B68: =SUM(B69:B79) -> 0 | C68: =SUM(C69:C79) -> 0 | D68: =SUM(D69:D79) -> 0 | E68: =SUM(E69:E79) -> 0 | F68: =SUM(F69:F79) -> 0 | G68: =SUM(G69:G79) -> 0 | H68: =SUM(H69:H79) -> 0 | I68: =SUM(I69:I79) -> 0 | ... AJ68: =SUM(AJ69:AJ79) -> 0
A69: NFCU Loan 1151 | AH69: =sum(B69:AG69) -> 0 | AI69: ='TOTALS&AVERAGES'!N69 | AJ69: =AI69-AH69 -> 0
A70: NFCU Credit Card 8743 | AH70: =sum(B70:AG70) -> 0 | AI70: ='TOTALS&AVERAGES'!N70 | AJ70: =AI70-AH70 -> 0
A71: Capital One Credit Card 1057 | AH71: =sum(B71:AG71) -> 0 | AI71: ='TOTALS&AVERAGES'!N71 | AJ71: =AI71-AH71 -> 0
A72: Blink Fitness Collections | AH72: =sum(B72:AG72) -> 0 | AI72: ='TOTALS&AVERAGES'!N72 | AJ72: =AI72-AH72 -> 0
A73: T-Mobile Phone Bill | AH73: =sum(B73:AG73) -> 0 | AI73: ='TOTALS&AVERAGES'!N73 | AJ73: =AI73-AH73 -> 0
A74: TD Bank Collections | AH74: =sum(B74:AG74) -> 0 | AI74: ='TOTALS&AVERAGES'!N74 | AJ74: =AI74-AH74 -> 0
A75: Safegaurd Operations Collections | AH75: =sum(B75:AG75) -> 0 | AI75: ='TOTALS&AVERAGES'!N75 | AJ75: =AI75-AH75 -> 0
A76: BMCC Loan 474.03 | AH76: =sum(B76:AG76) -> 0 | AI76: ='TOTALS&AVERAGES'!N76 | AJ76: =AI76-AH76 -> 0
A77: Han Personal Debt (Paid) | AH77: =sum(B77:AG77) -> 0 | AI77: ='TOTALS&AVERAGES'!N77 | AJ77: =AI77-AH77 -> 0
AH78: =sum(B78:AG78) -> 0 | AI78: ='TOTALS&AVERAGES'!N78 | AJ78: =AI78-AH78 -> 0
A79: Total Debt: 8,551.73 | AH79: =sum(B79:AG79) -> 0 | AI79: ='TOTALS&AVERAGES'!N79 | AJ79: =AI79-AH79 -> 0
A80: School | B80: =SUM(B81:B91) -> 0 | C80: =SUM(C81:C91) -> 0 | D80: =SUM(D81:D91) -> 0 | E80: =SUM(E81:E91) -> 0 | F80: =SUM(F81:F91) -> 0 | G80: =SUM(G81:G91) -> 0 | H80: =SUM(H81:H91) -> 0 | I80: =SUM(I81:I91) -> 0 | ... AJ80: =SUM(AJ81:AJ91) -> 0
A81: Tuition | AH81: =sum(AB81:AG81) -> 0 | AI81: ='TOTALS&AVERAGES'!N81 | AJ81: =AI81-AH81 -> 0
A82: Books | AH82: =sum(AB82:AG82) -> 0 | AI82: ='TOTALS&AVERAGES'!N82 | AJ82: =AI82-AH82 -> 0
AH83: =sum(AB83:AG83) -> 0 | AI83: ='TOTALS&AVERAGES'!N83 | AJ83: =AI83-AH83 -> 0
AH84: =sum(AB84:AG84) -> 0 | AI84: ='TOTALS&AVERAGES'!N84 | AJ84: =AI84-AH84 -> 0
AH85: =sum(AB85:AG85) -> 0 | AI85: ='TOTALS&AVERAGES'!N85 | AJ85: =AI85-AH85 -> 0
AH86: =sum(AB86:AG86) -> 0 | AI86: ='TOTALS&AVERAGES'!N86 | AJ86: =AI86-AH86 -> 0
AH87: =sum(AB87:AG87) -> 0 | AI87: ='TOTALS&AVERAGES'!N87 | AJ87: =AI87-AH87 -> 0
AH88: =sum(AB88:AG88) -> 0 | AI88: ='TOTALS&AVERAGES'!N88 | AJ88: =AI88-AH88 -> 0
AH89: =sum(AB89:AG89) -> 0 | AI89: ='TOTALS&AVERAGES'!N89 | AJ89: =AI89-AH89 -> 0
AH90: =sum(AB90:AG90) -> 0 | AI90: ='TOTALS&AVERAGES'!N90 | AJ90: =AI90-AH90 -> 0
AH91: =sum(AB91:AG91) -> 0 | AI91: ='TOTALS&AVERAGES'!N91 | AJ91: =AI91-AH91 -> 0
B92: =SUM(B93:B106) -> 0 | C92: =SUM(C93:C106) -> 0 | D92: =SUM(D93:D106) -> 0 | E92: =SUM(E93:E106) -> 0 | F92: =SUM(F93:F106) -> 0 | G92: =SUM(G93:G106) -> 0 | H92: =SUM(H93:H106) -> 0 | I92: =SUM(I93:I106) -> 0 | ... AJ92: =SUM(AJ93:AJ106) -> 0
AH93: =sum(AB93:AG93) -> 0 | AI93: ='TOTALS&AVERAGES'!N93 | AJ93: =AI93-AH93 -> 0
AH94: =sum(AB94:AG94) -> 0 | AI94: ='TOTALS&AVERAGES'!N94 | AJ94: =AI94-AH94 -> 0
B95: * | AH95: =sum(AB95:AG95) -> 0 | AI95: ='TOTALS&AVERAGES'!N95 | AJ95: =AI95-AH95 -> 0
AH96: =sum(AB96:AG96) -> 0 | AI96: ='TOTALS&AVERAGES'!N96 | AJ96: =AI96-AH96 -> 0
AH97: =sum(AB97:AG97) -> 0 | AI97: ='TOTALS&AVERAGES'!N97 | AJ97: =AI97-AH97 -> 0
AH98: =sum(AB98:AG98) -> 0 | AI98: ='TOTALS&AVERAGES'!N98 | AJ98: =AI98-AH98 -> 0
B99: * | AH99: =sum(AB99:AG99) -> 0 | AI99: ='TOTALS&AVERAGES'!N99 | AJ99: =AI99-AH99 -> 0
B100: * | AH100: =sum(AB100:AG100) -> 0 | AI100: ='TOTALS&AVERAGES'!N100 | AJ100: =AI100-AH100 -> 0
...

Sheet FEB
A1: FEBRUARY | B1: Monthly Regular Bills | C1: 46054 | D1: =C1+1 -> 46055 | E1: =D1+1 -> 46056 | F1: =E1+1 -> 46057 | G1: =F1+1 -> 46058 | H1: =G1+1 -> 46059 | I1: =H1+1 -> 46060 | J1: =I1+1 -> 46061 | K1: =J1+1 -> 46062 | ... AD1: =AC1+1 -> 46081 | AE1: TOTALS | AF1: SPENDING PLAN | AG1: DIFFERENCE
A2: INCOME
A3: =JAN!A3 -> Main Job | AE3: =sum(B3:AD3) -> 0 | AF3: ='TOTALS&AVERAGES'!N3 | AG3: =AF3-AE3 -> 0
A4: =JAN!A4 -> B Job | AE4: =sum(B4:AD4) -> 0 | AF4: ='TOTALS&AVERAGES'!N4 | AG4: =AF4-AE4 -> 0
A5: =JAN!A5 -> Bonuses | AE5: =sum(B5:AD5) -> 0 | AF5: ='TOTALS&AVERAGES'!N5 | AG5: =AF5-AE5 -> 0
A6: =JAN!A6 -> Gifts/Discounts | AE6: =sum(B6:AD6) -> 0 | AF6: ='TOTALS&AVERAGES'!N6 | AG6: =AF6-AE6 -> 0
A7: =JAN!A7 -> Reimbursement | AE7: =sum(B7:AD7) -> 0 | AF7: ='TOTALS&AVERAGES'!N7 | AG7: =AF7-AE7 -> 0
A8: =JAN!A8 -> Government Assistance | AE8: =sum(B8:AD8) -> 0 | AF8: ='TOTALS&AVERAGES'!N8 | AG8: =AF8-AE8 -> 0
A9: =JAN!A9 -> Side Hustles | AE9: =sum(B9:AD9) -> 0 | AF9: ='TOTALS&AVERAGES'!N9 | AG9: =AF9-AE9 -> 0
A10: =JAN!A10 -> Interest/Rewards | AE10: =sum(B10:AD10) -> 0 | AF10: ='TOTALS&AVERAGES'!N10 | AG10: =AF10-AE10 -> 0
A11: =JAN!A11 -> VA Benefits | AE11: =sum(B11:AD11) -> 0 | AF11: ='TOTALS&AVERAGES'!N11 | AG11: =AF11-AE11 -> 0
A12: =JAN!A12 -> Asset Cash Out | AE12: =sum(B12:AD12) -> 0 | AF12: ='TOTALS&AVERAGES'!N12 | AG12: =AF12-AE12 -> 0
A13: =JAN!A13 -> Fed Tax Refund | AE13: =sum(B13:AD13) -> 0 | AF13: ='TOTALS&AVERAGES'!N13 | AG13: =AF13-AE13 -> 0
A14: =JAN!A14 -> State Tax Refund | AE14: =sum(B14:AD14) -> 0 | AF14: ='TOTALS&AVERAGES'!N14 | AG14: =AF14-AE14 -> 0
A15: TOTAL INCOME BEFORE TAXES | B15: =SUM(C3:AE14) -> 0 | C15: =SUM(C3:C14) -> 0 | D15: =SUM(D3:D14) -> 0 | E15: =SUM(E3:E14) -> 0 | F15: =SUM(F3:F14) -> 0 | G15: =SUM(G3:G14) -> 0 | H15: =SUM(H3:H14) -> 0 | I15: =SUM(I3:I14) -> 0 | J15: =SUM(J3:J14) -> 0 | ... AG15: =SUM(AG3:AG14) -> 0
A16: EXPENSES BY D.A. CATEGORIES | B16: MONTHLY REGULAR BILLS
A17: 1 - SPIRITUAL | B17: =SUM(B18:B26) -> 0 | C17: =SUM(C18:C26) -> 0 | D17: =SUM(D18:D26) -> 0 | E17: =SUM(E18:E26) -> 0 | F17: =SUM(F18:F26) -> 0 | G17: =SUM(G18:G26) -> 0 | H17: =SUM(H18:H26) -> 0 | I17: =SUM(I18:I26) -> 0 | ... AG17: =SUM(AG18:AG26) -> 0
A18: =JAN!A18 -> Tithing/Church Donation | AE18: =sum(B18:AD18) -> 0 | AF18: ='TOTALS&AVERAGES'!N18 | AG18: =AF18-AE18 -> 0
A19: =JAN!A19 -> Books | AE19: =sum(B19:AD19) -> 0 | AF19: ='TOTALS&AVERAGES'!N19 | AG19: =AF19-AE19 -> 0
A20: =JAN!A20 -> Charity | AE20: =sum(B20:AD20) -> 0 | AF20: ='TOTALS&AVERAGES'!N20 | AG20: =AF20-AE20 -> 0
A21: =JAN!A21 -> Workshops | AE21: =sum(B21:AD21) -> 0 | AF21: ='TOTALS&AVERAGES'!N21 | AG21: =AF21-AE21 -> 0
A22: =JAN!A22 -> Generosity | AE22: =sum(B22:AD22) -> 0 | AF22: ='TOTALS&AVERAGES'!N22 | AG22: =AF22-AE22 -> 0
A23: =JAN!A23 -> Retreats / Seminars | AE23: =sum(B23:AD23) -> 0 | AF23: ='TOTALS&AVERAGES'!N23 | AG23: =AF23-AE23 -> 0
A24: =JAN!A24 -> 7TH TRADITION / FELLOWSHIP/ PRG | AE24: =sum(B24:AD24) -> 0 | AF24: ='TOTALS&AVERAGES'!N24 | AG24: =AF24-AE24 -> 0
A25: =JAN!A25 -> Conferences | AE25: =sum(B25:AD25) -> 0 | AF25: ='TOTALS&AVERAGES'!N25 | AG25: =AF25-AE25 -> 0
A26: =JAN!A26 -> Career Investment | AE26: =sum(B26:AD26) -> 0 | AF26: ='TOTALS&AVERAGES'!N26 | AG26: =AF26-AE26 -> 0
A27: =JAN!A27 -> Needs | B27: =SUM(B28:B43) -> 0 | C27: =SUM(C28:C43) -> 0 | D27: =SUM(D28:D43) -> 0 | E27: =SUM(E28:E43) -> 0 | F27: =SUM(F28:F43) -> 0 | G27: =SUM(G28:G43) -> 0 | H27: =SUM(H28:H43) -> 0 | I27: =SUM(I28:I43) -> 0 | ... AG27: =SUM(AG28:AG43) -> 0
A28: =JAN!A28 -> Groceries | AE28: =sum(B28:AD28) -> 0 | AF28: ='TOTALS&AVERAGES'!N28 | AG28: =AF28-AE28 -> 0
A29: =JAN!A29 -> Rent/Mortage | B29: * | AE29: =sum(B29:AD29) -> 0 | AF29: ='TOTALS&AVERAGES'!N29 | AG29: =AF29-AE29 -> 0
A30: =JAN!A30 -> Cell Phone | B30: * | AE30: =sum(B30:AD30) -> 0 | AF30: ='TOTALS&AVERAGES'!N30 | AG30: =AF30-AE30 -> 0
A31: =JAN!A31 -> Laundry/Cleaners | B31: * | AE31: =sum(B31:AD31) -> 0 | AF31: ='TOTALS&AVERAGES'!N31 | AG31: =AF31-AE31 -> 0
A32: =JAN!A32 -> Car Fuel | B32: * | AE32: =sum(B32:AD32) -> 0 | AF32: ='TOTALS&AVERAGES'!N32 | AG32: =AF32-AE32 -> 0
A33: =JAN!A33 -> Car Insurance | B33: * | AE33: =sum(B33:AD33) -> 0 | AF33: ='TOTALS&AVERAGES'!N33 | AG33: =AF33-AE33 -> 0
A34: =JAN!A34 -> Home Items | B34: * | AE34: =sum(B34:AD34) -> 0 | AF34: ='TOTALS&AVERAGES'!N34 | AG34: =AF34-AE34 -> 0
A35: =JAN!A35 -> Internet | AE35: =sum(B35:AD35) -> 0 | AF35: ='TOTALS&AVERAGES'!N35 | AG35: =AF35-AE35 -> 0
A36: =JAN!A36 -> Electricity | B36: * | AE36: =sum(B36:AD36) -> 0 | AF36: ='TOTALS&AVERAGES'!N36 | AG36: =AF36-AE36 -> 0
A37: =JAN!A37 -> Card Fees | AE37: =sum(B37:AD37) -> 0 | AF37: ='TOTALS&AVERAGES'!N37 | AG37: =AF37-AE37 -> 0
A38: =JAN!A38 -> Moving | AE38: =sum(B38:AD38) -> 0 | AF38: ='TOTALS&AVERAGES'!N38 | AG38: =AF38-AE38 -> 0
A39: =JAN!A39 -> Toiletries | B39: * | AE39: =sum(B39:AD39) -> 0 | AF39: ='TOTALS&AVERAGES'!N39 | AG39: =AF39-AE39 -> 0
A40: =JAN!A40 -> Storage | B40: * | AE40: =sum(B40:AD40) -> 0 | AF40: ='TOTALS&AVERAGES'!N40 | AG40: =AF40-AE40 -> 0
A41: =JAN!A41 -> MTA/Public Transportation | B41: * | AE41: =sum(B41:AD41) -> 0 | AF41: ='TOTALS&AVERAGES'!N41 | AG41: =AF41-AE41 -> 0
A42: =JAN!A42 -> Health Care | AE42: =sum(B42:AD42) -> 0 | AF42: ='TOTALS&AVERAGES'!N42 | AG42: =AF42-AE42 -> 0
A43: =JAN!A43 -> Repairs | AE43: =sum(B43:AD43) -> 0 | AF43: ='TOTALS&AVERAGES'!N43 | AG43: =AF43-AE43 -> 0
A44: =JAN!A44 -> Wants | B44: =SUM(B45:B52) -> 0 | C44: =SUM(C45:C52) -> 0 | D44: =SUM(D45:D52) -> 0 | E44: =SUM(E45:E52) -> 0 | F44: =SUM(F45:F52) -> 0 | G44: =SUM(G45:G52) -> 0 | H44: =SUM(H45:H52) -> 0 | I44: =SUM(I45:I52) -> 0 | ... AG44: =SUM(AG45:AG52) -> 0
A45: =JAN!A45 -> Clothes | AE45: =sum(B45:AD45) -> 0 | AF45: ='TOTALS&AVERAGES'!N45 | AG45: =AF45-AE45 -> 0
A46: =JAN!A46 -> Haircuts | AE46: =sum(B46:AD46) -> 0 | AF46: ='TOTALS&AVERAGES'!N46 | AG46: =AF46-AE46 -> 0
A47: =JAN!A47 -> Dining Out/Take out/Events | AE47: =sum(B47:AD47) -> 0 | AF47: ='TOTALS&AVERAGES'!N47 | AG47: =AF47-AE47 -> 0
A48: =JAN!A48 -> Gym Membership | AE48: =sum(B48:AD48) -> 0 | AF48: ='TOTALS&AVERAGES'!N48 | AG48: =AF48-AE48 -> 0
A49: =JAN!A49 -> Subscriptions Zoom/Paramount/Club Free/News Subsription | AE49: =sum(B49:AD49) -> 0 | AF49: ='TOTALS&AVERAGES'!N49 | AG49: =AF49-AE49 -> 0
A50: =JAN!A50 -> Snacks | AE50: =sum(B50:AD50) -> 0 | AF50: ='TOTALS&AVERAGES'!N50 | AG50: =AF50-AE50 -> 0
A51: =JAN!A51 -> Vacations/Trip to see Brother Bryant/Trip to NM/Trip to San Antonio | AE51: =sum(B51:AD51) -> 0 | AF51: ='TOTALS&AVERAGES'!N51 | AG51: =AF51-AE51 -> 0
A52: =JAN!A52 -> Other/Misc | AE52: =sum(B52:AD52) -> 0 | AF52: ='TOTALS&AVERAGES'!N52 | AG52: =AF52-AE52 -> 0
A53: =JAN!A53 -> Savings | B53: =SUM(B54:B67) -> 0 | C53: =SUM(C54:C67) -> 0 | D53: =SUM(D54:D67) -> 0 | E53: =SUM(E54:E67) -> 0 | F53: =SUM(F54:F67) -> 0 | G53: =SUM(G54:G67) -> 0 | H53: =SUM(H54:H67) -> 0 | I53: =SUM(I54:I67) -> 0 | ... AG53: =SUM(AG54:AG67) -> 0
A54: =JAN!A54 -> High yield Savings | B54: * | AE54: =sum(B54:AD54) -> 0 | AF54: ='TOTALS&AVERAGES'!N54 | AG54: =AF54-AE54 -> 0
A55: =JAN!A55 -> Emergency Fund | B55: * | AE55: =sum(B55:AD55) -> 0 | AF55: ='TOTALS&AVERAGES'!N55 | AG55: =AF55-AE55 -> 0
A56: =JAN!A56 -> Stocks/Index Fund | B56: * | AE56: =sum(B56:AD56) -> 0 | AF56: ='TOTALS&AVERAGES'!N56 | AG56: =AF56-AE56 -> 0
A57: =JAN!A57 -> Real Estate | AE57: =sum(B57:AD57) -> 0 | AF57: ='TOTALS&AVERAGES'!N57 | AG57: =AF57-AE57 -> 0
A58: =JAN!A58 -> Extra Debt Payment | AE58: =sum(B58:AD58) -> 0 | AF58: ='TOTALS&AVERAGES'!N58 | AG58: =AF58-AE58 -> 0
A59: =JAN!A59 -> Gold | AE59: =sum(B59:AD59) -> 0 | AF59: ='TOTALS&AVERAGES'!N59 | AG59: =AF59-AE59 -> 0
A60: =JAN!A60 -> Retirement/Roth IRA | AE60: =sum(B60:AD60) -> 0 | AF60: ='TOTALS&AVERAGES'!N60 | AG60: =AF60-AE60 -> 0
A61: =JAN!A61 -> Annuities | AE61: =sum(B61:AD61) -> 0 | AF61: ='TOTALS&AVERAGES'!N61 | AG61: =AF61-AE61 -> 0
A62: =JAN!A62 -> Life Insurance | AE62: =sum(B62:AD62) -> 0 | AF62: ='TOTALS&AVERAGES'!N62 | AG62: =AF62-AE62 -> 0
A63: =JAN!A63 -> Watch | AE63: =sum(B63:AD63) -> 0 | AF63: ='TOTALS&AVERAGES'!N63 | AG63: =AF63-AE63 -> 0
A64: =JAN!A64 -> CD | AE64: =sum(B64:AD64) -> 0 | AF64: ='TOTALS&AVERAGES'!N64 | AG64: =AF64-AE64 -> 0
A65: =JAN!A65 -> Taxes Savings | AE65: =sum(B65:AD65) -> 0 | AF65: ='TOTALS&AVERAGES'!N65 | AG65: =AF65-AE65 -> 0
A66: =JAN!A66 -> HSA | AE66: =sum(B66:AD66) -> 0 | AF66: ='TOTALS&AVERAGES'!N66 | AG66: =AF66-AE66 -> 0
A67: =JAN!A67 -> - | AE67: =sum(B67:AD67) -> 0 | AF67: ='TOTALS&AVERAGES'!N67 | AG67: =AF67-AE67 -> 0
A68: =JAN!A68 -> Debts | B68: =SUM(B69:B79) -> 0 | C68: =SUM(C69:C79) -> 0 | D68: =SUM(D69:D79) -> 0 | E68: =SUM(E69:E79) -> 0 | F68: =SUM(F69:F79) -> 0 | G68: =SUM(G69:G79) -> 0 | H68: =SUM(H69:H79) -> 0 | I68: =SUM(I69:I79) -> 0 | ... AG68: =SUM(AG69:AG79) -> 0
A69: =JAN!A69 -> NFCU Loan 1151 | AE69: =sum(B69:AD69) -> 0 | AF69: ='TOTALS&AVERAGES'!N69 | AG69: =AF69-AE69 -> 0
A70: =JAN!A70 -> NFCU Credit Card 8743 | AE70: =sum(B70:AD70) -> 0 | AF70: ='TOTALS&AVERAGES'!N70 | AG70: =AF70-AE70 -> 0
A71: =JAN!A71 -> Capital One Credit Card 1057 | AE71: =sum(B71:AD71) -> 0 | AF71: ='TOTALS&AVERAGES'!N71 | AG71: =AF71-AE71 -> 0
A72: =JAN!A72 -> Blink Fitness Collections | AE72: =sum(B72:AD72) -> 0 | AF72: ='TOTALS&AVERAGES'!N72 | AG72: =AF72-AE72 -> 0
A73: =JAN!A73 -> T-Mobile Phone Bill | AE73: =sum(B73:AD73) -> 0 | AF73: ='TOTALS&AVERAGES'!N73 | AG73: =AF73-AE73 -> 0
A74: =JAN!A74 -> TD Bank Collections | AE74: =sum(B74:AD74) -> 0 | AF74: ='TOTALS&AVERAGES'!N74 | AG74: =AF74-AE74 -> 0
A75: =JAN!A75 -> Safegaurd Operations Collections | AE75: =sum(B75:AD75) -> 0 | AF75: ='TOTALS&AVERAGES'!N75 | AG75: =AF75-AE75 -> 0
A76: =JAN!A76 -> BMCC Loan 474.03 | AE76: =sum(B76:AD76) -> 0 | AF76: ='TOTALS&AVERAGES'!N76 | AG76: =AF76-AE76 -> 0
A77: =JAN!A77 -> Han Personal Debt (Paid) | AE77: =sum(B77:AD77) -> 0 | AF77: ='TOTALS&AVERAGES'!N77 | AG77: =AF77-AE77 -> 0
A78: =JAN!A78 | AE78: =sum(B78:AD78) -> 0 | AF78: ='TOTALS&AVERAGES'!N78 | AG78: =AF78-AE78 -> 0
A79: =JAN!A79 -> Total Debt: 8,551.73 | AE79: =sum(B79:AD79) -> 0 | AF79: ='TOTALS&AVERAGES'!N79 | AG79: =AF79-AE79 -> 0
A80: =JAN!A80 -> School | B80: =SUM(B81:B91) -> 0 | C80: =SUM(C81:C91) -> 0 | D80: =SUM(D81:D91) -> 0 | E80: =SUM(E81:E91) -> 0 | F80: =SUM(F81:F91) -> 0 | G80: =SUM(G81:G91) -> 0 | H80: =SUM(H81:H91) -> 0 | I80: =SUM(I81:I91) -> 0 | ... AG80: =SUM(AG81:AG91) -> 0
A81: =JAN!A81 -> Tuition | AE81: =sum(B81:AD81) -> 0 | AF81: ='TOTALS&AVERAGES'!N81 | AG81: =AF81-AE81 -> 0
A82: =JAN!A82 -> Books | AE82: =sum(B82:AD82) -> 0 | AF82: ='TOTALS&AVERAGES'!N82 | AG82: =AF82-AE82 -> 0
A83: =JAN!A83 | AE83: =sum(B83:AD83) -> 0 | AF83: ='TOTALS&AVERAGES'!N83 | AG83: =AF83-AE83 -> 0
A84: =JAN!A84 | AE84: =sum(B84:AD84) -> 0 | AF84: ='TOTALS&AVERAGES'!N84 | AG84: =AF84-AE84 -> 0
A85: =JAN!A85 | AE85: =sum(B85:AD85) -> 0 | AF85: ='TOTALS&AVERAGES'!N85 | AG85: =AF85-AE85 -> 0
A86: =JAN!A86 | AE86: =sum(B86:AD86) -> 0 | AF86: ='TOTALS&AVERAGES'!N86 | AG86: =AF86-AE86 -> 0
A87: =JAN!A87 | AE87: =sum(B87:AD87) -> 0 | AF87: ='TOTALS&AVERAGES'!N87 | AG87: =AF87-AE87 -> 0
A88: =JAN!A88 | AE88: =sum(B88:AD88) -> 0 | AF88: ='TOTALS&AVERAGES'!N88 | AG88: =AF88-AE88 -> 0
A89: =JAN!A89 | AE89: =sum(B89:AD89) -> 0 | AF89: ='TOTALS&AVERAGES'!N89 | AG89: =AF89-AE89 -> 0
A90: =JAN!A90 | AE90: =sum(B90:AD90) -> 0 | AF90: ='TOTALS&AVERAGES'!N90 | AG90: =AF90-AE90 -> 0
A91: =JAN!A91 | AE91: =sum(B91:AD91) -> 0 | AF91: ='TOTALS&AVERAGES'!N91 | AG91: =AF91-AE91 -> 0
A92: =JAN!A92 | B92: =SUM(B93:B106) -> 0 | C92: =SUM(C93:C106) -> 0 | D92: =SUM(D93:D106) -> 0 | E92: =SUM(E93:E106) -> 0 | F92: =SUM(F93:F106) -> 0 | G92: =SUM(G93:G106) -> 0 | H92: =SUM(H93:H106) -> 0 | I92: =SUM(I93:I106) -> 0 | ... AG92: =SUM(AG93:AG106) -> 0
A93: =JAN!A93 | AE93: =sum(B93:AD93) -> 0 | AF93: ='TOTALS&AVERAGES'!N93 | AG93: =AF93-AE93 -> 0
A94: =JAN!A94 | AE94: =sum(B94:AD94) -> 0 | AF94: ='TOTALS&AVERAGES'!N94 | AG94: =AF94-AE94 -> 0
A95: =JAN!A95 | B95: * | AE95: =sum(B95:AD95) -> 0 | AF95: ='TOTALS&AVERAGES'!N95 | AG95: =AF95-AE95 -> 0
A96: =JAN!A96 | AE96: =sum(B96:AD96) -> 0 | AF96: ='TOTALS&AVERAGES'!N96 | AG96: =AF96-AE96 -> 0
A97: =JAN!A97 | AE97: =sum(B97:AD97) -> 0 | AF97: ='TOTALS&AVERAGES'!N97 | AG97: =AF97-AE97 -> 0
A98: =JAN!A98 | AE98: =sum(B98:AD98) -> 0 | AF98: ='TOTALS&AVERAGES'!N98 | AG98: =AF98-AE98 -> 0
A99: =JAN!A99 | B99: * | AE99: =sum(B99:AD99) -> 0 | AF99: ='TOTALS&AVERAGES'!N99 | AG99: =AF99-AE99 -> 0
A100: =JAN!A100 | B100: * | AE100: =sum(B100:AD100) -> 0 | AF100: ='TOTALS&AVERAGES'!N100 | AG100: =AF100-AE100 -> 0
...

Sheet MAR
A1: MARCH | B1: Monthly Regular Bills | C1: 46082 | D1: =C1+1 -> 46083 | E1: =D1+1 -> 46084 | F1: =E1+1 -> 46085 | G1: =F1+1 -> 46086 | H1: =G1+1 -> 46087 | I1: =H1+1 -> 46088 | J1: =I1+1 -> 46089 | K1: =J1+1 -> 46090 | ... AG1: =AF1+1 -> 46112 | AH1: TOTALS | AI1: SPENDING PLAN | AJ1: DIFFERENCE
A2: INCOME
A3: =JAN!A3 -> Main Job | AH3: =sum(B3:AF3) -> 0 | AI3: ='TOTALS&AVERAGES'!N3 | AJ3: =AI3-AH3 -> 0
A4: =JAN!A4 -> B Job | AH4: =sum(B4:AF4) -> 0 | AI4: ='TOTALS&AVERAGES'!N4 | AJ4: =AI4-AH4 -> 0
A5: =JAN!A5 -> Bonuses | AH5: =sum(B5:AF5) -> 0 | AI5: ='TOTALS&AVERAGES'!N5 | AJ5: =AI5-AH5 -> 0
A6: =JAN!A6 -> Gifts/Discounts | AH6: =sum(B6:AF6) -> 0 | AI6: ='TOTALS&AVERAGES'!N6 | AJ6: =AI6-AH6 -> 0
A7: =JAN!A7 -> Reimbursement | AH7: =sum(B7:AF7) -> 0 | AI7: ='TOTALS&AVERAGES'!N7 | AJ7: =AI7-AH7 -> 0
A8: =JAN!A8 -> Government Assistance | AH8: =sum(B8:AF8) -> 0 | AI8: ='TOTALS&AVERAGES'!N8 | AJ8: =AI8-AH8 -> 0
A9: =JAN!A9 -> Side Hustles | AH9: =sum(B9:AF9) -> 0 | AI9: ='TOTALS&AVERAGES'!N9 | AJ9: =AI9-AH9 -> 0
A10: =JAN!A10 -> Interest/Rewards | AH10: =sum(B10:AG10) -> 0 | AI10: ='TOTALS&AVERAGES'!N10 | AJ10: =AI10-AH10 -> 0
A11: =JAN!A11 -> VA Benefits | AH11: =sum(B11:AF11) -> 0 | AI11: ='TOTALS&AVERAGES'!N11 | AJ11: =AI11-AH11 -> 0
A12: =JAN!A12 -> Asset Cash Out | AH12: =sum(B12:AF12) -> 0 | AI12: ='TOTALS&AVERAGES'!N12 | AJ12: =AI12-AH12 -> 0
A13: =JAN!A13 -> Fed Tax Refund | AH13: =sum(B13:AF13) -> 0 | AI13: ='TOTALS&AVERAGES'!N13 | AJ13: =AI13-AH13 -> 0
A14: =JAN!A14 -> State Tax Refund | AH14: =sum(B14:AF14) -> 0 | AI14: ='TOTALS&AVERAGES'!N14 | AJ14: =AI14-AH14 -> 0
A15: TOTAL INCOME BEFORE TAXES | B15: =SUM(C3:AH14) -> 0 | C15: =SUM(C3:C14) -> 0 | D15: =SUM(D3:D14) -> 0 | E15: =SUM(E3:E14) -> 0 | F15: =SUM(F3:F14) -> 0 | G15: =SUM(G3:G14) -> 0 | H15: =SUM(H3:H14) -> 0 | I15: =SUM(I3:I14) -> 0 | J15: =SUM(J3:J14) -> 0 | ... AJ15: =SUM(AJ3:AJ14) -> 0
A16: EXPENSES BY D.A. CATEGORIES | B16: MONTHLY REGULAR BILLS
A17: 1 - SPIRITUAL | B17: =SUM(B18:B26) -> 0 | C17: =SUM(C18:C26) -> 0 | D17: =SUM(D18:D26) -> 0 | E17: =SUM(E18:E26) -> 0 | F17: =SUM(F18:F26) -> 0 | G17: =SUM(G18:G26) -> 0 | H17: =SUM(H18:H26) -> 0 | I17: =SUM(I18:I26) -> 0 | ... AJ17: =SUM(AJ18:AJ26) -> 0
A18: =JAN!A18 -> Tithing/Church Donation | AH18: =sum(B18:AF18) -> 0 | AI18: ='TOTALS&AVERAGES'!N18 | AJ18: =AI18-AH18 -> 0
A19: =JAN!A19 -> Books | AH19: =sum(B19:AF19) -> 0 | AI19: ='TOTALS&AVERAGES'!N19 | AJ19: =AI19-AH19 -> 0
A20: =JAN!A20 -> Charity | AH20: =sum(B20:AF20) -> 0 | AI20: ='TOTALS&AVERAGES'!N20 | AJ20: =AI20-AH20 -> 0
A21: =JAN!A21 -> Workshops | AH21: =sum(B21:AF21) -> 0 | AI21: ='TOTALS&AVERAGES'!N21 | AJ21: =AI21-AH21 -> 0
A22: =JAN!A22 -> Generosity | AH22: =sum(B22:AF22) -> 0 | AI22: ='TOTALS&AVERAGES'!N22 | AJ22: =AI22-AH22 -> 0
A23: =JAN!A23 -> Retreats / Seminars | AH23: =sum(B23:AF23) -> 0 | AI23: ='TOTALS&AVERAGES'!N23 | AJ23: =AI23-AH23 -> 0
A24: =JAN!A24 -> 7TH TRADITION / FELLOWSHIP/ PRG | AH24: =sum(B24:AF24) -> 0 | AI24: ='TOTALS&AVERAGES'!N24 | AJ24: =AI24-AH24 -> 0
A25: =JAN!A25 -> Conferences | AH25: =sum(B25:AF25) -> 0 | AI25: ='TOTALS&AVERAGES'!N25 | AJ25: =AI25-AH25 -> 0
A26: =JAN!A26 -> Career Investment | AH26: =sum(B26:AF26) -> 0 | AI26: ='TOTALS&AVERAGES'!N26 | AJ26: =AI26-AH26 -> 0
A27: =JAN!A27 -> Needs | B27: =SUM(B28:B43) -> 0 | C27: =SUM(C28:C43) -> 0 | D27: =SUM(D28:D43) -> 0 | E27: =SUM(E28:E43) -> 0 | F27: =SUM(F28:F43) -> 0 | G27: =SUM(G28:G43) -> 0 | H27: =SUM(H28:H43) -> 0 | I27: =SUM(I28:I43) -> 0 | ... AJ27: =SUM(AJ28:AJ43) -> 0
A28: =JAN!A28 -> Groceries | AH28: =sum(B28:AF28) -> 0 | AI28: ='TOTALS&AVERAGES'!N28 | AJ28: =AI28-AH28 -> 0
A29: =JAN!A29 -> Rent/Mortage | B29: * | AH29: =sum(B29:AF29) -> 0 | AI29: ='TOTALS&AVERAGES'!N29 | AJ29: =AI29-AH29 -> 0
A30: =JAN!A30 -> Cell Phone | B30: * | AH30: =sum(B30:AF30) -> 0 | AI30: ='TOTALS&AVERAGES'!N30 | AJ30: =AI30-AH30 -> 0
A31: =JAN!A31 -> Laundry/Cleaners | B31: * | AH31: =sum(B31:AF31) -> 0 | AI31: ='TOTALS&AVERAGES'!N31 | AJ31: =AI31-AH31 -> 0
A32: =JAN!A32 -> Car Fuel | B32: * | AH32: =sum(B32:AF32) -> 0 | AI32: ='TOTALS&AVERAGES'!N32 | AJ32: =AI32-AH32 -> 0
A33: =JAN!A33 -> Car Insurance | B33: * | AH33: =sum(B33:AF33) -> 0 | AI33: ='TOTALS&AVERAGES'!N33 | AJ33: =AI33-AH33 -> 0
A34: =JAN!A34 -> Home Items | B34: * | AH34: =sum(B34:AF34) -> 0 | AI34: ='TOTALS&AVERAGES'!N34 | AJ34: =AI34-AH34 -> 0
A35: =JAN!A35 -> Internet | AH35: =sum(B35:AF35) -> 0 | AI35: ='TOTALS&AVERAGES'!N35 | AJ35: =AI35-AH35 -> 0
A36: =JAN!A36 -> Electricity | B36: * | AH36: =sum(B36:AF36) -> 0 | AI36: ='TOTALS&AVERAGES'!N36 | AJ36: =AI36-AH36 -> 0
A37: =JAN!A37 -> Card Fees | AH37: =sum(B37:AF37) -> 0 | AI37: ='TOTALS&AVERAGES'!N37 | AJ37: =AI37-AH37 -> 0
A38: =JAN!A38 -> Moving | AH38: =sum(B38:AF38) -> 0 | AI38: ='TOTALS&AVERAGES'!N38 | AJ38: =AI38-AH38 -> 0
A39: =JAN!A39 -> Toiletries | B39: * | AH39: =sum(B39:AF39) -> 0 | AI39: ='TOTALS&AVERAGES'!N39 | AJ39: =AI39-AH39 -> 0
A40: =JAN!A40 -> Storage | B40: * | AH40: =sum(B40:AF40) -> 0 | AI40: ='TOTALS&AVERAGES'!N40 | AJ40: =AI40-AH40 -> 0
A41: =JAN!A41 -> MTA/Public Transportation | B41: * | AH41: =sum(B41:AF41) -> 0 | AI41: ='TOTALS&AVERAGES'!N41 | AJ41: =AI41-AH41 -> 0
A42: =JAN!A42 -> Health Care | AH42: =sum(B42:AF42) -> 0 | AI42: ='TOTALS&AVERAGES'!N42 | AJ42: =AI42-AH42 -> 0
A43: =JAN!A43 -> Repairs | AH43: =sum(B43:AF43) -> 0 | AI43: ='TOTALS&AVERAGES'!N43 | AJ43: =AI43-AH43 -> 0
A44: =JAN!A44 -> Wants | B44: =SUM(B45:B52) -> 0 | C44: =SUM(C45:C52) -> 0 | D44: =SUM(D45:D52) -> 0 | E44: =SUM(E45:E52) -> 0 | F44: =SUM(F45:F52) -> 0 | G44: =SUM(G45:G52) -> 0 | H44: =SUM(H45:H52) -> 0 | I44: =SUM(I45:I52) -> 0 | ... AJ44: =SUM(AJ45:AJ52) -> 0
A45: =JAN!A45 -> Clothes | AH45: =sum(B45:AF45) -> 0 | AI45: ='TOTALS&AVERAGES'!N45 | AJ45: =AI45-AH45 -> 0
A46: =JAN!A46 -> Haircuts | AH46: =sum(B46:AF46) -> 0 | AI46: ='TOTALS&AVERAGES'!N46 | AJ46: =AI46-AH46 -> 0
A47: =JAN!A47 -> Dining Out/Take out/Events | AH47: =sum(B47:AF47) -> 0 | AI47: ='TOTALS&AVERAGES'!N47 | AJ47: =AI47-AH47 -> 0
A48: =JAN!A48 -> Gym Membership | AH48: =sum(B48:AF48) -> 0 | AI48: ='TOTALS&AVERAGES'!N48 | AJ48: =AI48-AH48 -> 0
A49: =JAN!A49 -> Subscriptions Zoom/Paramount/Club Free/News Subsription | AH49: =sum(B49:AG49) -> 0 | AI49: ='TOTALS&AVERAGES'!N49 | AJ49: =AI49-AH49 -> 0
A50: =JAN!A50 -> Snacks | AH50: =sum(B50:AF50) -> 0 | AI50: ='TOTALS&AVERAGES'!N50 | AJ50: =AI50-AH50 -> 0
A51: =JAN!A51 -> Vacations/Trip to see Brother Bryant/Trip to NM/Trip to San Antonio | AH51: =sum(B51:AF51) -> 0 | AI51: ='TOTALS&AVERAGES'!N51 | AJ51: =AI51-AH51 -> 0
A52: =JAN!A52 -> Other/Misc | AH52: =sum(B52:AF52) -> 0 | AI52: ='TOTALS&AVERAGES'!N52 | AJ52: =AI52-AH52 -> 0
A53: =JAN!A53 -> Savings | B53: =SUM(B54:B67) -> 0 | C53: =SUM(C54:C67) -> 0 | D53: =SUM(D54:D67) -> 0 | E53: =SUM(E54:E67) -> 0 | F53: =SUM(F54:F67) -> 0 | G53: =SUM(G54:G67) -> 0 | H53: =SUM(H54:H67) -> 0 | I53: =SUM(I54:I67) -> 0 | ... AJ53: =SUM(AJ54:AJ67) -> -235.16
A54: =JAN!A54 -> High yield Savings | B54: * | AG54: 235.16 | AH54: =sum(B54:AG54) -> 235.16 | AI54: ='TOTALS&AVERAGES'!N54 | AJ54: =AI54-AH54 -> -235.16
A55: =JAN!A55 -> Emergency Fund | B55: * | AH55: =sum(B55:AF55) -> 0 | AI55: ='TOTALS&AVERAGES'!N55 | AJ55: =AI55-AH55 -> 0
A56: =JAN!A56 -> Stocks/Index Fund | B56: * | AH56: =sum(B56:AF56) -> 0 | AI56: ='TOTALS&AVERAGES'!N56 | AJ56: =AI56-AH56 -> 0
A57: =JAN!A57 -> Real Estate | AH57: =sum(B57:AF57) -> 0 | AI57: ='TOTALS&AVERAGES'!N57 | AJ57: =AI57-AH57 -> 0
A58: =JAN!A58 -> Extra Debt Payment | AH58: =sum(B58:AF58) -> 0 | AI58: ='TOTALS&AVERAGES'!N58 | AJ58: =AI58-AH58 -> 0
A59: =JAN!A59 -> Gold | AH59: =sum(B59:AF59) -> 0 | AI59: ='TOTALS&AVERAGES'!N59 | AJ59: =AI59-AH59 -> 0
A60: =JAN!A60 -> Retirement/Roth IRA | AH60: =sum(B60:AF60) -> 0 | AI60: ='TOTALS&AVERAGES'!N60 | AJ60: =AI60-AH60 -> 0
A61: =JAN!A61 -> Annuities | AH61: =sum(B61:AF61) -> 0 | AI61: ='TOTALS&AVERAGES'!N61 | AJ61: =AI61-AH61 -> 0
A62: =JAN!A62 -> Life Insurance | AH62: =sum(B62:AF62) -> 0 | AI62: ='TOTALS&AVERAGES'!N62 | AJ62: =AI62-AH62 -> 0
A63: =JAN!A63 -> Watch | AH63: =sum(B63:AF63) -> 0 | AI63: ='TOTALS&AVERAGES'!N63 | AJ63: =AI63-AH63 -> 0
A64: =JAN!A64 -> CD | AH64: =sum(B64:AF64) -> 0 | AI64: ='TOTALS&AVERAGES'!N64 | AJ64: =AI64-AH64 -> 0
A65: =JAN!A65 -> Taxes Savings | AH65: =sum(B65:AF65) -> 0 | AI65: ='TOTALS&AVERAGES'!N65 | AJ65: =AI65-AH65 -> 0
A66: =JAN!A66 -> HSA | AH66: =sum(B66:AF66) -> 0 | AI66: ='TOTALS&AVERAGES'!N66 | AJ66: =AI66-AH66 -> 0
A67: =JAN!A67 -> - | AH67: =sum(B67:AF67) -> 0 | AI67: ='TOTALS&AVERAGES'!N67 | AJ67: =AI67-AH67 -> 0
A68: =JAN!A68 -> Debts | B68: =SUM(B69:B79) -> 0 | C68: =SUM(C69:C79) -> 0 | D68: =SUM(D69:D79) -> 0 | E68: =SUM(E69:E79) -> 0 | F68: =SUM(F69:F79) -> 0 | G68: =SUM(G69:G79) -> 0 | H68: =SUM(H69:H79) -> 0 | I68: =SUM(I69:I79) -> 0 | ... AJ68: =SUM(AJ69:AJ79) -> 0
A69: =JAN!A69 -> NFCU Loan 1151 | AH69: =sum(B69:AF69) -> 0 | AI69: ='TOTALS&AVERAGES'!N69 | AJ69: =AI69-AH69 -> 0
A70: =JAN!A70 -> NFCU Credit Card 8743 | AH70: =sum(B70:AF70) -> 0 | AI70: ='TOTALS&AVERAGES'!N70 | AJ70: =AI70-AH70 -> 0
A71: =JAN!A71 -> Capital One Credit Card 1057 | AH71: =sum(B71:AF71) -> 0 | AI71: ='TOTALS&AVERAGES'!N71 | AJ71: =AI71-AH71 -> 0
A72: =JAN!A72 -> Blink Fitness Collections | AH72: =sum(B72:AF72) -> 0 | AI72: ='TOTALS&AVERAGES'!N72 | AJ72: =AI72-AH72 -> 0
A73: =JAN!A73 -> T-Mobile Phone Bill | AH73: =sum(B73:AF73) -> 0 | AI73: ='TOTALS&AVERAGES'!N73 | AJ73: =AI73-AH73 -> 0
A74: =JAN!A74 -> TD Bank Collections | AH74: =sum(B74:AF74) -> 0 | AI74: ='TOTALS&AVERAGES'!N74 | AJ74: =AI74-AH74 -> 0
A75: =JAN!A75 -> Safegaurd Operations Collections | AH75: =sum(B75:AF75) -> 0 | AI75: ='TOTALS&AVERAGES'!N75 | AJ75: =AI75-AH75 -> 0
A76: =JAN!A76 -> BMCC Loan 474.03 | AH76: =sum(B76:AF76) -> 0 | AI76: ='TOTALS&AVERAGES'!N76 | AJ76: =AI76-AH76 -> 0
A77: =JAN!A77 -> Han Personal Debt (Paid) | AH77: =sum(B77:AF77) -> 0 | AI77: ='TOTALS&AVERAGES'!N77 | AJ77: =AI77-AH77 -> 0
A78: =JAN!A78 | AH78: =sum(B78:AF78) -> 0 | AI78: ='TOTALS&AVERAGES'!N78 | AJ78: =AI78-AH78 -> 0
A79: =JAN!A79 -> Total Debt: 8,551.73 | AH79: =sum(B79:AF79) -> 0 | AI79: ='TOTALS&AVERAGES'!N79 | AJ79: =AI79-AH79 -> 0
A80: =JAN!A80 -> School | B80: =SUM(B81:B91) -> 0 | C80: =SUM(C81:C91) -> 0 | D80: =SUM(D81:D91) -> 0 | E80: =SUM(E81:E91) -> 0 | F80: =SUM(F81:F91) -> 0 | G80: =SUM(G81:G91) -> 0 | H80: =SUM(H81:H91) -> 0 | I80: =SUM(I81:I91) -> 0 | ... AJ80: =SUM(AJ81:AJ91) -> 0
A81: =JAN!A81 -> Tuition | AH81: =sum(B81:AF81) -> 0 | AI81: ='TOTALS&AVERAGES'!N81 | AJ81: =AI81-AH81 -> 0
A82: =JAN!A82 -> Books | AH82: =sum(B82:AF82) -> 0 | AI82: ='TOTALS&AVERAGES'!N82 | AJ82: =AI82-AH82 -> 0
A83: =JAN!A83 | AH83: =sum(B83:AF83) -> 0 | AI83: ='TOTALS&AVERAGES'!N83 | AJ83: =AI83-AH83 -> 0
A84: =JAN!A84 | AH84: =sum(B84:AF84) -> 0 | AI84: ='TOTALS&AVERAGES'!N84 | AJ84: =AI84-AH84 -> 0
A85: =JAN!A85 | AH85: =sum(B85:AF85) -> 0 | AI85: ='TOTALS&AVERAGES'!N85 | AJ85: =AI85-AH85 -> 0
A86: =JAN!A86 | AH86: =sum(B86:AF86) -> 0 | AI86: ='TOTALS&AVERAGES'!N86 | AJ86: =AI86-AH86 -> 0
A87: =JAN!A87 | AH87: =sum(B87:AF87) -> 0 | AI87: ='TOTALS&AVERAGES'!N87 | AJ87: =AI87-AH87 -> 0
A88: =JAN!A88 | AH88: =sum(B88:AF88) -> 0 | AI88: ='TOTALS&AVERAGES'!N88 | AJ88: =AI88-AH88 -> 0
A89: =JAN!A89 | AH89: =sum(B89:AF89) -> 0 | AI89: ='TOTALS&AVERAGES'!N89 | AJ89: =AI89-AH89 -> 0
A90: =JAN!A90 | AH90: =sum(B90:AF90) -> 0 | AI90: ='TOTALS&AVERAGES'!N90 | AJ90: =AI90-AH90 -> 0
A91: =JAN!A91 | AH91: =sum(B91:AF91) -> 0 | AI91: ='TOTALS&AVERAGES'!N91 | AJ91: =AI91-AH91 -> 0
A92: =JAN!A92 | B92: =SUM(B93:B106) -> 0 | C92: =SUM(C93:C106) -> 0 | D92: =SUM(D93:D106) -> 0 | E92: =SUM(E93:E106) -> 0 | F92: =SUM(F93:F106) -> 0 | G92: =SUM(G93:G106) -> 0 | H92: =SUM(H93:H106) -> 0 | I92: =SUM(I93:I106) -> 0 | ... AJ92: =SUM(AJ93:AJ106) -> 0
A93: =JAN!A93 | AH93: =sum(B93:AF93) -> 0 | AI93: ='TOTALS&AVERAGES'!N93 | AJ93: =AI93-AH93 -> 0
A94: =JAN!A94 | AH94: =sum(B94:AF94) -> 0 | AI94: ='TOTALS&AVERAGES'!N94 | AJ94: =AI94-AH94 -> 0
A95: =JAN!A95 | B95: * | AH95: =sum(B95:AF95) -> 0 | AI95: ='TOTALS&AVERAGES'!N95 | AJ95: =AI95-AH95 -> 0
A96: =JAN!A96 | AH96: =sum(B96:AF96) -> 0 | AI96: ='TOTALS&AVERAGES'!N96 | AJ96: =AI96-AH96 -> 0
A97: =JAN!A97 | AH97: =sum(B97:AF97) -> 0 | AI97: ='TOTALS&AVERAGES'!N97 | AJ97: =AI97-AH97 -> 0
A98: =JAN!A98 | AH98: =sum(B98:AF98) -> 0 | AI98: ='TOTALS&AVERAGES'!N98 | AJ98: =AI98-AH98 -> 0
A99: =JAN!A99 | B99: * | AH99: =sum(B99:AF99) -> 0 | AI99: ='TOTALS&AVERAGES'!N99 | AJ99: =AI99-AH99 -> 0
A100: =JAN!A100 | B100: * | AH100: =sum(B100:AF100) -> 0 | AI100: ='TOTALS&AVERAGES'!N100 | AJ100: =AI100-AH100 -> 0
...

Sheet APR
A1: APRIL | B1: Monthly Regular Bills | C1: 46113 | D1: =C1+1 -> 46114 | E1: =D1+1 -> 46115 | F1: =E1+1 -> 46116 | G1: =F1+1 -> 46117 | H1: =G1+1 -> 46118 | I1: =H1+1 -> 46119 | J1: =I1+1 -> 46120 | K1: =J1+1 -> 46121 | ... AG1: =AF1+1 -> 46143 | AH1: TOTALS | AI1: SPENDING PLAN | AJ1: DIFFERENCE
A2: INCOME
A3: =JAN!A3 -> Main Job | AH3: =sum(B3:AF3) -> 0 | AI3: ='TOTALS&AVERAGES'!N3 | AJ3: =AI3-AH3 -> 0
A4: =JAN!A4 -> B Job | AH4: =sum(B4:AF4) -> 0 | AI4: ='TOTALS&AVERAGES'!N4 | AJ4: =AI4-AH4 -> 0
A5: =JAN!A5 -> Bonuses | AH5: =sum(B5:AF5) -> 0 | AI5: ='TOTALS&AVERAGES'!N5 | AJ5: =AI5-AH5 -> 0
A6: =JAN!A6 -> Gifts/Discounts | AH6: =sum(B6:AF6) -> 0 | AI6: ='TOTALS&AVERAGES'!N6 | AJ6: =AI6-AH6 -> 0
A7: =JAN!A7 -> Reimbursement | AH7: =sum(B7:AF7) -> 0 | AI7: ='TOTALS&AVERAGES'!N7 | AJ7: =AI7-AH7 -> 0
A8: =JAN!A8 -> Government Assistance | AH8: =sum(B8:AF8) -> 0 | AI8: ='TOTALS&AVERAGES'!N8 | AJ8: =AI8-AH8 -> 0
A9: =JAN!A9 -> Side Hustles | AH9: =sum(B9:AF9) -> 0 | AI9: ='TOTALS&AVERAGES'!N9 | AJ9: =AI9-AH9 -> 0
A10: =JAN!A10 -> Interest/Rewards | AH10: =sum(B10:AF10) -> 0 | AI10: ='TOTALS&AVERAGES'!N10 | AJ10: =AI10-AH10 -> 0
A11: =JAN!A11 -> VA Benefits | AH11: =sum(B11:AF11) -> 0 | AI11: ='TOTALS&AVERAGES'!N11 | AJ11: =AI11-AH11 -> 0
A12: =JAN!A12 -> Asset Cash Out | AH12: =sum(B12:AF12) -> 0 | AI12: ='TOTALS&AVERAGES'!N12 | AJ12: =AI12-AH12 -> 0
A13: =JAN!A13 -> Fed Tax Refund | AH13: =sum(B13:AF13) -> 0 | AI13: ='TOTALS&AVERAGES'!N13 | AJ13: =AI13-AH13 -> 0
A14: =JAN!A14 -> State Tax Refund | AH14: =sum(B14:AF14) -> 0 | AI14: ='TOTALS&AVERAGES'!N14 | AJ14: =AI14-AH14 -> 0
A15: TOTAL INCOME BEFORE TAXES | B15: =SUM(C3:AH14) -> 0 | C15: =SUM(C3:C14) -> 0 | D15: =SUM(D3:D14) -> 0 | E15: =SUM(E3:E14) -> 0 | F15: =SUM(F3:F14) -> 0 | G15: =SUM(G3:G14) -> 0 | H15: =SUM(H3:H14) -> 0 | I15: =SUM(I3:I14) -> 0 | J15: =SUM(J3:J14) -> 0 | ... AJ15: =SUM(AJ3:AJ14) -> 0
A16: EXPENSES BY D.A. CATEGORIES | B16: MONTHLY REGULAR BILLS
A17: 1 - SPIRITUAL | B17: =SUM(B18:B26) -> 0 | C17: =SUM(C18:C26) -> 0 | D17: =SUM(D18:D26) -> 0 | E17: =SUM(E18:E26) -> 0 | F17: =SUM(F18:F26) -> 0 | G17: =SUM(G18:G26) -> 0 | H17: =SUM(H18:H26) -> 0 | I17: =SUM(I18:I26) -> 0 | ... AJ17: =SUM(AJ18:AJ26) -> 0
A18: =JAN!A18 -> Tithing/Church Donation | AH18: =sum(B18:AF18) -> 0 | AI18: ='TOTALS&AVERAGES'!N18 | AJ18: =AI18-AH18 -> 0
A19: =JAN!A19 -> Books | AH19: =sum(B19:AF19) -> 0 | AI19: ='TOTALS&AVERAGES'!N19 | AJ19: =AI19-AH19 -> 0
A20: =JAN!A20 -> Charity | AH20: =sum(B20:AF20) -> 0 | AI20: ='TOTALS&AVERAGES'!N20 | AJ20: =AI20-AH20 -> 0
A21: =JAN!A21 -> Workshops | AH21: =sum(B21:AF21) -> 0 | AI21: ='TOTALS&AVERAGES'!N21 | AJ21: =AI21-AH21 -> 0
A22: =JAN!A22 -> Generosity | AH22: =sum(B22:AF22) -> 0 | AI22: ='TOTALS&AVERAGES'!N22 | AJ22: =AI22-AH22 -> 0
A23: =JAN!A23 -> Retreats / Seminars | AH23: =sum(B23:AF23) -> 0 | AI23: ='TOTALS&AVERAGES'!N23 | AJ23: =AI23-AH23 -> 0
A24: =JAN!A24 -> 7TH TRADITION / FELLOWSHIP/ PRG | AH24: =sum(B24:AF24) -> 0 | AI24: ='TOTALS&AVERAGES'!N24 | AJ24: =AI24-AH24 -> 0
A25: =JAN!A25 -> Conferences | AH25: =sum(B25:AF25) -> 0 | AI25: ='TOTALS&AVERAGES'!N25 | AJ25: =AI25-AH25 -> 0
A26: =JAN!A26 -> Career Investment | AH26: =sum(B26:AF26) -> 0 | AI26: ='TOTALS&AVERAGES'!N26 | AJ26: =AI26-AH26 -> 0
A27: =JAN!A27 -> Needs | B27: =SUM(B28:B43) -> 0 | C27: =SUM(C28:C43) -> 0 | D27: =SUM(D28:D43) -> 0 | E27: =SUM(E28:E43) -> 0 | F27: =SUM(F28:F43) -> 0 | G27: =SUM(G28:G43) -> 0 | H27: =SUM(H28:H43) -> 0 | I27: =SUM(I28:I43) -> 0 | ... AJ27: =SUM(AJ28:AJ43) -> 0
A28: =JAN!A28 -> Groceries | AH28: =sum(B28:AF28) -> 0 | AI28: ='TOTALS&AVERAGES'!N28 | AJ28: =AI28-AH28 -> 0
A29: =JAN!A29 -> Rent/Mortage | B29: * | AH29: =sum(B29:AF29) -> 0 | AI29: ='TOTALS&AVERAGES'!N29 | AJ29: =AI29-AH29 -> 0
A30: =JAN!A30 -> Cell Phone | B30: * | AH30: =sum(B30:AF30) -> 0 | AI30: ='TOTALS&AVERAGES'!N30 | AJ30: =AI30-AH30 -> 0
A31: =JAN!A31 -> Laundry/Cleaners | B31: * | AH31: =sum(B31:AF31) -> 0 | AI31: ='TOTALS&AVERAGES'!N31 | AJ31: =AI31-AH31 -> 0
A32: =JAN!A32 -> Car Fuel | B32: * | AH32: =sum(B32:AF32) -> 0 | AI32: ='TOTALS&AVERAGES'!N32 | AJ32: =AI32-AH32 -> 0
A33: =JAN!A33 -> Car Insurance | B33: * | AH33: =sum(B33:AF33) -> 0 | AI33: ='TOTALS&AVERAGES'!N33 | AJ33: =AI33-AH33 -> 0
A34: =JAN!A34 -> Home Items | B34: * | AH34: =sum(B34:AF34) -> 0 | AI34: ='TOTALS&AVERAGES'!N34 | AJ34: =AI34-AH34 -> 0
A35: =JAN!A35 -> Internet | AH35: =sum(B35:AF35) -> 0 | AI35: ='TOTALS&AVERAGES'!N35 | AJ35: =AI35-AH35 -> 0
A36: =JAN!A36 -> Electricity | B36: * | AH36: =sum(B36:AF36) -> 0 | AI36: ='TOTALS&AVERAGES'!N36 | AJ36: =AI36-AH36 -> 0
A37: =JAN!A37 -> Card Fees | AH37: =sum(B37:AF37) -> 0 | AI37: ='TOTALS&AVERAGES'!N37 | AJ37: =AI37-AH37 -> 0
A38: =JAN!A38 -> Moving | AH38: =sum(B38:AF38) -> 0 | AI38: ='TOTALS&AVERAGES'!N38 | AJ38: =AI38-AH38 -> 0
A39: =JAN!A39 -> Toiletries | B39: * | AH39: =sum(B39:AF39) -> 0 | AI39: ='TOTALS&AVERAGES'!N39 | AJ39: =AI39-AH39 -> 0
A40: =JAN!A40 -> Storage | B40: * | AH40: =sum(B40:AF40) -> 0 | AI40: ='TOTALS&AVERAGES'!N40 | AJ40: =AI40-AH40 -> 0
A41: =JAN!A41 -> MTA/Public Transportation | B41: * | AH41: =sum(B41:AF41) -> 0 | AI41: ='TOTALS&AVERAGES'!N41 | AJ41: =AI41-AH41 -> 0
A42: =JAN!A42 -> Health Care | AH42: =sum(B42:AF42) -> 0 | AI42: ='TOTALS&AVERAGES'!N42 | AJ42: =AI42-AH42 -> 0
A43: =JAN!A43 -> Repairs | AH43: =sum(B43:AF43) -> 0 | AI43: ='TOTALS&AVERAGES'!N43 | AJ43: =AI43-AH43 -> 0
A44: =JAN!A44 -> Wants | B44: =SUM(B45:B52) -> 0 | C44: =SUM(C45:C52) -> 0 | D44: =SUM(D45:D52) -> 0 | E44: =SUM(E45:E52) -> 0 | F44: =SUM(F45:F52) -> 0 | G44: =SUM(G45:G52) -> 0 | H44: =SUM(H45:H52) -> 0 | I44: =SUM(I45:I52) -> 0 | ... AJ44: =SUM(AJ45:AJ52) -> 0
A45: =JAN!A45 -> Clothes | AH45: =sum(B45:AF45) -> 0 | AI45: ='TOTALS&AVERAGES'!N45 | AJ45: =AI45-AH45 -> 0
A46: =JAN!A46 -> Haircuts | AH46: =sum(B46:AF46) -> 0 | AI46: ='TOTALS&AVERAGES'!N46 | AJ46: =AI46-AH46 -> 0
A47: =JAN!A47 -> Dining Out/Take out/Events | AH47: =sum(B47:AF47) -> 0 | AI47: ='TOTALS&AVERAGES'!N47 | AJ47: =AI47-AH47 -> 0
A48: =JAN!A48 -> Gym Membership | AH48: =sum(B48:AF48) -> 0 | AI48: ='TOTALS&AVERAGES'!N48 | AJ48: =AI48-AH48 -> 0
A49: =JAN!A49 -> Subscriptions Zoom/Paramount/Club Free/News Subsription | B49: * | AH49: =sum(B49:AF49) -> 0 | AI49: ='TOTALS&AVERAGES'!N49 | AJ49: =AI49-AH49 -> 0
A50: =JAN!A50 -> Snacks | AH50: =sum(B50:AF50) -> 0 | AI50: ='TOTALS&AVERAGES'!N50 | AJ50: =AI50-AH50 -> 0
A51: =JAN!A51 -> Vacations/Trip to see Brother Bryant/Trip to NM/Trip to San Antonio | AH51: =sum(B51:AF51) -> 0 | AI51: ='TOTALS&AVERAGES'!N51 | AJ51: =AI51-AH51 -> 0
A52: =JAN!A52 -> Other/Misc | AH52: =sum(B52:AF52) -> 0 | AI52: ='TOTALS&AVERAGES'!N52 | AJ52: =AI52-AH52 -> 0
A53: =JAN!A53 -> Savings | B53: =SUM(B54:B67) -> 0 | C53: =SUM(C54:C67) -> 0 | D53: =SUM(D54:D67) -> 0 | E53: =SUM(E54:E67) -> 0 | F53: =SUM(F54:F67) -> 0 | G53: =SUM(G54:G67) -> 0 | H53: =SUM(H54:H67) -> 0 | I53: =SUM(I54:I67) -> 0 | ... AJ53: =SUM(AJ54:AJ67) -> 0
A54: =JAN!A54 -> High yield Savings | B54: * | AH54: =sum(B54:AF54) -> 0 | AI54: ='TOTALS&AVERAGES'!N54 | AJ54: =AI54-AH54 -> 0
A55: =JAN!A55 -> Emergency Fund | B55: * | AH55: =sum(B55:AF55) -> 0 | AI55: ='TOTALS&AVERAGES'!N55 | AJ55: =AI55-AH55 -> 0
A56: =JAN!A56 -> Stocks/Index Fund | B56: * | AH56: =sum(B56:AF56) -> 0 | AI56: ='TOTALS&AVERAGES'!N56 | AJ56: =AI56-AH56 -> 0
A57: =JAN!A57 -> Real Estate | AH57: =sum(B57:AF57) -> 0 | AI57: ='TOTALS&AVERAGES'!N57 | AJ57: =AI57-AH57 -> 0
A58: =JAN!A58 -> Extra Debt Payment | AH58: =sum(B58:AF58) -> 0 | AI58: ='TOTALS&AVERAGES'!N58 | AJ58: =AI58-AH58 -> 0
A59: =JAN!A59 -> Gold | AH59: =sum(B59:AF59) -> 0 | AI59: ='TOTALS&AVERAGES'!N59 | AJ59: =AI59-AH59 -> 0
A60: =JAN!A60 -> Retirement/Roth IRA | AH60: =sum(B60:AF60) -> 0 | AI60: ='TOTALS&AVERAGES'!N60 | AJ60: =AI60-AH60 -> 0
A61: =JAN!A61 -> Annuities | AH61: =sum(B61:AF61) -> 0 | AI61: ='TOTALS&AVERAGES'!N61 | AJ61: =AI61-AH61 -> 0
A62: =JAN!A62 -> Life Insurance | AH62: =sum(B62:AF62) -> 0 | AI62: ='TOTALS&AVERAGES'!N62 | AJ62: =AI62-AH62 -> 0
A63: =JAN!A63 -> Watch | AH63: =sum(B63:AF63) -> 0 | AI63: ='TOTALS&AVERAGES'!N63 | AJ63: =AI63-AH63 -> 0
A64: =JAN!A64 -> CD | AH64: =sum(B64:AF64) -> 0 | AI64: ='TOTALS&AVERAGES'!N64 | AJ64: =AI64-AH64 -> 0
A65: =JAN!A65 -> Taxes Savings | AH65: =sum(B65:AF65) -> 0 | AI65: ='TOTALS&AVERAGES'!N65 | AJ65: =AI65-AH65 -> 0
A66: =JAN!A66 -> HSA | AH66: =sum(B66:AF66) -> 0 | AI66: ='TOTALS&AVERAGES'!N66 | AJ66: =AI66-AH66 -> 0
A67: =JAN!A67 -> - | AH67: =sum(B67:AF67) -> 0 | AI67: ='TOTALS&AVERAGES'!N67 | AJ67: =AI67-AH67 -> 0
A68: =JAN!A68 -> Debts | B68: =SUM(B69:B79) -> 0 | C68: =SUM(C69:C79) -> 0 | D68: =SUM(D69:D79) -> 0 | E68: =SUM(E69:E79) -> 0 | F68: =SUM(F69:F79) -> 0 | G68: =SUM(G69:G79) -> 0 | H68: =SUM(H69:H79) -> 0 | I68: =SUM(I69:I79) -> 0 | ... AJ68: =SUM(AJ69:AJ79) -> 0
A69: =JAN!A69 -> NFCU Loan 1151 | AH69: =sum(B69:AF69) -> 0 | AI69: ='TOTALS&AVERAGES'!N69 | AJ69: =AI69-AH69 -> 0
A70: =JAN!A70 -> NFCU Credit Card 8743 | AH70: =sum(B70:AF70) -> 0 | AI70: ='TOTALS&AVERAGES'!N70 | AJ70: =AI70-AH70 -> 0
A71: =JAN!A71 -> Capital One Credit Card 1057 | AH71: =sum(B71:AF71) -> 0 | AI71: ='TOTALS&AVERAGES'!N71 | AJ71: =AI71-AH71 -> 0
A72: =JAN!A72 -> Blink Fitness Collections | AH72: =sum(B72:AF72) -> 0 | AI72: ='TOTALS&AVERAGES'!N72 | AJ72: =AI72-AH72 -> 0
A73: =JAN!A73 -> T-Mobile Phone Bill | AH73: =sum(B73:AF73) -> 0 | AI73: ='TOTALS&AVERAGES'!N73 | AJ73: =AI73-AH73 -> 0
A74: =JAN!A74 -> TD Bank Collections | AH74: =sum(B74:AF74) -> 0 | AI74: ='TOTALS&AVERAGES'!N74 | AJ74: =AI74-AH74 -> 0
A75: =JAN!A75 -> Safegaurd Operations Collections | AH75: =sum(B75:AF75) -> 0 | AI75: ='TOTALS&AVERAGES'!N75 | AJ75: =AI75-AH75 -> 0
A76: =JAN!A76 -> BMCC Loan 474.03 | AH76: =sum(B76:AF76) -> 0 | AI76: ='TOTALS&AVERAGES'!N76 | AJ76: =AI76-AH76 -> 0
A77: =JAN!A77 -> Han Personal Debt (Paid) | AH77: =sum(B77:AF77) -> 0 | AI77: ='TOTALS&AVERAGES'!N77 | AJ77: =AI77-AH77 -> 0
A78: =JAN!A78 | AH78: =sum(B78:AF78) -> 0 | AI78: ='TOTALS&AVERAGES'!N78 | AJ78: =AI78-AH78 -> 0
A79: =JAN!A79 -> Total Debt: 8,551.73 | AH79: =sum(B79:AF79) -> 0 | AI79: ='TOTALS&AVERAGES'!N79 | AJ79: =AI79-AH79 -> 0
A80: =JAN!A80 -> School | B80: =SUM(B81:B91) -> 0 | C80: =SUM(C81:C91) -> 0 | D80: =SUM(D81:D91) -> 0 | E80: =SUM(E81:E91) -> 0 | F80: =SUM(F81:F91) -> 0 | G80: =SUM(G81:G91) -> 0 | H80: =SUM(H81:H91) -> 0 | I80: =SUM(I81:I91) -> 0 | ... AJ80: =SUM(AJ81:AJ91) -> 0
A81: =JAN!A81 -> Tuition | AH81: =sum(B81:AF81) -> 0 | AI81: ='TOTALS&AVERAGES'!N81 | AJ81: =AI81-AH81 -> 0
A82: =JAN!A82 -> Books | AH82: =sum(B82:AF82) -> 0 | AI82: ='TOTALS&AVERAGES'!N82 | AJ82: =AI82-AH82 -> 0
A83: =JAN!A83 | AH83: =sum(B83:AF83) -> 0 | AI83: ='TOTALS&AVERAGES'!N83 | AJ83: =AI83-AH83 -> 0
A84: =JAN!A84 | AH84: =sum(B84:AF84) -> 0 | AI84: ='TOTALS&AVERAGES'!N84 | AJ84: =AI84-AH84 -> 0
A85: =JAN!A85 | AH85: =sum(B85:AF85) -> 0 | AI85: ='TOTALS&AVERAGES'!N85 | AJ85: =AI85-AH85 -> 0
A86: =JAN!A86 | AH86: =sum(B86:AF86) -> 0 | AI86: ='TOTALS&AVERAGES'!N86 | AJ86: =AI86-AH86 -> 0
A87: =JAN!A87 | AH87: =sum(B87:AF87) -> 0 | AI87: ='TOTALS&AVERAGES'!N87 | AJ87: =AI87-AH87 -> 0
A88: =JAN!A88 | AH88: =sum(B88:AF88) -> 0 | AI88: ='TOTALS&AVERAGES'!N88 | AJ88: =AI88-AH88 -> 0
A89: =JAN!A89 | AH89: =sum(B89:AF89) -> 0 | AI89: ='TOTALS&AVERAGES'!N89 | AJ89: =AI89-AH89 -> 0
A90: =JAN!A90 | AH90: =sum(B90:AF90) -> 0 | AI90: ='TOTALS&AVERAGES'!N90 | AJ90: =AI90-AH90 -> 0
A91: =JAN!A91 | AH91: =sum(B91:AF91) -> 0 | AI91: ='TOTALS&AVERAGES'!N91 | AJ91: =AI91-AH91 -> 0
A92: =JAN!A92 | B92: =SUM(B93:B106) -> 0 | C92: =SUM(C93:C106) -> 0 | D92: =SUM(D93:D106) -> 0 | E92: =SUM(E93:E106) -> 0 | F92: =SUM(F93:F106) -> 0 | G92: =SUM(G93:G106) -> 0 | H92: =SUM(H93:H106) -> 0 | I92: =SUM(I93:I106) -> 0 | ... AJ92: =SUM(AJ93:AJ106) -> 0
A93: =JAN!A93 | AH93: =sum(B93:AF93) -> 0 | AI93: ='TOTALS&AVERAGES'!N93 | AJ93: =AI93-AH93 -> 0
A94: =JAN!A94 | AH94: =sum(B94:AF94) -> 0 | AI94: ='TOTALS&AVERAGES'!N94 | AJ94: =AI94-AH94 -> 0
A95: =JAN!A95 | B95: * | AH95: =sum(B95:AF95) -> 0 | AI95: ='TOTALS&AVERAGES'!N95 | AJ95: =AI95-AH95 -> 0
A96: =JAN!A96 | AH96: =sum(B96:AF96) -> 0 | AI96: ='TOTALS&AVERAGES'!N96 | AJ96: =AI96-AH96 -> 0
A97: =JAN!A97 | AH97: =sum(B97:AF97) -> 0 | AI97: ='TOTALS&AVERAGES'!N97 | AJ97: =AI97-AH97 -> 0
A98: =JAN!A98 | AH98: =sum(B98:AF98) -> 0 | AI98: ='TOTALS&AVERAGES'!N98 | AJ98: =AI98-AH98 -> 0
A99: =JAN!A99 | B99: * | AH99: =sum(B99:AF99) -> 0 | AI99: ='TOTALS&AVERAGES'!N99 | AJ99: =AI99-AH99 -> 0
A100: =JAN!A100 | B100: * | AH100: =sum(B100:AF100) -> 0 | AI100: ='TOTALS&AVERAGES'!N100 | AJ100: =AI100-AH100 -> 0
...

Sheet MAY
A1: MAY | B1: Monthly Regular Bills | C1: 46143 | D1: =C1+1 -> 46144 | E1: =D1+1 -> 46145 | F1: =E1+1 -> 46146 | G1: =F1+1 -> 46147 | H1: =G1+1 -> 46148 | I1: =H1+1 -> 46149 | J1: =I1+1 -> 46150 | K1: =J1+1 -> 46151 | ... AG1: =AF1+1 -> 46173 | AH1: TOTALS | AI1: SPENDING PLAN | AJ1: DIFFERENCE
A2: INCOME
A3: =JAN!A3 -> Main Job | AH3: =sum(B3:AF3) -> 0 | AI3: ='TOTALS&AVERAGES'!N3 | AJ3: =AI3-AH3 -> 0
A4: =JAN!A4 -> B Job | AH4: =sum(B4:AF4) -> 0 | AI4: ='TOTALS&AVERAGES'!N4 | AJ4: =AI4-AH4 -> 0
A5: =JAN!A5 -> Bonuses | AH5: =sum(B5:AF5) -> 0 | AI5: ='TOTALS&AVERAGES'!N5 | AJ5: =AI5-AH5 -> 0
A6: =JAN!A6 -> Gifts/Discounts | AH6: =sum(B6:AF6) -> 0 | AI6: ='TOTALS&AVERAGES'!N6 | AJ6: =AI6-AH6 -> 0
A7: =JAN!A7 -> Reimbursement | AH7: =sum(B7:AF7) -> 0 | AI7: ='TOTALS&AVERAGES'!N7 | AJ7: =AI7-AH7 -> 0
A8: =JAN!A8 -> Government Assistance | AH8: =sum(B8:AF8) -> 0 | AI8: ='TOTALS&AVERAGES'!N8 | AJ8: =AI8-AH8 -> 0
A9: =JAN!A9 -> Side Hustles | AH9: =sum(B9:AF9) -> 0 | AI9: ='TOTALS&AVERAGES'!N9 | AJ9: =AI9-AH9 -> 0
A10: =JAN!A10 -> Interest/Rewards | AH10: =sum(B10:AF10) -> 0 | AI10: ='TOTALS&AVERAGES'!N10 | AJ10: =AI10-AH10 -> 0
A11: =JAN!A11 -> VA Benefits | AH11: =sum(B11:AF11) -> 0 | AI11: ='TOTALS&AVERAGES'!N11 | AJ11: =AI11-AH11 -> 0
A12: =JAN!A12 -> Asset Cash Out | AH12: =sum(B12:AF12) -> 0 | AI12: ='TOTALS&AVERAGES'!N12 | AJ12: =AI12-AH12 -> 0
A13: =JAN!A13 -> Fed Tax Refund | AH13: =sum(B13:AF13) -> 0 | AI13: ='TOTALS&AVERAGES'!N13 | AJ13: =AI13-AH13 -> 0
A14: =JAN!A14 -> State Tax Refund | AH14: =sum(B14:AF14) -> 0 | AI14: ='TOTALS&AVERAGES'!N14 | AJ14: =AI14-AH14 -> 0
A15: TOTAL INCOME BEFORE TAXES | B15: =SUM(C3:AH14) -> 0 | C15: =SUM(C3:C14) -> 0 | D15: =SUM(D3:D14) -> 0 | E15: =SUM(E3:E14) -> 0 | F15: =SUM(F3:F14) -> 0 | G15: =SUM(G3:G14) -> 0 | H15: =SUM(H3:H14) -> 0 | I15: =SUM(I3:I14) -> 0 | J15: =SUM(J3:J14) -> 0 | ... AJ15: =SUM(AJ3:AJ14) -> 0
A16: EXPENSES BY D.A. CATEGORIES | B16: MONTHLY REGULAR BILLS
A17: 1 - SPIRITUAL | B17: =SUM(B18:B26) -> 0 | C17: =SUM(C18:C26) -> 0 | D17: =SUM(D18:D26) -> 0 | E17: =SUM(E18:E26) -> 0 | F17: =SUM(F18:F26) -> 0 | G17: =SUM(G18:G26) -> 0 | H17: =SUM(H18:H26) -> 0 | I17: =SUM(I18:I26) -> 0 | ... AJ17: =SUM(AJ18:AJ26) -> 0
A18: =JAN!A18 -> Tithing/Church Donation | AH18: =sum(B18:AF18) -> 0 | AI18: ='TOTALS&AVERAGES'!N18 | AJ18: =AI18-AH18 -> 0
A19: =JAN!A19 -> Books | AH19: =sum(B19:AF19) -> 0 | AI19: ='TOTALS&AVERAGES'!N19 | AJ19: =AI19-AH19 -> 0
A20: =JAN!A20 -> Charity | AH20: =sum(B20:AF20) -> 0 | AI20: ='TOTALS&AVERAGES'!N20 | AJ20: =AI20-AH20 -> 0
A21: =JAN!A21 -> Workshops | AH21: =sum(B21:AF21) -> 0 | AI21: ='TOTALS&AVERAGES'!N21 | AJ21: =AI21-AH21 -> 0
A22: =JAN!A22 -> Generosity | AH22: =sum(B22:AF22) -> 0 | AI22: ='TOTALS&AVERAGES'!N22 | AJ22: =AI22-AH22 -> 0
A23: =JAN!A23 -> Retreats / Seminars | AH23: =sum(B23:AF23) -> 0 | AI23: ='TOTALS&AVERAGES'!N23 | AJ23: =AI23-AH23 -> 0
A24: =JAN!A24 -> 7TH TRADITION / FELLOWSHIP/ PRG | AH24: =sum(B24:AF24) -> 0 | AI24: ='TOTALS&AVERAGES'!N24 | AJ24: =AI24-AH24 -> 0
A25: =JAN!A25 -> Conferences | AH25: =sum(B25:AF25) -> 0 | AI25: ='TOTALS&AVERAGES'!N25 | AJ25: =AI25-AH25 -> 0
A26: =JAN!A26 -> Career Investment | AH26: =sum(B26:AF26) -> 0 | AI26: ='TOTALS&AVERAGES'!N26 | AJ26: =AI26-AH26 -> 0
A27: =JAN!A27 -> Needs | B27: =SUM(B28:B43) -> 0 | C27: =SUM(C28:C43) -> 0 | D27: =SUM(D28:D43) -> 0 | E27: =SUM(E28:E43) -> 0 | F27: =SUM(F28:F43) -> 0 | G27: =SUM(G28:G43) -> 0 | H27: =SUM(H28:H43) -> 0 | I27: =SUM(I28:I43) -> 0 | ... AJ27: =SUM(AJ28:AJ43) -> 0
A28: =JAN!A28 -> Groceries | AH28: =sum(B28:AF28) -> 0 | AI28: ='TOTALS&AVERAGES'!N28 | AJ28: =AI28-AH28 -> 0
A29: =JAN!A29 -> Rent/Mortage | B29: * | AH29: =sum(B29:AF29) -> 0 | AI29: ='TOTALS&AVERAGES'!N29 | AJ29: =AI29-AH29 -> 0
A30: =JAN!A30 -> Cell Phone | B30: * | AH30: =sum(B30:AF30) -> 0 | AI30: ='TOTALS&AVERAGES'!N30 | AJ30: =AI30-AH30 -> 0
A31: =JAN!A31 -> Laundry/Cleaners | B31: * | AH31: =sum(B31:AF31) -> 0 | AI31: ='TOTALS&AVERAGES'!N31 | AJ31: =AI31-AH31 -> 0
A32: =JAN!A32 -> Car Fuel | B32: * | AH32: =sum(B32:AF32) -> 0 | AI32: ='TOTALS&AVERAGES'!N32 | AJ32: =AI32-AH32 -> 0
A33: =JAN!A33 -> Car Insurance | B33: * | AH33: =sum(B33:AF33) -> 0 | AI33: ='TOTALS&AVERAGES'!N33 | AJ33: =AI33-AH33 -> 0
A34: =JAN!A34 -> Home Items | B34: * | AH34: =sum(B34:AF34) -> 0 | AI34: ='TOTALS&AVERAGES'!N34 | AJ34: =AI34-AH34 -> 0
A35: =JAN!A35 -> Internet | AH35: =sum(B35:AF35) -> 0 | AI35: ='TOTALS&AVERAGES'!N35 | AJ35: =AI35-AH35 -> 0
A36: =JAN!A36 -> Electricity | B36: * | AH36: =sum(B36:AF36) -> 0 | AI36: ='TOTALS&AVERAGES'!N36 | AJ36: =AI36-AH36 -> 0
A37: =JAN!A37 -> Card Fees | AH37: =sum(B37:AF37) -> 0 | AI37: ='TOTALS&AVERAGES'!N37 | AJ37: =AI37-AH37 -> 0
A38: =JAN!A38 -> Moving | AH38: =sum(B38:AF38) -> 0 | AI38: ='TOTALS&AVERAGES'!N38 | AJ38: =AI38-AH38 -> 0
A39: =JAN!A39 -> Toiletries | B39: * | AH39: =sum(B39:AF39) -> 0 | AI39: ='TOTALS&AVERAGES'!N39 | AJ39: =AI39-AH39 -> 0
A40: =JAN!A40 -> Storage | B40: * | AH40: =sum(B40:AF40) -> 0 | AI40: ='TOTALS&AVERAGES'!N40 | AJ40: =AI40-AH40 -> 0
A41: =JAN!A41 -> MTA/Public Transportation | B41: * | AH41: =sum(B41:AF41) -> 0 | AI41: ='TOTALS&AVERAGES'!N41 | AJ41: =AI41-AH41 -> 0
A42: =JAN!A42 -> Health Care | AH42: =sum(B42:AF42) -> 0 | AI42: ='TOTALS&AVERAGES'!N42 | AJ42: =AI42-AH42 -> 0
A43: =JAN!A43 -> Repairs | AH43: =sum(B43:AF43) -> 0 | AI43: ='TOTALS&AVERAGES'!N43 | AJ43: =AI43-AH43 -> 0
A44: =JAN!A44 -> Wants | B44: =SUM(B45:B52) -> 0 | C44: =SUM(C45:C52) -> 0 | D44: =SUM(D45:D52) -> 0 | E44: =SUM(E45:E52) -> 0 | F44: =SUM(F45:F52) -> 0 | G44: =SUM(G45:G52) -> 0 | H44: =SUM(H45:H52) -> 0 | I44: =SUM(I45:I52) -> 0 | ... AJ44: =SUM(AJ45:AJ52) -> 0
A45: =JAN!A45 -> Clothes | AH45: =sum(B45:AF45) -> 0 | AI45: ='TOTALS&AVERAGES'!N45 | AJ45: =AI45-AH45 -> 0
A46: =JAN!A46 -> Haircuts | AH46: =sum(B46:AF46) -> 0 | AI46: ='TOTALS&AVERAGES'!N46 | AJ46: =AI46-AH46 -> 0
A47: =JAN!A47 -> Dining Out/Take out/Events | AH47: =sum(B47:AF47) -> 0 | AI47: ='TOTALS&AVERAGES'!N47 | AJ47: =AI47-AH47 -> 0
A48: =JAN!A48 -> Gym Membership | AH48: =sum(B48:AF48) -> 0 | AI48: ='TOTALS&AVERAGES'!N48 | AJ48: =AI48-AH48 -> 0
A49: =JAN!A49 -> Subscriptions Zoom/Paramount/Club Free/News Subsription | AH49: =sum(B49:AF49) -> 0 | AI49: ='TOTALS&AVERAGES'!N49 | AJ49: =AI49-AH49 -> 0
A50: =JAN!A50 -> Snacks | AH50: =sum(B50:AF50) -> 0 | AI50: ='TOTALS&AVERAGES'!N50 | AJ50: =AI50-AH50 -> 0
A51: =JAN!A51 -> Vacations/Trip to see Brother Bryant/Trip to NM/Trip to San Antonio | AH51: =sum(B51:AF51) -> 0 | AI51: ='TOTALS&AVERAGES'!N51 | AJ51: =AI51-AH51 -> 0
A52: =JAN!A52 -> Other/Misc | AH52: =sum(B52:AF52) -> 0 | AI52: ='TOTALS&AVERAGES'!N52 | AJ52: =AI52-AH52 -> 0
A53: =JAN!A53 -> Savings | B53: =SUM(B54:B67) -> 0 | C53: =SUM(C54:C67) -> 0 | D53: =SUM(D54:D67) -> 0 | E53: =SUM(E54:E67) -> 0 | F53: =SUM(F54:F67) -> 0 | G53: =SUM(G54:G67) -> 0 | H53: =SUM(H54:H67) -> 0 | I53: =SUM(I54:I67) -> 0 | ... AJ53: =SUM(AJ54:AJ67) -> 0
A54: =JAN!A54 -> High yield Savings | B54: * | AH54: =sum(B54:AF54) -> 0 | AI54: ='TOTALS&AVERAGES'!N54 | AJ54: =AI54-AH54 -> 0
A55: =JAN!A55 -> Emergency Fund | B55: * | AH55: =sum(B55:AF55) -> 0 | AI55: ='TOTALS&AVERAGES'!N55 | AJ55: =AI55-AH55 -> 0
A56: =JAN!A56 -> Stocks/Index Fund | B56: * | AH56: =sum(B56:AF56) -> 0 | AI56: ='TOTALS&AVERAGES'!N56 | AJ56: =AI56-AH56 -> 0
A57: =JAN!A57 -> Real Estate | AH57: =sum(B57:AF57) -> 0 | AI57: ='TOTALS&AVERAGES'!N57 | AJ57: =AI57-AH57 -> 0
A58: =JAN!A58 -> Extra Debt Payment | AH58: =sum(B58:AF58) -> 0 | AI58: ='TOTALS&AVERAGES'!N58 | AJ58: =AI58-AH58 -> 0
A59: =JAN!A59 -> Gold | AH59: =sum(B59:AF59) -> 0 | AI59: ='TOTALS&AVERAGES'!N59 | AJ59: =AI59-AH59 -> 0
A60: =JAN!A60 -> Retirement/Roth IRA | AH60: =sum(B60:AF60) -> 0 | AI60: ='TOTALS&AVERAGES'!N60 | AJ60: =AI60-AH60 -> 0
A61: =JAN!A61 -> Annuities | AH61: =sum(B61:AF61) -> 0 | AI61: ='TOTALS&AVERAGES'!N61 | AJ61: =AI61-AH61 -> 0
A62: =JAN!A62 -> Life Insurance | AH62: =sum(B62:AF62) -> 0 | AI62: ='TOTALS&AVERAGES'!N62 | AJ62: =AI62-AH62 -> 0
A63: =JAN!A63 -> Watch | AH63: =sum(B63:AF63) -> 0 | AI63: ='TOTALS&AVERAGES'!N63 | AJ63: =AI63-AH63 -> 0
A64: =JAN!A64 -> CD | AH64: =sum(B64:AF64) -> 0 | AI64: ='TOTALS&AVERAGES'!N64 | AJ64: =AI64-AH64 -> 0
A65: =JAN!A65 -> Taxes Savings | AH65: =sum(B65:AF65) -> 0 | AI65: ='TOTALS&AVERAGES'!N65 | AJ65: =AI65-AH65 -> 0
A66: =JAN!A66 -> HSA | AH66: =sum(B66:AF66) -> 0 | AI66: ='TOTALS&AVERAGES'!N66 | AJ66: =AI66-AH66 -> 0
A67: =JAN!A67 -> - | AH67: =sum(B67:AF67) -> 0 | AI67: ='TOTALS&AVERAGES'!N67 | AJ67: =AI67-AH67 -> 0
A68: =JAN!A68 -> Debts | B68: =SUM(B69:B79) -> 0 | C68: =SUM(C69:C79) -> 0 | D68: =SUM(D69:D79) -> 0 | E68: =SUM(E69:E79) -> 0 | F68: =SUM(F69:F79) -> 0 | G68: =SUM(G69:G79) -> 0 | H68: =SUM(H69:H79) -> 0 | I68: =SUM(I69:I79) -> 0 | ... AJ68: =SUM(AJ69:AJ79) -> 0
A69: =JAN!A69 -> NFCU Loan 1151 | AH69: =sum(B69:AF69) -> 0 | AI69: ='TOTALS&AVERAGES'!N69 | AJ69: =AI69-AH69 -> 0
A70: =JAN!A70 -> NFCU Credit Card 8743 | AH70: =sum(B70:AF70) -> 0 | AI70: ='TOTALS&AVERAGES'!N70 | AJ70: =AI70-AH70 -> 0
A71: =JAN!A71 -> Capital One Credit Card 1057 | AH71: =sum(B71:AF71) -> 0 | AI71: ='TOTALS&AVERAGES'!N71 | AJ71: =AI71-AH71 -> 0
A72: =JAN!A72 -> Blink Fitness Collections | AH72: =sum(B72:AF72) -> 0 | AI72: ='TOTALS&AVERAGES'!N72 | AJ72: =AI72-AH72 -> 0
A73: =JAN!A73 -> T-Mobile Phone Bill | AH73: =sum(B73:AF73) -> 0 | AI73: ='TOTALS&AVERAGES'!N73 | AJ73: =AI73-AH73 -> 0
A74: =JAN!A74 -> TD Bank Collections | AH74: =sum(B74:AF74) -> 0 | AI74: ='TOTALS&AVERAGES'!N74 | AJ74: =AI74-AH74 -> 0
A75: =JAN!A75 -> Safegaurd Operations Collections | AH75: =sum(B75:AF75) -> 0 | AI75: ='TOTALS&AVERAGES'!N75 | AJ75: =AI75-AH75 -> 0
A76: =JAN!A76 -> BMCC Loan 474.03 | AH76: =sum(B76:AF76) -> 0 | AI76: ='TOTALS&AVERAGES'!N76 | AJ76: =AI76-AH76 -> 0
A77: =JAN!A77 -> Han Personal Debt (Paid) | AH77: =sum(B77:AF77) -> 0 | AI77: ='TOTALS&AVERAGES'!N77 | AJ77: =AI77-AH77 -> 0
A78: =JAN!A78 | AH78: =sum(B78:AF78) -> 0 | AI78: ='TOTALS&AVERAGES'!N78 | AJ78: =AI78-AH78 -> 0
A79: =JAN!A79 -> Total Debt: 8,551.73 | AH79: =sum(B79:AF79) -> 0 | AI79: ='TOTALS&AVERAGES'!N79 | AJ79: =AI79-AH79 -> 0
A80: =JAN!A80 -> School | B80: =SUM(B81:B91) -> 0 | C80: =SUM(C81:C91) -> 0 | D80: =SUM(D81:D91) -> 0 | E80: =SUM(E81:E91) -> 0 | F80: =SUM(F81:F91) -> 0 | G80: =SUM(G81:G91) -> 0 | H80: =SUM(H81:H91) -> 0 | I80: =SUM(I81:I91) -> 0 | ... AJ80: =SUM(AJ81:AJ91) -> 0
A81: =JAN!A81 -> Tuition | AH81: =sum(B81:AF81) -> 0 | AI81: ='TOTALS&AVERAGES'!N81 | AJ81: =AI81-AH81 -> 0
A82: =JAN!A82 -> Books | AH82: =sum(B82:AF82) -> 0 | AI82: ='TOTALS&AVERAGES'!N82 | AJ82: =AI82-AH82 -> 0
A83: =JAN!A83 | AH83: =sum(B83:AF83) -> 0 | AI83: ='TOTALS&AVERAGES'!N83 | AJ83: =AI83-AH83 -> 0
A84: =JAN!A84 | AH84: =sum(B84:AF84) -> 0 | AI84: ='TOTALS&AVERAGES'!N84 | AJ84: =AI84-AH84 -> 0
A85: =JAN!A85 | AH85: =sum(B85:AF85) -> 0 | AI85: ='TOTALS&AVERAGES'!N85 | AJ85: =AI85-AH85 -> 0
A86: =JAN!A86 | AH86: =sum(B86:AF86) -> 0 | AI86: ='TOTALS&AVERAGES'!N86 | AJ86: =AI86-AH86 -> 0
A87: =JAN!A87 | AH87: =sum(B87:AF87) -> 0 | AI87: ='TOTALS&AVERAGES'!N87 | AJ87: =AI87-AH87 -> 0
A88: =JAN!A88 | AH88: =sum(B88:AF88) -> 0 | AI88: ='TOTALS&AVERAGES'!N88 | AJ88: =AI88-AH88 -> 0
A89: =JAN!A89 | AH89: =sum(B89:AF89) -> 0 | AI89: ='TOTALS&AVERAGES'!N89 | AJ89: =AI89-AH89 -> 0
A90: =JAN!A90 | AH90: =sum(B90:AF90) -> 0 | AI90: ='TOTALS&AVERAGES'!N90 | AJ90: =AI90-AH90 -> 0
A91: =JAN!A91 | AH91: =sum(B91:AF91) -> 0 | AI91: ='TOTALS&AVERAGES'!N91 | AJ91: =AI91-AH91 -> 0
A92: =JAN!A92 | B92: =SUM(B93:B106) -> 0 | C92: =SUM(C93:C106) -> 0 | D92: =SUM(D93:D106) -> 0 | E92: =SUM(E93:E106) -> 0 | F92: =SUM(F93:F106) -> 0 | G92: =SUM(G93:G106) -> 0 | H92: =SUM(H93:H106) -> 0 | I92: =SUM(I93:I106) -> 0 | ... AJ92: =SUM(AJ93:AJ106) -> 0
A93: =JAN!A93 | AH93: =sum(B93:AF93) -> 0 | AI93: ='TOTALS&AVERAGES'!N93 | AJ93: =AI93-AH93 -> 0
A94: =JAN!A94 | AH94: =sum(B94:AF94) -> 0 | AI94: ='TOTALS&AVERAGES'!N94 | AJ94: =AI94-AH94 -> 0
A95: =JAN!A95 | B95: * | AH95: =sum(B95:AF95) -> 0 | AI95: ='TOTALS&AVERAGES'!N95 | AJ95: =AI95-AH95 -> 0
A96: =JAN!A96 | AH96: =sum(B96:AF96) -> 0 | AI96: ='TOTALS&AVERAGES'!N96 | AJ96: =AI96-AH96 -> 0
A97: =JAN!A97 | AH97: =sum(B97:AF97) -> 0 | AI97: ='TOTALS&AVERAGES'!N97 | AJ97: =AI97-AH97 -> 0
A98: =JAN!A98 | AH98: =sum(B98:AF98) -> 0 | AI98: ='TOTALS&AVERAGES'!N98 | AJ98: =AI98-AH98 -> 0
A99: =JAN!A99 | B99: * | AH99: =sum(B99:AF99) -> 0 | AI99: ='TOTALS&AVERAGES'!N99 | AJ99: =AI99-AH99 -> 0
A100: =JAN!A100 | B100: * | AH100: =sum(B100:AF100) -> 0 | AI100: ='TOTALS&AVERAGES'!N100 | AJ100: =AI100-AH100 -> 0
...

Sheet JUN
A1: JUNE | B1: Monthly Regular Bills | C1: 46174 | D1: =C1+1 -> 46175 | E1: =D1+1 -> 46176 | F1: =E1+1 -> 46177 | G1: =F1+1 -> 46178 | H1: =G1+1 -> 46179 | I1: =H1+1 -> 46180 | J1: =I1+1 -> 46181 | K1: =J1+1 -> 46182 | ... AG1: =AF1+1 -> 46204 | AH1: TOTALS | AI1: SPENDING PLAN | AJ1: DIFFERENCE
A2: INCOME
A3: =JAN!A3 -> Main Job | AH3: =sum(B3:AF3) -> 0 | AI3: ='TOTALS&AVERAGES'!N3 | AJ3: =AI3-AH3 -> 0
A4: =JAN!A4 -> B Job | AH4: =sum(B4:AF4) -> 0 | AI4: ='TOTALS&AVERAGES'!N4 | AJ4: =AI4-AH4 -> 0
A5: =JAN!A5 -> Bonuses | AH5: =sum(B5:AF5) -> 0 | AI5: ='TOTALS&AVERAGES'!N5 | AJ5: =AI5-AH5 -> 0
A6: =JAN!A6 -> Gifts/Discounts | AH6: =sum(B6:AF6) -> 0 | AI6: ='TOTALS&AVERAGES'!N6 | AJ6: =AI6-AH6 -> 0
A7: =JAN!A7 -> Reimbursement | AH7: =sum(B7:AF7) -> 0 | AI7: ='TOTALS&AVERAGES'!N7 | AJ7: =AI7-AH7 -> 0
A8: =JAN!A8 -> Government Assistance | AH8: =sum(B8:AF8) -> 0 | AI8: ='TOTALS&AVERAGES'!N8 | AJ8: =AI8-AH8 -> 0
A9: =JAN!A9 -> Side Hustles | AH9: =sum(B9:AF9) -> 0 | AI9: ='TOTALS&AVERAGES'!N9 | AJ9: =AI9-AH9 -> 0
A10: =JAN!A10 -> Interest/Rewards | AH10: =sum(B10:AF10) -> 0 | AI10: ='TOTALS&AVERAGES'!N10 | AJ10: =AI10-AH10 -> 0
A11: =JAN!A11 -> VA Benefits | AH11: =sum(B11:AF11) -> 0 | AI11: ='TOTALS&AVERAGES'!N11 | AJ11: =AI11-AH11 -> 0
A12: =JAN!A12 -> Asset Cash Out | AH12: =sum(B12:AF12) -> 0 | AI12: ='TOTALS&AVERAGES'!N12 | AJ12: =AI12-AH12 -> 0
A13: =JAN!A13 -> Fed Tax Refund | AH13: =sum(B13:AF13) -> 0 | AI13: ='TOTALS&AVERAGES'!N13 | AJ13: =AI13-AH13 -> 0
A14: =JAN!A14 -> State Tax Refund | AH14: =sum(B14:AF14) -> 0 | AI14: ='TOTALS&AVERAGES'!N14 | AJ14: =AI14-AH14 -> 0
A15: TOTAL INCOME BEFORE TAXES | B15: =SUM(C3:AH14) -> 0 | C15: =SUM(C3:C14) -> 0 | D15: =SUM(D3:D14) -> 0 | E15: =SUM(E3:E14) -> 0 | F15: =SUM(F3:F14) -> 0 | G15: =SUM(G3:G14) -> 0 | H15: =SUM(H3:H14) -> 0 | I15: =SUM(I3:I14) -> 0 | J15: =SUM(J3:J14) -> 0 | ... AJ15: =SUM(AJ3:AJ14) -> 0
A16: EXPENSES BY D.A. CATEGORIES | B16: MONTHLY REGULAR BILLS
A17: 1 - SPIRITUAL | B17: =SUM(B18:B26) -> 0 | C17: =SUM(C18:C26) -> 0 | D17: =SUM(D18:D26) -> 0 | E17: =SUM(E18:E26) -> 0 | F17: =SUM(F18:F26) -> 0 | G17: =SUM(G18:G26) -> 0 | H17: =SUM(H18:H26) -> 0 | I17: =SUM(I18:I26) -> 0 | ... AJ17: =SUM(AJ18:AJ26) -> 0
A18: =JAN!A18 -> Tithing/Church Donation | AH18: =sum(B18:AF18) -> 0 | AI18: ='TOTALS&AVERAGES'!N18 | AJ18: =AI18-AH18 -> 0
A19: =JAN!A19 -> Books | AH19: =sum(B19:AF19) -> 0 | AI19: ='TOTALS&AVERAGES'!N19 | AJ19: =AI19-AH19 -> 0
A20: =JAN!A20 -> Charity | AH20: =sum(B20:AF20) -> 0 | AI20: ='TOTALS&AVERAGES'!N20 | AJ20: =AI20-AH20 -> 0
A21: =JAN!A21 -> Workshops | AH21: =sum(B21:AF21) -> 0 | AI21: ='TOTALS&AVERAGES'!N21 | AJ21: =AI21-AH21 -> 0
A22: =JAN!A22 -> Generosity | AH22: =sum(B22:AF22) -> 0 | AI22: ='TOTALS&AVERAGES'!N22 | AJ22: =AI22-AH22 -> 0
A23: =JAN!A23 -> Retreats / Seminars | AH23: =sum(B23:AF23) -> 0 | AI23: ='TOTALS&AVERAGES'!N23 | AJ23: =AI23-AH23 -> 0
A24: =JAN!A24 -> 7TH TRADITION / FELLOWSHIP/ PRG | AH24: =sum(B24:AF24) -> 0 | AI24: ='TOTALS&AVERAGES'!N24 | AJ24: =AI24-AH24 -> 0
A25: =JAN!A25 -> Conferences | AH25: =sum(B25:AF25) -> 0 | AI25: ='TOTALS&AVERAGES'!N25 | AJ25: =AI25-AH25 -> 0
A26: =JAN!A26 -> Career Investment | AH26: =sum(B26:AF26) -> 0 | AI26: ='TOTALS&AVERAGES'!N26 | AJ26: =AI26-AH26 -> 0
A27: =JAN!A27 -> Needs | B27: =SUM(B28:B43) -> 0 | C27: =SUM(C28:C43) -> 0 | D27: =SUM(D28:D43) -> 0 | E27: =SUM(E28:E43) -> 0 | F27: =SUM(F28:F43) -> 0 | G27: =SUM(G28:G43) -> 0 | H27: =SUM(H28:H43) -> 0 | I27: =SUM(I28:I43) -> 0 | ... AJ27: =SUM(AJ28:AJ43) -> 0
A28: =JAN!A28 -> Groceries | AH28: =sum(B28:AF28) -> 0 | AI28: ='TOTALS&AVERAGES'!N28 | AJ28: =AI28-AH28 -> 0
A29: =JAN!A29 -> Rent/Mortage | B29: * | AH29: =sum(B29:AF29) -> 0 | AI29: ='TOTALS&AVERAGES'!N29 | AJ29: =AI29-AH29 -> 0
A30: =JAN!A30 -> Cell Phone | B30: * | AH30: =sum(B30:AF30) -> 0 | AI30: ='TOTALS&AVERAGES'!N30 | AJ30: =AI30-AH30 -> 0
A31: =JAN!A31 -> Laundry/Cleaners | B31: * | AH31: =sum(B31:AF31) -> 0 | AI31: ='TOTALS&AVERAGES'!N31 | AJ31: =AI31-AH31 -> 0
A32: =JAN!A32 -> Car Fuel | B32: * | AH32: =sum(B32:AF32) -> 0 | AI32: ='TOTALS&AVERAGES'!N32 | AJ32: =AI32-AH32 -> 0
A33: =JAN!A33 -> Car Insurance | B33: * | AH33: =sum(B33:AF33) -> 0 | AI33: ='TOTALS&AVERAGES'!N33 | AJ33: =AI33-AH33 -> 0
A34: =JAN!A34 -> Home Items | B34: * | AH34: =sum(B34:AF34) -> 0 | AI34: ='TOTALS&AVERAGES'!N34 | AJ34: =AI34-AH34 -> 0
A35: =JAN!A35 -> Internet | AH35: =sum(B35:AF35) -> 0 | AI35: ='TOTALS&AVERAGES'!N35 | AJ35: =AI35-AH35 -> 0
A36: =JAN!A36 -> Electricity | B36: * | AH36: =sum(B36:AF36) -> 0 | AI36: ='TOTALS&AVERAGES'!N36 | AJ36: =AI36-AH36 -> 0
A37: =JAN!A37 -> Card Fees | AH37: =sum(B37:AF37) -> 0 | AI37: ='TOTALS&AVERAGES'!N37 | AJ37: =AI37-AH37 -> 0
A38: =JAN!A38 -> Moving | AH38: =sum(B38:AF38) -> 0 | AI38: ='TOTALS&AVERAGES'!N38 | AJ38: =AI38-AH38 -> 0
A39: =JAN!A39 -> Toiletries | B39: * | AH39: =sum(B39:AF39) -> 0 | AI39: ='TOTALS&AVERAGES'!N39 | AJ39: =AI39-AH39 -> 0
A40: =JAN!A40 -> Storage | B40: * | AH40: =sum(B40:AF40) -> 0 | AI40: ='TOTALS&AVERAGES'!N40 | AJ40: =AI40-AH40 -> 0
A41: =JAN!A41 -> MTA/Public Transportation | B41: * | AH41: =sum(B41:AF41) -> 0 | AI41: ='TOTALS&AVERAGES'!N41 | AJ41: =AI41-AH41 -> 0
A42: =JAN!A42 -> Health Care | AH42: =sum(B42:AF42) -> 0 | AI42: ='TOTALS&AVERAGES'!N42 | AJ42: =AI42-AH42 -> 0
A43: =JAN!A43 -> Repairs | AH43: =sum(B43:AF43) -> 0 | AI43: ='TOTALS&AVERAGES'!N43 | AJ43: =AI43-AH43 -> 0
A44: =JAN!A44 -> Wants | B44: =SUM(B45:B52) -> 0 | C44: =SUM(C45:C52) -> 0 | D44: =SUM(D45:D52) -> 0 | E44: =SUM(E45:E52) -> 0 | F44: =SUM(F45:F52) -> 0 | G44: =SUM(G45:G52) -> 0 | H44: =SUM(H45:H52) -> 0 | I44: =SUM(I45:I52) -> 0 | ... AJ44: =SUM(AJ45:AJ52) -> 0
A45: =JAN!A45 -> Clothes | AH45: =sum(B45:AF45) -> 0 | AI45: ='TOTALS&AVERAGES'!N45 | AJ45: =AI45-AH45 -> 0
A46: =JAN!A46 -> Haircuts | AH46: =sum(B46:AF46) -> 0 | AI46: ='TOTALS&AVERAGES'!N46 | AJ46: =AI46-AH46 -> 0
A47: =JAN!A47 -> Dining Out/Take out/Events | AH47: =sum(B47:AF47) -> 0 | AI47: ='TOTALS&AVERAGES'!N47 | AJ47: =AI47-AH47 -> 0
A48: =JAN!A48 -> Gym Membership | AH48: =sum(B48:AF48) -> 0 | AI48: ='TOTALS&AVERAGES'!N48 | AJ48: =AI48-AH48 -> 0
A49: =JAN!A49 -> Subscriptions Zoom/Paramount/Club Free/News Subsription | AH49: =sum(B49:AF49) -> 0 | AI49: ='TOTALS&AVERAGES'!N49 | AJ49: =AI49-AH49 -> 0
A50: =JAN!A50 -> Snacks | AH50: =sum(B50:AF50) -> 0 | AI50: ='TOTALS&AVERAGES'!N50 | AJ50: =AI50-AH50 -> 0
A51: =JAN!A51 -> Vacations/Trip to see Brother Bryant/Trip to NM/Trip to San Antonio | AH51: =sum(B51:AF51) -> 0 | AI51: ='TOTALS&AVERAGES'!N51 | AJ51: =AI51-AH51 -> 0
A52: =JAN!A52 -> Other/Misc | AH52: =sum(B52:AF52) -> 0 | AI52: ='TOTALS&AVERAGES'!N52 | AJ52: =AI52-AH52 -> 0
A53: =JAN!A53 -> Savings | B53: =SUM(B54:B67) -> 0 | C53: =SUM(C54:C67) -> 0 | D53: =SUM(D54:D67) -> 0 | E53: =SUM(E54:E67) -> 0 | F53: =SUM(F54:F67) -> 0 | G53: =SUM(G54:G67) -> 0 | H53: =SUM(H54:H67) -> 0 | I53: =SUM(I54:I67) -> 0 | ... AJ53: =SUM(AJ54:AJ67) -> 0
A54: =JAN!A54 -> High yield Savings | B54: * | AH54: =sum(B54:AF54) -> 0 | AI54: ='TOTALS&AVERAGES'!N54 | AJ54: =AI54-AH54 -> 0
A55: =JAN!A55 -> Emergency Fund | B55: * | AH55: =sum(B55:AF55) -> 0 | AI55: ='TOTALS&AVERAGES'!N55 | AJ55: =AI55-AH55 -> 0
A56: =JAN!A56 -> Stocks/Index Fund | B56: * | AH56: =sum(B56:AF56) -> 0 | AI56: ='TOTALS&AVERAGES'!N56 | AJ56: =AI56-AH56 -> 0
A57: =JAN!A57 -> Real Estate | AH57: =sum(B57:AF57) -> 0 | AI57: ='TOTALS&AVERAGES'!N57 | AJ57: =AI57-AH57 -> 0
A58: =JAN!A58 -> Extra Debt Payment | AH58: =sum(B58:AF58) -> 0 | AI58: ='TOTALS&AVERAGES'!N58 | AJ58: =AI58-AH58 -> 0
A59: =JAN!A59 -> Gold | AH59: =sum(B59:AF59) -> 0 | AI59: ='TOTALS&AVERAGES'!N59 | AJ59: =AI59-AH59 -> 0
A60: =JAN!A60 -> Retirement/Roth IRA | AH60: =sum(B60:AF60) -> 0 | AI60: ='TOTALS&AVERAGES'!N60 | AJ60: =AI60-AH60 -> 0
A61: =JAN!A61 -> Annuities | AH61: =sum(B61:AF61) -> 0 | AI61: ='TOTALS&AVERAGES'!N61 | AJ61: =AI61-AH61 -> 0
A62: =JAN!A62 -> Life Insurance | AH62: =sum(B62:AF62) -> 0 | AI62: ='TOTALS&AVERAGES'!N62 | AJ62: =AI62-AH62 -> 0
A63: =JAN!A63 -> Watch | AH63: =sum(B63:AF63) -> 0 | AI63: ='TOTALS&AVERAGES'!N63 | AJ63: =AI63-AH63 -> 0
A64: =JAN!A64 -> CD | AH64: =sum(B64:AF64) -> 0 | AI64: ='TOTALS&AVERAGES'!N64 | AJ64: =AI64-AH64 -> 0
A65: =JAN!A65 -> Taxes Savings | AH65: =sum(B65:AF65) -> 0 | AI65: ='TOTALS&AVERAGES'!N65 | AJ65: =AI65-AH65 -> 0
A66: =JAN!A66 -> HSA | AH66: =sum(B66:AF66) -> 0 | AI66: ='TOTALS&AVERAGES'!N66 | AJ66: =AI66-AH66 -> 0
A67: =JAN!A67 -> - | AH67: =sum(B67:AF67) -> 0 | AI67: ='TOTALS&AVERAGES'!N67 | AJ67: =AI67-AH67 -> 0
A68: =JAN!A68 -> Debts | B68: =SUM(B69:B79) -> 0 | C68: =SUM(C69:C79) -> 0 | D68: =SUM(D69:D79) -> 0 | E68: =SUM(E69:E79) -> 0 | F68: =SUM(F69:F79) -> 0 | G68: =SUM(G69:G79) -> 0 | H68: =SUM(H69:H79) -> 0 | I68: =SUM(I69:I79) -> 0 | ... AJ68: =SUM(AJ69:AJ79) -> 0
A69: =JAN!A69 -> NFCU Loan 1151 | AH69: =sum(B69:AF69) -> 0 | AI69: ='TOTALS&AVERAGES'!N69 | AJ69: =AI69-AH69 -> 0
A70: =JAN!A70 -> NFCU Credit Card 8743 | AH70: =sum(B70:AF70) -> 0 | AI70: ='TOTALS&AVERAGES'!N70 | AJ70: =AI70-AH70 -> 0
A71: =JAN!A71 -> Capital One Credit Card 1057 | AH71: =sum(B71:AF71) -> 0 | AI71: ='TOTALS&AVERAGES'!N71 | AJ71: =AI71-AH71 -> 0
A72: =JAN!A72 -> Blink Fitness Collections | AH72: =sum(B72:AF72) -> 0 | AI72: ='TOTALS&AVERAGES'!N72 | AJ72: =AI72-AH72 -> 0
A73: =JAN!A73 -> T-Mobile Phone Bill | AH73: =sum(B73:AF73) -> 0 | AI73: ='TOTALS&AVERAGES'!N73 | AJ73: =AI73-AH73 -> 0
A74: =JAN!A74 -> TD Bank Collections | AH74: =sum(B74:AF74) -> 0 | AI74: ='TOTALS&AVERAGES'!N74 | AJ74: =AI74-AH74 -> 0
A75: =JAN!A75 -> Safegaurd Operations Collections | AH75: =sum(B75:AF75) -> 0 | AI75: ='TOTALS&AVERAGES'!N75 | AJ75: =AI75-AH75 -> 0
A76: =JAN!A76 -> BMCC Loan 474.03 | AH76: =sum(B76:AF76) -> 0 | AI76: ='TOTALS&AVERAGES'!N76 | AJ76: =AI76-AH76 -> 0
A77: =JAN!A77 -> Han Personal Debt (Paid) | AH77: =sum(B77:AF77) -> 0 | AI77: ='TOTALS&AVERAGES'!N77 | AJ77: =AI77-AH77 -> 0
A78: =JAN!A78 | AH78: =sum(B78:AF78) -> 0 | AI78: ='TOTALS&AVERAGES'!N78 | AJ78: =AI78-AH78 -> 0
A79: =JAN!A79 -> Total Debt: 8,551.73 | AH79: =sum(B79:AF79) -> 0 | AI79: ='TOTALS&AVERAGES'!N79 | AJ79: =AI79-AH79 -> 0
A80: =JAN!A80 -> School | B80: =SUM(B81:B91) -> 0 | C80: =SUM(C81:C91) -> 0 | D80: =SUM(D81:D91) -> 0 | E80: =SUM(E81:E91) -> 0 | F80: =SUM(F81:F91) -> 0 | G80: =SUM(G81:G91) -> 0 | H80: =SUM(H81:H91) -> 0 | I80: =SUM(I81:I91) -> 0 | ... AJ80: =SUM(AJ81:AJ91) -> 0
A81: =JAN!A81 -> Tuition | AH81: =sum(B81:AF81) -> 0 | AI81: ='TOTALS&AVERAGES'!N81 | AJ81: =AI81-AH81 -> 0
A82: =JAN!A82 -> Books | AH82: =sum(B82:AF82) -> 0 | AI82: ='TOTALS&AVERAGES'!N82 | AJ82: =AI82-AH82 -> 0
A83: =JAN!A83 | AH83: =sum(B83:AF83) -> 0 | AI83: ='TOTALS&AVERAGES'!N83 | AJ83: =AI83-AH83 -> 0
A84: =JAN!A84 | AH84: =sum(B84:AF84) -> 0 | AI84: ='TOTALS&AVERAGES'!N84 | AJ84: =AI84-AH84 -> 0
A85: =JAN!A85 | AH85: =sum(B85:AF85) -> 0 | AI85: ='TOTALS&AVERAGES'!N85 | AJ85: =AI85-AH85 -> 0
A86: =JAN!A86 | AH86: =sum(B86:AF86) -> 0 | AI86: ='TOTALS&AVERAGES'!N86 | AJ86: =AI86-AH86 -> 0
A87: =JAN!A87 | AH87: =sum(B87:AF87) -> 0 | AI87: ='TOTALS&AVERAGES'!N87 | AJ87: =AI87-AH87 -> 0
A88: =JAN!A88 | AH88: =sum(B88:AF88) -> 0 | AI88: ='TOTALS&AVERAGES'!N88 | AJ88: =AI88-AH88 -> 0
A89: =JAN!A89 | AH89: =sum(B89:AF89) -> 0 | AI89: ='TOTALS&AVERAGES'!N89 | AJ89: =AI89-AH89 -> 0
A90: =JAN!A90 | AH90: =sum(B90:AF90) -> 0 | AI90: ='TOTALS&AVERAGES'!N90 | AJ90: =AI90-AH90 -> 0
A91: =JAN!A91 | AH91: =sum(B91:AF91) -> 0 | AI91: ='TOTALS&AVERAGES'!N91 | AJ91: =AI91-AH91 -> 0
A92: =JAN!A92 | B92: =SUM(B93:B106) -> 0 | C92: =SUM(C93:C106) -> 0 | D92: =SUM(D93:D106) -> 0 | E92: =SUM(E93:E106) -> 0 | F92: =SUM(F93:F106) -> 0 | G92: =SUM(G93:G106) -> 0 | H92: =SUM(H93:H106) -> 0 | I92: =SUM(I93:I106) -> 0 | ... AJ92: =SUM(AJ93:AJ106) -> 0
A93: =JAN!A93 | AH93: =sum(B93:AF93) -> 0 | AI93: ='TOTALS&AVERAGES'!N93 | AJ93: =AI93-AH93 -> 0
A94: =JAN!A94 | AH94: =sum(B94:AF94) -> 0 | AI94: ='TOTALS&AVERAGES'!N94 | AJ94: =AI94-AH94 -> 0
A95: =JAN!A95 | B95: * | AH95: =sum(B95:AF95) -> 0 | AI95: ='TOTALS&AVERAGES'!N95 | AJ95: =AI95-AH95 -> 0
A96: =JAN!A96 | AH96: =sum(B96:AF96) -> 0 | AI96: ='TOTALS&AVERAGES'!N96 | AJ96: =AI96-AH96 -> 0
A97: =JAN!A97 | AH97: =sum(B97:AF97) -> 0 | AI97: ='TOTALS&AVERAGES'!N97 | AJ97: =AI97-AH97 -> 0
A98: =JAN!A98 | AH98: =sum(B98:AF98) -> 0 | AI98: ='TOTALS&AVERAGES'!N98 | AJ98: =AI98-AH98 -> 0
A99: =JAN!A99 | B99: * | AH99: =sum(B99:AF99) -> 0 | AI99: ='TOTALS&AVERAGES'!N99 | AJ99: =AI99-AH99 -> 0
A100: =JAN!A100 | B100: * | AH100: =sum(B100:AF100) -> 0 | AI100: ='TOTALS&AVERAGES'!N100 | AJ100: =AI100-AH100 -> 0
...

Sheet JUL
A1: JUL | B1: Monthly Regular Bills | C1: 46204 | D1: =C1+1 -> 46205 | E1: =D1+1 -> 46206 | F1: =E1+1 -> 46207 | G1: =F1+1 -> 46208 | H1: =G1+1 -> 46209 | I1: =H1+1 -> 46210 | J1: =I1+1 -> 46211 | K1: =J1+1 -> 46212 | ... AG1: =AF1+1 -> 46234 | AH1: TOTALS | AI1: SPENDING PLAN | AJ1: DIFFERENCE
A2: INCOME
A3: =JAN!A3 -> Main Job | AH3: =sum(B3:AF3) -> 0 | AI3: ='TOTALS&AVERAGES'!N3 | AJ3: =AI3-AH3 -> 0
A4: =JAN!A4 -> B Job | AH4: =sum(B4:AF4) -> 0 | AI4: ='TOTALS&AVERAGES'!N4 | AJ4: =AI4-AH4 -> 0
A5: =JAN!A5 -> Bonuses | AH5: =sum(B5:AF5) -> 0 | AI5: ='TOTALS&AVERAGES'!N5 | AJ5: =AI5-AH5 -> 0
A6: =JAN!A6 -> Gifts/Discounts | AH6: =sum(B6:AF6) -> 0 | AI6: ='TOTALS&AVERAGES'!N6 | AJ6: =AI6-AH6 -> 0
A7: =JAN!A7 -> Reimbursement | AH7: =sum(B7:AF7) -> 0 | AI7: ='TOTALS&AVERAGES'!N7 | AJ7: =AI7-AH7 -> 0
A8: =JAN!A8 -> Government Assistance | AH8: =sum(B8:AF8) -> 0 | AI8: ='TOTALS&AVERAGES'!N8 | AJ8: =AI8-AH8 -> 0
A9: =JAN!A9 -> Side Hustles | AH9: =sum(B9:AF9) -> 0 | AI9: ='TOTALS&AVERAGES'!N9 | AJ9: =AI9-AH9 -> 0
A10: =JAN!A10 -> Interest/Rewards | AH10: =sum(B10:AF10) -> 0 | AI10: ='TOTALS&AVERAGES'!N10 | AJ10: =AI10-AH10 -> 0
A11: =JAN!A11 -> VA Benefits | AH11: =sum(B11:AF11) -> 0 | AI11: ='TOTALS&AVERAGES'!N11 | AJ11: =AI11-AH11 -> 0
A12: =JAN!A12 -> Asset Cash Out | AH12: =sum(B12:AF12) -> 0 | AI12: ='TOTALS&AVERAGES'!N12 | AJ12: =AI12-AH12 -> 0
A13: =JAN!A13 -> Fed Tax Refund | AH13: =sum(B13:AF13) -> 0 | AI13: ='TOTALS&AVERAGES'!N13 | AJ13: =AI13-AH13 -> 0
A14: =JAN!A14 -> State Tax Refund | AH14: =sum(B14:AF14) -> 0 | AI14: ='TOTALS&AVERAGES'!N14 | AJ14: =AI14-AH14 -> 0
A15: TOTAL INCOME BEFORE TAXES | B15: =SUM(C3:AH14) -> 0 | C15: =SUM(C3:C14) -> 0 | D15: =SUM(D3:D14) -> 0 | E15: =SUM(E3:E14) -> 0 | F15: =SUM(F3:F14) -> 0 | G15: =SUM(G3:G14) -> 0 | H15: =SUM(H3:H14) -> 0 | I15: =SUM(I3:I14) -> 0 | J15: =SUM(J3:J14) -> 0 | ... AJ15: =SUM(AJ3:AJ14) -> 0
A16: EXPENSES BY D.A. CATEGORIES | B16: MONTHLY REGULAR BILLS
A17: 1 - SPIRITUAL | B17: =SUM(B18:B26) -> 0 | C17: =SUM(C18:C26) -> 0 | D17: =SUM(D18:D26) -> 0 | E17: =SUM(E18:E26) -> 0 | F17: =SUM(F18:F26) -> 0 | G17: =SUM(G18:G26) -> 0 | H17: =SUM(H18:H26) -> 0 | I17: =SUM(I18:I26) -> 0 | ... AJ17: =SUM(AJ18:AJ26) -> 0
A18: =JAN!A18 -> Tithing/Church Donation | AH18: =sum(B18:AF18) -> 0 | AI18: ='TOTALS&AVERAGES'!N18 | AJ18: =AI18-AH18 -> 0
A19: =JAN!A19 -> Books | AH19: =sum(B19:AF19) -> 0 | AI19: ='TOTALS&AVERAGES'!N19 | AJ19: =AI19-AH19 -> 0
A20: =JAN!A20 -> Charity | AH20: =sum(B20:AF20) -> 0 | AI20: ='TOTALS&AVERAGES'!N20 | AJ20: =AI20-AH20 -> 0
A21: =JAN!A21 -> Workshops | AH21: =sum(B21:AF21) -> 0 | AI21: ='TOTALS&AVERAGES'!N21 | AJ21: =AI21-AH21 -> 0
A22: =JAN!A22 -> Generosity | AH22: =sum(B22:AF22) -> 0 | AI22: ='TOTALS&AVERAGES'!N22 | AJ22: =AI22-AH22 -> 0
A23: =JAN!A23 -> Retreats / Seminars | AH23: =sum(B23:AF23) -> 0 | AI23: ='TOTALS&AVERAGES'!N23 | AJ23: =AI23-AH23 -> 0
A24: =JAN!A24 -> 7TH TRADITION / FELLOWSHIP/ PRG | AH24: =sum(B24:AF24) -> 0 | AI24: ='TOTALS&AVERAGES'!N24 | AJ24: =AI24-AH24 -> 0
A25: =JAN!A25 -> Conferences | AH25: =sum(B25:AF25) -> 0 | AI25: ='TOTALS&AVERAGES'!N25 | AJ25: =AI25-AH25 -> 0
A26: =JAN!A26 -> Career Investment | AH26: =sum(B26:AF26) -> 0 | AI26: ='TOTALS&AVERAGES'!N26 | AJ26: =AI26-AH26 -> 0
A27: =JAN!A27 -> Needs | B27: =SUM(B28:B43) -> 0 | C27: =SUM(C28:C43) -> 0 | D27: =SUM(D28:D43) -> 0 | E27: =SUM(E28:E43) -> 0 | F27: =SUM(F28:F43) -> 0 | G27: =SUM(G28:G43) -> 0 | H27: =SUM(H28:H43) -> 0 | I27: =SUM(I28:I43) -> 0 | ... AJ27: =SUM(AJ28:AJ43) -> 0
A28: =JAN!A28 -> Groceries | AH28: =sum(B28:AF28) -> 0 | AI28: ='TOTALS&AVERAGES'!N28 | AJ28: =AI28-AH28 -> 0
A29: =JAN!A29 -> Rent/Mortage | B29: * | AH29: =sum(B29:AF29) -> 0 | AI29: ='TOTALS&AVERAGES'!N29 | AJ29: =AI29-AH29 -> 0
A30: =JAN!A30 -> Cell Phone | B30: * | AH30: =sum(B30:AF30) -> 0 | AI30: ='TOTALS&AVERAGES'!N30 | AJ30: =AI30-AH30 -> 0
A31: =JAN!A31 -> Laundry/Cleaners | B31: * | AH31: =sum(B31:AF31) -> 0 | AI31: ='TOTALS&AVERAGES'!N31 | AJ31: =AI31-AH31 -> 0
A32: =JAN!A32 -> Car Fuel | B32: * | AH32: =sum(B32:AF32) -> 0 | AI32: ='TOTALS&AVERAGES'!N32 | AJ32: =AI32-AH32 -> 0
A33: =JAN!A33 -> Car Insurance | B33: * | AH33: =sum(B33:AF33) -> 0 | AI33: ='TOTALS&AVERAGES'!N33 | AJ33: =AI33-AH33 -> 0
A34: =JAN!A34 -> Home Items | B34: * | AH34: =sum(B34:AF34) -> 0 | AI34: ='TOTALS&AVERAGES'!N34 | AJ34: =AI34-AH34 -> 0
A35: =JAN!A35 -> Internet | AH35: =sum(B35:AF35) -> 0 | AI35: ='TOTALS&AVERAGES'!N35 | AJ35: =AI35-AH35 -> 0
A36: =JAN!A36 -> Electricity | B36: * | AH36: =sum(B36:AF36) -> 0 | AI36: ='TOTALS&AVERAGES'!N36 | AJ36: =AI36-AH36 -> 0
A37: =JAN!A37 -> Card Fees | AH37: =sum(B37:AF37) -> 0 | AI37: ='TOTALS&AVERAGES'!N37 | AJ37: =AI37-AH37 -> 0
A38: =JAN!A38 -> Moving | AH38: =sum(B38:AF38) -> 0 | AI38: ='TOTALS&AVERAGES'!N38 | AJ38: =AI38-AH38 -> 0
A39: =JAN!A39 -> Toiletries | B39: * | AH39: =sum(B39:AF39) -> 0 | AI39: ='TOTALS&AVERAGES'!N39 | AJ39: =AI39-AH39 -> 0
A40: =JAN!A40 -> Storage | B40: * | AH40: =sum(B40:AF40) -> 0 | AI40: ='TOTALS&AVERAGES'!N40 | AJ40: =AI40-AH40 -> 0
A41: =JAN!A41 -> MTA/Public Transportation | B41: * | AH41: =sum(B41:AF41) -> 0 | AI41: ='TOTALS&AVERAGES'!N41 | AJ41: =AI41-AH41 -> 0
A42: =JAN!A42 -> Health Care | AH42: =sum(B42:AF42) -> 0 | AI42: ='TOTALS&AVERAGES'!N42 | AJ42: =AI42-AH42 -> 0
A43: =JAN!A43 -> Repairs | AH43: =sum(B43:AF43) -> 0 | AI43: ='TOTALS&AVERAGES'!N43 | AJ43: =AI43-AH43 -> 0
A44: =JAN!A44 -> Wants | B44: =SUM(B45:B52) -> 0 | C44: =SUM(C45:C52) -> 0 | D44: =SUM(D45:D52) -> 0 | E44: =SUM(E45:E52) -> 0 | F44: =SUM(F45:F52) -> 0 | G44: =SUM(G45:G52) -> 0 | H44: =SUM(H45:H52) -> 0 | I44: =SUM(I45:I52) -> 0 | ... AJ44: =SUM(AJ45:AJ52) -> 0
A45: =JAN!A45 -> Clothes | AH45: =sum(B45:AF45) -> 0 | AI45: ='TOTALS&AVERAGES'!N45 | AJ45: =AI45-AH45 -> 0
A46: =JAN!A46 -> Haircuts | AH46: =sum(B46:AF46) -> 0 | AI46: ='TOTALS&AVERAGES'!N46 | AJ46: =AI46-AH46 -> 0
A47: =JAN!A47 -> Dining Out/Take out/Events | AH47: =sum(B47:AF47) -> 0 | AI47: ='TOTALS&AVERAGES'!N47 | AJ47: =AI47-AH47 -> 0
A48: =JAN!A48 -> Gym Membership | AH48: =sum(B48:AF48) -> 0 | AI48: ='TOTALS&AVERAGES'!N48 | AJ48: =AI48-AH48 -> 0
A49: =JAN!A49 -> Subscriptions Zoom/Paramount/Club Free/News Subsription | AH49: =sum(B49:AF49) -> 0 | AI49: ='TOTALS&AVERAGES'!N49 | AJ49: =AI49-AH49 -> 0
A50: =JAN!A50 -> Snacks | AH50: =sum(B50:AF50) -> 0 | AI50: ='TOTALS&AVERAGES'!N50 | AJ50: =AI50-AH50 -> 0
A51: =JAN!A51 -> Vacations/Trip to see Brother Bryant/Trip to NM/Trip to San Antonio | AH51: =sum(B51:AF51) -> 0 | AI51: ='TOTALS&AVERAGES'!N51 | AJ51: =AI51-AH51 -> 0
A52: =JAN!A52 -> Other/Misc | AH52: =sum(B52:AF52) -> 0 | AI52: ='TOTALS&AVERAGES'!N52 | AJ52: =AI52-AH52 -> 0
A53: =JAN!A53 -> Savings | B53: =SUM(B54:B67) -> 0 | C53: =SUM(C54:C67) -> 0 | D53: =SUM(D54:D67) -> 0 | E53: =SUM(E54:E67) -> 0 | F53: =SUM(F54:F67) -> 0 | G53: =SUM(G54:G67) -> 0 | H53: =SUM(H54:H67) -> 0 | I53: =SUM(I54:I67) -> 0 | ... AJ53: =SUM(AJ54:AJ67) -> 0
A54: =JAN!A54 -> High yield Savings | B54: * | AH54: =sum(B54:AF54) -> 0 | AI54: ='TOTALS&AVERAGES'!N54 | AJ54: =AI54-AH54 -> 0
A55: =JAN!A55 -> Emergency Fund | B55: * | AH55: =sum(B55:AF55) -> 0 | AI55: ='TOTALS&AVERAGES'!N55 | AJ55: =AI55-AH55 -> 0
A56: =JAN!A56 -> Stocks/Index Fund | B56: * | AH56: =sum(B56:AF56) -> 0 | AI56: ='TOTALS&AVERAGES'!N56 | AJ56: =AI56-AH56 -> 0
A57: =JAN!A57 -> Real Estate | AH57: =sum(B57:AF57) -> 0 | AI57: ='TOTALS&AVERAGES'!N57 | AJ57: =AI57-AH57 -> 0
A58: =JAN!A58 -> Extra Debt Payment | AH58: =sum(B58:AF58) -> 0 | AI58: ='TOTALS&AVERAGES'!N58 | AJ58: =AI58-AH58 -> 0
A59: =JAN!A59 -> Gold | AH59: =sum(B59:AF59) -> 0 | AI59: ='TOTALS&AVERAGES'!N59 | AJ59: =AI59-AH59 -> 0
A60: =JAN!A60 -> Retirement/Roth IRA | AH60: =sum(B60:AF60) -> 0 | AI60: ='TOTALS&AVERAGES'!N60 | AJ60: =AI60-AH60 -> 0
A61: =JAN!A61 -> Annuities | AH61: =sum(B61:AF61) -> 0 | AI61: ='TOTALS&AVERAGES'!N61 | AJ61: =AI61-AH61 -> 0
A62: =JAN!A62 -> Life Insurance | AH62: =sum(B62:AF62) -> 0 | AI62: ='TOTALS&AVERAGES'!N62 | AJ62: =AI62-AH62 -> 0
A63: =JAN!A63 -> Watch | AH63: =sum(B63:AF63) -> 0 | AI63: ='TOTALS&AVERAGES'!N63 | AJ63: =AI63-AH63 -> 0
A64: =JAN!A64 -> CD | AH64: =sum(B64:AF64) -> 0 | AI64: ='TOTALS&AVERAGES'!N64 | AJ64: =AI64-AH64 -> 0
A65: =JAN!A65 -> Taxes Savings | AH65: =sum(B65:AF65) -> 0 | AI65: ='TOTALS&AVERAGES'!N65 | AJ65: =AI65-AH65 -> 0
A66: =JAN!A66 -> HSA | AH66: =sum(B66:AF66) -> 0 | AI66: ='TOTALS&AVERAGES'!N66 | AJ66: =AI66-AH66 -> 0
A67: =JAN!A67 -> - | AH67: =sum(B67:AF67) -> 0 | AI67: ='TOTALS&AVERAGES'!N67 | AJ67: =AI67-AH67 -> 0
A68: =JAN!A68 -> Debts | B68: =SUM(B69:B79) -> 0 | C68: =SUM(C69:C79) -> 0 | D68: =SUM(D69:D79) -> 0 | E68: =SUM(E69:E79) -> 0 | F68: =SUM(F69:F79) -> 0 | G68: =SUM(G69:G79) -> 0 | H68: =SUM(H69:H79) -> 0 | I68: =SUM(I69:I79) -> 0 | ... AJ68: =SUM(AJ69:AJ79) -> 0
A69: =JAN!A69 -> NFCU Loan 1151 | AH69: =sum(B69:AF69) -> 0 | AI69: ='TOTALS&AVERAGES'!N69 | AJ69: =AI69-AH69 -> 0
A70: =JAN!A70 -> NFCU Credit Card 8743 | AH70: =sum(B70:AF70) -> 0 | AI70: ='TOTALS&AVERAGES'!N70 | AJ70: =AI70-AH70 -> 0
A71: =JAN!A71 -> Capital One Credit Card 1057 | AH71: =sum(B71:AF71) -> 0 | AI71: ='TOTALS&AVERAGES'!N71 | AJ71: =AI71-AH71 -> 0
A72: =JAN!A72 -> Blink Fitness Collections | AH72: =sum(B72:AF72) -> 0 | AI72: ='TOTALS&AVERAGES'!N72 | AJ72: =AI72-AH72 -> 0
A73: =JAN!A73 -> T-Mobile Phone Bill | AH73: =sum(B73:AF73) -> 0 | AI73: ='TOTALS&AVERAGES'!N73 | AJ73: =AI73-AH73 -> 0
A74: =JAN!A74 -> TD Bank Collections | AH74: =sum(B74:AF74) -> 0 | AI74: ='TOTALS&AVERAGES'!N74 | AJ74: =AI74-AH74 -> 0
A75: =JAN!A75 -> Safegaurd Operations Collections | AH75: =sum(B75:AF75) -> 0 | AI75: ='TOTALS&AVERAGES'!N75 | AJ75: =AI75-AH75 -> 0
A76: =JAN!A76 -> BMCC Loan 474.03 | AH76: =sum(B76:AF76) -> 0 | AI76: ='TOTALS&AVERAGES'!N76 | AJ76: =AI76-AH76 -> 0
A77: =JAN!A77 -> Han Personal Debt (Paid) | AH77: =sum(B77:AF77) -> 0 | AI77: ='TOTALS&AVERAGES'!N77 | AJ77: =AI77-AH77 -> 0
A78: =JAN!A78 | AH78: =sum(B78:AF78) -> 0 | AI78: ='TOTALS&AVERAGES'!N78 | AJ78: =AI78-AH78 -> 0
A79: =JAN!A79 -> Total Debt: 8,551.73 | AH79: =sum(B79:AF79) -> 0 | AI79: ='TOTALS&AVERAGES'!N79 | AJ79: =AI79-AH79 -> 0
A80: =JAN!A80 -> School | B80: =SUM(B81:B91) -> 0 | C80: =SUM(C81:C91) -> 0 | D80: =SUM(D81:D91) -> 0 | E80: =SUM(E81:E91) -> 0 | F80: =SUM(F81:F91) -> 0 | G80: =SUM(G81:G91) -> 0 | H80: =SUM(H81:H91) -> 0 | I80: =SUM(I81:I91) -> 0 | ... AJ80: =SUM(AJ81:AJ91) -> 0
A81: =JAN!A81 -> Tuition | AH81: =sum(B81:AF81) -> 0 | AI81: ='TOTALS&AVERAGES'!N81 | AJ81: =AI81-AH81 -> 0
A82: =JAN!A82 -> Books | AH82: =sum(B82:AF82) -> 0 | AI82: ='TOTALS&AVERAGES'!N82 | AJ82: =AI82-AH82 -> 0
A83: =JAN!A83 | AH83: =sum(B83:AF83) -> 0 | AI83: ='TOTALS&AVERAGES'!N83 | AJ83: =AI83-AH83 -> 0
A84: =JAN!A84 | AH84: =sum(B84:AF84) -> 0 | AI84: ='TOTALS&AVERAGES'!N84 | AJ84: =AI84-AH84 -> 0
A85: =JAN!A85 | AH85: =sum(B85:AF85) -> 0 | AI85: ='TOTALS&AVERAGES'!N85 | AJ85: =AI85-AH85 -> 0
A86: =JAN!A86 | AH86: =sum(B86:AF86) -> 0 | AI86: ='TOTALS&AVERAGES'!N86 | AJ86: =AI86-AH86 -> 0
A87: =JAN!A87 | AH87: =sum(B87:AF87) -> 0 | AI87: ='TOTALS&AVERAGES'!N87 | AJ87: =AI87-AH87 -> 0
A88: =JAN!A88 | AH88: =sum(B88:AF88) -> 0 | AI88: ='TOTALS&AVERAGES'!N88 | AJ88: =AI88-AH88 -> 0
A89: =JAN!A89 | AH89: =sum(B89:AF89) -> 0 | AI89: ='TOTALS&AVERAGES'!N89 | AJ89: =AI89-AH89 -> 0
A90: =JAN!A90 | AH90: =sum(B90:AF90) -> 0 | AI90: ='TOTALS&AVERAGES'!N90 | AJ90: =AI90-AH90 -> 0
A91: =JAN!A91 | AH91: =sum(B91:AF91) -> 0 | AI91: ='TOTALS&AVERAGES'!N91 | AJ91: =AI91-AH91 -> 0
A92: =JAN!A92 | B92: =SUM(B93:B106) -> 0 | C92: =SUM(C93:C106) -> 0 | D92: =SUM(D93:D106) -> 0 | E92: =SUM(E93:E106) -> 0 | F92: =SUM(F93:F106) -> 0 | G92: =SUM(G93:G106) -> 0 | H92: =SUM(H93:H106) -> 0 | I92: =SUM(I93:I106) -> 0 | ... AJ92: =SUM(AJ93:AJ106) -> 0
A93: =JAN!A93 | AH93: =sum(B93:AF93) -> 0 | AI93: ='TOTALS&AVERAGES'!N93 | AJ93: =AI93-AH93 -> 0
A94: =JAN!A94 | AH94: =sum(B94:AF94) -> 0 | AI94: ='TOTALS&AVERAGES'!N94 | AJ94: =AI94-AH94 -> 0
A95: =JAN!A95 | B95: * | AH95: =sum(B95:AF95) -> 0 | AI95: ='TOTALS&AVERAGES'!N95 | AJ95: =AI95-AH95 -> 0
A96: =JAN!A96 | AH96: =sum(B96:AF96) -> 0 | AI96: ='TOTALS&AVERAGES'!N96 | AJ96: =AI96-AH96 -> 0
A97: =JAN!A97 | AH97: =sum(B97:AF97) -> 0 | AI97: ='TOTALS&AVERAGES'!N97 | AJ97: =AI97-AH97 -> 0
A98: =JAN!A98 | AH98: =sum(B98:AF98) -> 0 | AI98: ='TOTALS&AVERAGES'!N98 | AJ98: =AI98-AH98 -> 0
A99: =JAN!A99 | B99: * | AH99: =sum(B99:AF99) -> 0 | AI99: ='TOTALS&AVERAGES'!N99 | AJ99: =AI99-AH99 -> 0
A100: =JAN!A100 | B100: * | AH100: =sum(B100:AF100) -> 0 | AI100: ='TOTALS&AVERAGES'!N100 | AJ100: =AI100-AH100 -> 0
...

Sheet AUG
A1: AUGUST | B1: Monthly Regular Bills | C1: 46235 | D1: =C1+1 -> 46236 | E1: =D1+1 -> 46237 | F1: =E1+1 -> 46238 | G1: =F1+1 -> 46239 | H1: =G1+1 -> 46240 | I1: =H1+1 -> 46241 | J1: =I1+1 -> 46242 | K1: =J1+1 -> 46243 | ... AG1: =AF1+1 -> 46265 | AH1: TOTALS | AI1: SPENDING PLAN | AJ1: DIFFERENCE
A2: INCOME
A3: =JAN!A3 -> Main Job | AH3: =sum(B3:AF3) -> 0 | AI3: ='TOTALS&AVERAGES'!N3 | AJ3: =AI3-AH3 -> 0
A4: =JAN!A4 -> B Job | AH4: =sum(B4:AF4) -> 0 | AI4: ='TOTALS&AVERAGES'!N4 | AJ4: =AI4-AH4 -> 0
A5: =JAN!A5 -> Bonuses | AH5: =sum(B5:AF5) -> 0 | AI5: ='TOTALS&AVERAGES'!N5 | AJ5: =AI5-AH5 -> 0
A6: =JAN!A6 -> Gifts/Discounts | AH6: =sum(B6:AF6) -> 0 | AI6: ='TOTALS&AVERAGES'!N6 | AJ6: =AI6-AH6 -> 0
A7: =JAN!A7 -> Reimbursement | AH7: =sum(B7:AF7) -> 0 | AI7: ='TOTALS&AVERAGES'!N7 | AJ7: =AI7-AH7 -> 0
A8: =JAN!A8 -> Government Assistance | AH8: =sum(B8:AF8) -> 0 | AI8: ='TOTALS&AVERAGES'!N8 | AJ8: =AI8-AH8 -> 0
A9: =JAN!A9 -> Side Hustles | AH9: =sum(B9:AF9) -> 0 | AI9: ='TOTALS&AVERAGES'!N9 | AJ9: =AI9-AH9 -> 0
A10: =JAN!A10 -> Interest/Rewards | AH10: =sum(B10:AF10) -> 0 | AI10: ='TOTALS&AVERAGES'!N10 | AJ10: =AI10-AH10 -> 0
A11: =JAN!A11 -> VA Benefits | AH11: =sum(B11:AF11) -> 0 | AI11: ='TOTALS&AVERAGES'!N11 | AJ11: =AI11-AH11 -> 0
A12: =JAN!A12 -> Asset Cash Out | AH12: =sum(B12:AF12) -> 0 | AI12: ='TOTALS&AVERAGES'!N12 | AJ12: =AI12-AH12 -> 0
A13: =JAN!A13 -> Fed Tax Refund | AH13: =sum(B13:AF13) -> 0 | AI13: ='TOTALS&AVERAGES'!N13 | AJ13: =AI13-AH13 -> 0
A14: =JAN!A14 -> State Tax Refund | AH14: =sum(B14:AF14) -> 0 | AI14: ='TOTALS&AVERAGES'!N14 | AJ14: =AI14-AH14 -> 0
A15: TOTAL INCOME BEFORE TAXES | B15: =SUM(C3:AH14) -> 0 | C15: =SUM(C3:C14) -> 0 | D15: =SUM(D3:D14) -> 0 | E15: =SUM(E3:E14) -> 0 | F15: =SUM(F3:F14) -> 0 | G15: =SUM(G3:G14) -> 0 | H15: =SUM(H3:H14) -> 0 | I15: =SUM(I3:I14) -> 0 | J15: =SUM(J3:J14) -> 0 | ... AJ15: =SUM(AJ3:AJ14) -> 0
A16: EXPENSES BY D.A. CATEGORIES | B16: MONTHLY REGULAR BILLS
A17: 1 - SPIRITUAL | B17: =SUM(B18:B26) -> 0 | C17: =SUM(C18:C26) -> 0 | D17: =SUM(D18:D26) -> 0 | E17: =SUM(E18:E26) -> 0 | F17: =SUM(F18:F26) -> 0 | G17: =SUM(G18:G26) -> 0 | H17: =SUM(H18:H26) -> 0 | I17: =SUM(I18:I26) -> 0 | ... AJ17: =SUM(AJ18:AJ26) -> 0
A18: =JAN!A18 -> Tithing/Church Donation | AH18: =sum(B18:AF18) -> 0 | AI18: ='TOTALS&AVERAGES'!N18 | AJ18: =AI18-AH18 -> 0
A19: =JAN!A19 -> Books | AH19: =sum(B19:AF19) -> 0 | AI19: ='TOTALS&AVERAGES'!N19 | AJ19: =AI19-AH19 -> 0
A20: =JAN!A20 -> Charity | AH20: =sum(B20:AF20) -> 0 | AI20: ='TOTALS&AVERAGES'!N20 | AJ20: =AI20-AH20 -> 0
A21: =JAN!A21 -> Workshops | AH21: =sum(B21:AF21) -> 0 | AI21: ='TOTALS&AVERAGES'!N21 | AJ21: =AI21-AH21 -> 0
A22: =JAN!A22 -> Generosity | AH22: =sum(B22:AF22) -> 0 | AI22: ='TOTALS&AVERAGES'!N22 | AJ22: =AI22-AH22 -> 0
A23: =JAN!A23 -> Retreats / Seminars | AH23: =sum(B23:AF23) -> 0 | AI23: ='TOTALS&AVERAGES'!N23 | AJ23: =AI23-AH23 -> 0
A24: =JAN!A24 -> 7TH TRADITION / FELLOWSHIP/ PRG | AH24: =sum(B24:AF24) -> 0 | AI24: ='TOTALS&AVERAGES'!N24 | AJ24: =AI24-AH24 -> 0
A25: =JAN!A25 -> Conferences | AH25: =sum(B25:AF25) -> 0 | AI25: ='TOTALS&AVERAGES'!N25 | AJ25: =AI25-AH25 -> 0
A26: =JAN!A26 -> Career Investment | AH26: =sum(B26:AF26) -> 0 | AI26: ='TOTALS&AVERAGES'!N26 | AJ26: =AI26-AH26 -> 0
A27: =JAN!A27 -> Needs | B27: =SUM(B28:B43) -> 0 | C27: =SUM(C28:C43) -> 0 | D27: =SUM(D28:D43) -> 0 | E27: =SUM(E28:E43) -> 0 | F27: =SUM(F28:F43) -> 0 | G27: =SUM(G28:G43) -> 0 | H27: =SUM(H28:H43) -> 0 | I27: =SUM(I28:I43) -> 0 | ... AJ27: =SUM(AJ28:AJ43) -> 0
A28: =JAN!A28 -> Groceries | AH28: =sum(B28:AF28) -> 0 | AI28: ='TOTALS&AVERAGES'!N28 | AJ28: =AI28-AH28 -> 0
A29: =JAN!A29 -> Rent/Mortage | B29: * | AH29: =sum(B29:AF29) -> 0 | AI29: ='TOTALS&AVERAGES'!N29 | AJ29: =AI29-AH29 -> 0
A30: =JAN!A30 -> Cell Phone | B30: * | AH30: =sum(B30:AF30) -> 0 | AI30: ='TOTALS&AVERAGES'!N30 | AJ30: =AI30-AH30 -> 0
A31: =JAN!A31 -> Laundry/Cleaners | B31: * | AH31: =sum(B31:AF31) -> 0 | AI31: ='TOTALS&AVERAGES'!N31 | AJ31: =AI31-AH31 -> 0
A32: =JAN!A32 -> Car Fuel | B32: * | AH32: =sum(B32:AF32) -> 0 | AI32: ='TOTALS&AVERAGES'!N32 | AJ32: =AI32-AH32 -> 0
A33: =JAN!A33 -> Car Insurance | B33: * | AH33: =sum(B33:AF33) -> 0 | AI33: ='TOTALS&AVERAGES'!N33 | AJ33: =AI33-AH33 -> 0
A34: =JAN!A34 -> Home Items | B34: * | AH34: =sum(B34:AF34) -> 0 | AI34: ='TOTALS&AVERAGES'!N34 | AJ34: =AI34-AH34 -> 0
A35: =JAN!A35 -> Internet | AH35: =sum(B35:AF35) -> 0 | AI35: ='TOTALS&AVERAGES'!N35 | AJ35: =AI35-AH35 -> 0
A36: =JAN!A36 -> Electricity | B36: * | AH36: =sum(B36:AF36) -> 0 | AI36: ='TOTALS&AVERAGES'!N36 | AJ36: =AI36-AH36 -> 0
A37: =JAN!A37 -> Card Fees | AH37: =sum(B37:AF37) -> 0 | AI37: ='TOTALS&AVERAGES'!N37 | AJ37: =AI37-AH37 -> 0
A38: =JAN!A38 -> Moving | AH38: =sum(B38:AF38) -> 0 | AI38: ='TOTALS&AVERAGES'!N38 | AJ38: =AI38-AH38 -> 0
A39: =JAN!A39 -> Toiletries | B39: * | AH39: =sum(B39:AF39) -> 0 | AI39: ='TOTALS&AVERAGES'!N39 | AJ39: =AI39-AH39 -> 0
A40: =JAN!A40 -> Storage | B40: * | AH40: =sum(B40:AF40) -> 0 | AI40: ='TOTALS&AVERAGES'!N40 | AJ40: =AI40-AH40 -> 0
A41: =JAN!A41 -> MTA/Public Transportation | B41: * | AH41: =sum(B41:AF41) -> 0 | AI41: ='TOTALS&AVERAGES'!N41 | AJ41: =AI41-AH41 -> 0
A42: =JAN!A42 -> Health Care | AH42: =sum(B42:AF42) -> 0 | AI42: ='TOTALS&AVERAGES'!N42 | AJ42: =AI42-AH42 -> 0
A43: =JAN!A43 -> Repairs | AH43: =sum(B43:AF43) -> 0 | AI43: ='TOTALS&AVERAGES'!N43 | AJ43: =AI43-AH43 -> 0
A44: =JAN!A44 -> Wants | B44: =SUM(B45:B52) -> 0 | C44: =SUM(C45:C52) -> 0 | D44: =SUM(D45:D52) -> 0 | E44: =SUM(E45:E52) -> 0 | F44: =SUM(F45:F52) -> 0 | G44: =SUM(G45:G52) -> 0 | H44: =SUM(H45:H52) -> 0 | I44: =SUM(I45:I52) -> 0 | ... AJ44: =SUM(AJ45:AJ52) -> 0
A45: =JAN!A45 -> Clothes | AH45: =sum(B45:AF45) -> 0 | AI45: ='TOTALS&AVERAGES'!N45 | AJ45: =AI45-AH45 -> 0
A46: =JAN!A46 -> Haircuts | AH46: =sum(B46:AF46) -> 0 | AI46: ='TOTALS&AVERAGES'!N46 | AJ46: =AI46-AH46 -> 0
A47: =JAN!A47 -> Dining Out/Take out/Events | AH47: =sum(B47:AF47) -> 0 | AI47: ='TOTALS&AVERAGES'!N47 | AJ47: =AI47-AH47 -> 0
A48: =JAN!A48 -> Gym Membership | AH48: =sum(B48:AF48) -> 0 | AI48: ='TOTALS&AVERAGES'!N48 | AJ48: =AI48-AH48 -> 0
A49: =JAN!A49 -> Subscriptions Zoom/Paramount/Club Free/News Subsription | AH49: =sum(B49:AF49) -> 0 | AI49: ='TOTALS&AVERAGES'!N49 | AJ49: =AI49-AH49 -> 0
A50: =JAN!A50 -> Snacks | AH50: =sum(B50:AF50) -> 0 | AI50: ='TOTALS&AVERAGES'!N50 | AJ50: =AI50-AH50 -> 0
A51: =JAN!A51 -> Vacations/Trip to see Brother Bryant/Trip to NM/Trip to San Antonio | AH51: =sum(B51:AF51) -> 0 | AI51: ='TOTALS&AVERAGES'!N51 | AJ51: =AI51-AH51 -> 0
A52: =JAN!A52 -> Other/Misc | AH52: =sum(B52:AF52) -> 0 | AI52: ='TOTALS&AVERAGES'!N52 | AJ52: =AI52-AH52 -> 0
A53: =JAN!A53 -> Savings | B53: =SUM(B54:B67) -> 0 | C53: =SUM(C54:C67) -> 0 | D53: =SUM(D54:D67) -> 0 | E53: =SUM(E54:E67) -> 0 | F53: =SUM(F54:F67) -> 0 | G53: =SUM(G54:G67) -> 0 | H53: =SUM(H54:H67) -> 0 | I53: =SUM(I54:I67) -> 0 | ... AJ53: =SUM(AJ54:AJ67) -> 0
A54: =JAN!A54 -> High yield Savings | B54: * | AH54: =sum(B54:AF54) -> 0 | AI54: ='TOTALS&AVERAGES'!N54 | AJ54: =AI54-AH54 -> 0
A55: =JAN!A55 -> Emergency Fund | B55: * | AH55: =sum(B55:AF55) -> 0 | AI55: ='TOTALS&AVERAGES'!N55 | AJ55: =AI55-AH55 -> 0
A56: =JAN!A56 -> Stocks/Index Fund | B56: * | AH56: =sum(B56:AF56) -> 0 | AI56: ='TOTALS&AVERAGES'!N56 | AJ56: =AI56-AH56 -> 0
A57: =JAN!A57 -> Real Estate | AH57: =sum(B57:AF57) -> 0 | AI57: ='TOTALS&AVERAGES'!N57 | AJ57: =AI57-AH57 -> 0
A58: =JAN!A58 -> Extra Debt Payment | AH58: =sum(B58:AF58) -> 0 | AI58: ='TOTALS&AVERAGES'!N58 | AJ58: =AI58-AH58 -> 0
A59: =JAN!A59 -> Gold | AH59: =sum(B59:AF59) -> 0 | AI59: ='TOTALS&AVERAGES'!N59 | AJ59: =AI59-AH59 -> 0
A60: =JAN!A60 -> Retirement/Roth IRA | AH60: =sum(B60:AF60) -> 0 | AI60: ='TOTALS&AVERAGES'!N60 | AJ60: =AI60-AH60 -> 0
A61: =JAN!A61 -> Annuities | AH61: =sum(B61:AF61) -> 0 | AI61: ='TOTALS&AVERAGES'!N61 | AJ61: =AI61-AH61 -> 0
A62: =JAN!A62 -> Life Insurance | AH62: =sum(B62:AF62) -> 0 | AI62: ='TOTALS&AVERAGES'!N62 | AJ62: =AI62-AH62 -> 0
A63: =JAN!A63 -> Watch | AH63: =sum(B63:AF63) -> 0 | AI63: ='TOTALS&AVERAGES'!N63 | AJ63: =AI63-AH63 -> 0
A64: =JAN!A64 -> CD | AH64: =sum(B64:AF64) -> 0 | AI64: ='TOTALS&AVERAGES'!N64 | AJ64: =AI64-AH64 -> 0
A65: =JAN!A65 -> Taxes Savings | AH65: =sum(B65:AF65) -> 0 | AI65: ='TOTALS&AVERAGES'!N65 | AJ65: =AI65-AH65 -> 0
A66: =JAN!A66 -> HSA | AH66: =sum(B66:AF66) -> 0 | AI66: ='TOTALS&AVERAGES'!N66 | AJ66: =AI66-AH66 -> 0
A67: =JAN!A67 -> - | AH67: =sum(B67:AF67) -> 0 | AI67: ='TOTALS&AVERAGES'!N67 | AJ67: =AI67-AH67 -> 0
A68: =JAN!A68 -> Debts | B68: =SUM(B69:B79) -> 0 | C68: =SUM(C69:C79) -> 0 | D68: =SUM(D69:D79) -> 0 | E68: =SUM(E69:E79) -> 0 | F68: =SUM(F69:F79) -> 0 | G68: =SUM(G69:G79) -> 0 | H68: =SUM(H69:H79) -> 0 | I68: =SUM(I69:I79) -> 0 | ... AJ68: =SUM(AJ69:AJ79) -> 0
A69: =JAN!A69 -> NFCU Loan 1151 | AH69: =sum(B69:AF69) -> 0 | AI69: ='TOTALS&AVERAGES'!N69 | AJ69: =AI69-AH69 -> 0
A70: =JAN!A70 -> NFCU Credit Card 8743 | AH70: =sum(B70:AF70) -> 0 | AI70: ='TOTALS&AVERAGES'!N70 | AJ70: =AI70-AH70 -> 0
A71: =JAN!A71 -> Capital One Credit Card 1057 | AH71: =sum(B71:AF71) -> 0 | AI71: ='TOTALS&AVERAGES'!N71 | AJ71: =AI71-AH71 -> 0
A72: =JAN!A72 -> Blink Fitness Collections | AH72: =sum(B72:AF72) -> 0 | AI72: ='TOTALS&AVERAGES'!N72 | AJ72: =AI72-AH72 -> 0
A73: =JAN!A73 -> T-Mobile Phone Bill | AH73: =sum(B73:AF73) -> 0 | AI73: ='TOTALS&AVERAGES'!N73 | AJ73: =AI73-AH73 -> 0
A74: =JAN!A74 -> TD Bank Collections | AH74: =sum(B74:AF74) -> 0 | AI74: ='TOTALS&AVERAGES'!N74 | AJ74: =AI74-AH74 -> 0
A75: =JAN!A75 -> Safegaurd Operations Collections | AH75: =sum(B75:AF75) -> 0 | AI75: ='TOTALS&AVERAGES'!N75 | AJ75: =AI75-AH75 -> 0
A76: =JAN!A76 -> BMCC Loan 474.03 | AH76: =sum(B76:AF76) -> 0 | AI76: ='TOTALS&AVERAGES'!N76 | AJ76: =AI76-AH76 -> 0
A77: =JAN!A77 -> Han Personal Debt (Paid) | AH77: =sum(B77:AF77) -> 0 | AI77: ='TOTALS&AVERAGES'!N77 | AJ77: =AI77-AH77 -> 0
A78: =JAN!A78 | AH78: =sum(B78:AF78) -> 0 | AI78: ='TOTALS&AVERAGES'!N78 | AJ78: =AI78-AH78 -> 0
A79: =JAN!A79 -> Total Debt: 8,551.73 | AH79: =sum(B79:AF79) -> 0 | AI79: ='TOTALS&AVERAGES'!N79 | AJ79: =AI79-AH79 -> 0
A80: =JAN!A80 -> School | B80: =SUM(B81:B91) -> 0 | C80: =SUM(C81:C91) -> 0 | D80: =SUM(D81:D91) -> 0 | E80: =SUM(E81:E91) -> 0 | F80: =SUM(F81:F91) -> 0 | G80: =SUM(G81:G91) -> 0 | H80: =SUM(H81:H91) -> 0 | I80: =SUM(I81:I91) -> 0 | ... AJ80: =SUM(AJ81:AJ91) -> 0
A81: =JAN!A81 -> Tuition | AH81: =sum(B81:AF81) -> 0 | AI81: ='TOTALS&AVERAGES'!N81 | AJ81: =AI81-AH81 -> 0
A82: =JAN!A82 -> Books | AH82: =sum(B82:AF82) -> 0 | AI82: ='TOTALS&AVERAGES'!N82 | AJ82: =AI82-AH82 -> 0
A83: =JAN!A83 | AH83: =sum(B83:AF83) -> 0 | AI83: ='TOTALS&AVERAGES'!N83 | AJ83: =AI83-AH83 -> 0
A84: =JAN!A84 | AH84: =sum(B84:AF84) -> 0 | AI84: ='TOTALS&AVERAGES'!N84 | AJ84: =AI84-AH84 -> 0
A85: =JAN!A85 | AH85: =sum(B85:AF85) -> 0 | AI85: ='TOTALS&AVERAGES'!N85 | AJ85: =AI85-AH85 -> 0
A86: =JAN!A86 | AH86: =sum(B86:AF86) -> 0 | AI86: ='TOTALS&AVERAGES'!N86 | AJ86: =AI86-AH86 -> 0
A87: =JAN!A87 | AH87: =sum(B87:AF87) -> 0 | AI87: ='TOTALS&AVERAGES'!N87 | AJ87: =AI87-AH87 -> 0
A88: =JAN!A88 | AH88: =sum(B88:AF88) -> 0 | AI88: ='TOTALS&AVERAGES'!N88 | AJ88: =AI88-AH88 -> 0
A89: =JAN!A89 | AH89: =sum(B89:AF89) -> 0 | AI89: ='TOTALS&AVERAGES'!N89 | AJ89: =AI89-AH89 -> 0
A90: =JAN!A90 | AH90: =sum(B90:AF90) -> 0 | AI90: ='TOTALS&AVERAGES'!N90 | AJ90: =AI90-AH90 -> 0
A91: =JAN!A91 | AH91: =sum(B91:AF91) -> 0 | AI91: ='TOTALS&AVERAGES'!N91 | AJ91: =AI91-AH91 -> 0
A92: =JAN!A92 | B92: =SUM(B93:B106) -> 0 | C92: =SUM(C93:C106) -> 0 | D92: =SUM(D93:D106) -> 0 | E92: =SUM(E93:E106) -> 0 | F92: =SUM(F93:F106) -> 0 | G92: =SUM(G93:G106) -> 0 | H92: =SUM(H93:H106) -> 0 | I92: =SUM(I93:I106) -> 0 | ... AJ92: =SUM(AJ93:AJ106) -> 0
A93: =JAN!A93 | AH93: =sum(B93:AF93) -> 0 | AI93: ='TOTALS&AVERAGES'!N93 | AJ93: =AI93-AH93 -> 0
A94: =JAN!A94 | AH94: =sum(B94:AF94) -> 0 | AI94: ='TOTALS&AVERAGES'!N94 | AJ94: =AI94-AH94 -> 0
A95: =JAN!A95 | B95: * | AH95: =sum(B95:AF95) -> 0 | AI95: ='TOTALS&AVERAGES'!N95 | AJ95: =AI95-AH95 -> 0
A96: =JAN!A96 | AH96: =sum(B96:AF96) -> 0 | AI96: ='TOTALS&AVERAGES'!N96 | AJ96: =AI96-AH96 -> 0
A97: =JAN!A97 | AH97: =sum(B97:AF97) -> 0 | AI97: ='TOTALS&AVERAGES'!N97 | AJ97: =AI97-AH97 -> 0
A98: =JAN!A98 | AH98: =sum(B98:AF98) -> 0 | AI98: ='TOTALS&AVERAGES'!N98 | AJ98: =AI98-AH98 -> 0
A99: =JAN!A99 | B99: * | AH99: =sum(B99:AF99) -> 0 | AI99: ='TOTALS&AVERAGES'!N99 | AJ99: =AI99-AH99 -> 0
A100: =JAN!A100 | B100: * | AH100: =sum(B100:AF100) -> 0 | AI100: ='TOTALS&AVERAGES'!N100 | AJ100: =AI100-AH100 -> 0
...

Sheet SEP
A1: SEPTEMBER | B1: Monthly Regular Bills | C1: 46266 | D1: =C1+1 -> 46267 | E1: =D1+1 -> 46268 | F1: =E1+1 -> 46269 | G1: =F1+1 -> 46270 | H1: =G1+1 -> 46271 | I1: =H1+1 -> 46272 | J1: =I1+1 -> 46273 | K1: =J1+1 -> 46274 | ... AG1: =AF1+1 -> 46296 | AH1: TOTALS | AI1: SPENDING PLAN | AJ1: DIFFERENCE
A2: INCOME
A3: =JAN!A3 -> Main Job | AH3: =sum(B3:AF3) -> 0 | AI3: ='TOTALS&AVERAGES'!N3 | AJ3: =AI3-AH3 -> 0
A4: =JAN!A4 -> B Job | AH4: =sum(B4:AF4) -> 0 | AI4: ='TOTALS&AVERAGES'!N4 | AJ4: =AI4-AH4 -> 0
A5: =JAN!A5 -> Bonuses | AH5: =sum(B5:AF5) -> 0 | AI5: ='TOTALS&AVERAGES'!N5 | AJ5: =AI5-AH5 -> 0
A6: =JAN!A6 -> Gifts/Discounts | AH6: =sum(B6:AF6) -> 0 | AI6: ='TOTALS&AVERAGES'!N6 | AJ6: =AI6-AH6 -> 0
A7: =JAN!A7 -> Reimbursement | AH7: =sum(B7:AF7) -> 0 | AI7: ='TOTALS&AVERAGES'!N7 | AJ7: =AI7-AH7 -> 0
A8: =JAN!A8 -> Government Assistance | AH8: =sum(B8:AF8) -> 0 | AI8: ='TOTALS&AVERAGES'!N8 | AJ8: =AI8-AH8 -> 0
A9: =JAN!A9 -> Side Hustles | AH9: =sum(B9:AF9) -> 0 | AI9: ='TOTALS&AVERAGES'!N9 | AJ9: =AI9-AH9 -> 0
A10: =JAN!A10 -> Interest/Rewards | AH10: =sum(B10:AF10) -> 0 | AI10: ='TOTALS&AVERAGES'!N10 | AJ10: =AI10-AH10 -> 0
A11: =JAN!A11 -> VA Benefits | AH11: =sum(B11:AF11) -> 0 | AI11: ='TOTALS&AVERAGES'!N11 | AJ11: =AI11-AH11 -> 0
A12: =JAN!A12 -> Asset Cash Out | AH12: =sum(B12:AF12) -> 0 | AI12: ='TOTALS&AVERAGES'!N12 | AJ12: =AI12-AH12 -> 0
A13: =JAN!A13 -> Fed Tax Refund | AH13: =sum(B13:AF13) -> 0 | AI13: ='TOTALS&AVERAGES'!N13 | AJ13: =AI13-AH13 -> 0
A14: =JAN!A14 -> State Tax Refund | AH14: =sum(B14:AF14) -> 0 | AI14: ='TOTALS&AVERAGES'!N14 | AJ14: =AI14-AH14 -> 0
A15: TOTAL INCOME BEFORE TAXES | B15: =SUM(C3:AH14) -> 0 | C15: =SUM(C3:C14) -> 0 | D15: =SUM(D3:D14) -> 0 | E15: =SUM(E3:E14) -> 0 | F15: =SUM(F3:F14) -> 0 | G15: =SUM(G3:G14) -> 0 | H15: =SUM(H3:H14) -> 0 | I15: =SUM(I3:I14) -> 0 | J15: =SUM(J3:J14) -> 0 | ... AJ15: =SUM(AJ3:AJ14) -> 0
A16: EXPENSES BY D.A. CATEGORIES | B16: MONTHLY REGULAR BILLS
A17: 1 - SPIRITUAL | B17: =SUM(B18:B26) -> 0 | C17: =SUM(C18:C26) -> 0 | D17: =SUM(D18:D26) -> 0 | E17: =SUM(E18:E26) -> 0 | F17: =SUM(F18:F26) -> 0 | G17: =SUM(G18:G26) -> 0 | H17: =SUM(H18:H26) -> 0 | I17: =SUM(I18:I26) -> 0 | ... AJ17: =SUM(AJ18:AJ26) -> 0
A18: =JAN!A18 -> Tithing/Church Donation | AH18: =sum(B18:AF18) -> 0 | AI18: ='TOTALS&AVERAGES'!N18 | AJ18: =AI18-AH18 -> 0
A19: =JAN!A19 -> Books | AH19: =sum(B19:AF19) -> 0 | AI19: ='TOTALS&AVERAGES'!N19 | AJ19: =AI19-AH19 -> 0
A20: =JAN!A20 -> Charity | AH20: =sum(B20:AF20) -> 0 | AI20: ='TOTALS&AVERAGES'!N20 | AJ20: =AI20-AH20 -> 0
A21: =JAN!A21 -> Workshops | AH21: =sum(B21:AF21) -> 0 | AI21: ='TOTALS&AVERAGES'!N21 | AJ21: =AI21-AH21 -> 0
A22: =JAN!A22 -> Generosity | AH22: =sum(B22:AF22) -> 0 | AI22: ='TOTALS&AVERAGES'!N22 | AJ22: =AI22-AH22 -> 0
A23: =JAN!A23 -> Retreats / Seminars | AH23: =sum(B23:AF23) -> 0 | AI23: ='TOTALS&AVERAGES'!N23 | AJ23: =AI23-AH23 -> 0
A24: =JAN!A24 -> 7TH TRADITION / FELLOWSHIP/ PRG | AH24: =sum(B24:AF24) -> 0 | AI24: ='TOTALS&AVERAGES'!N24 | AJ24: =AI24-AH24 -> 0
A25: =JAN!A25 -> Conferences | AH25: =sum(B25:AF25) -> 0 | AI25: ='TOTALS&AVERAGES'!N25 | AJ25: =AI25-AH25 -> 0
A26: =JAN!A26 -> Career Investment | AH26: =sum(B26:AF26) -> 0 | AI26: ='TOTALS&AVERAGES'!N26 | AJ26: =AI26-AH26 -> 0
A27: =JAN!A27 -> Needs | B27: =SUM(B28:B43) -> 0 | C27: =SUM(C28:C43) -> 0 | D27: =SUM(D28:D43) -> 0 | E27: =SUM(E28:E43) -> 0 | F27: =SUM(F28:F43) -> 0 | G27: =SUM(G28:G43) -> 0 | H27: =SUM(H28:H43) -> 0 | I27: =SUM(I28:I43) -> 0 | ... AJ27: =SUM(AJ28:AJ43) -> 0
A28: =JAN!A28 -> Groceries | AH28: =sum(B28:AF28) -> 0 | AI28: ='TOTALS&AVERAGES'!N28 | AJ28: =AI28-AH28 -> 0
A29: =JAN!A29 -> Rent/Mortage | B29: * | AH29: =sum(B29:AF29) -> 0 | AI29: ='TOTALS&AVERAGES'!N29 | AJ29: =AI29-AH29 -> 0
A30: =JAN!A30 -> Cell Phone | B30: * | AH30: =sum(B30:AF30) -> 0 | AI30: ='TOTALS&AVERAGES'!N30 | AJ30: =AI30-AH30 -> 0
A31: =JAN!A31 -> Laundry/Cleaners | B31: * | AH31: =sum(B31:AF31) -> 0 | AI31: ='TOTALS&AVERAGES'!N31 | AJ31: =AI31-AH31 -> 0
A32: =JAN!A32 -> Car Fuel | B32: * | AH32: =sum(B32:AF32) -> 0 | AI32: ='TOTALS&AVERAGES'!N32 | AJ32: =AI32-AH32 -> 0
A33: =JAN!A33 -> Car Insurance | B33: * | AH33: =sum(B33:AF33) -> 0 | AI33: ='TOTALS&AVERAGES'!N33 | AJ33: =AI33-AH33 -> 0
A34: =JAN!A34 -> Home Items | B34: * | AH34: =sum(B34:AF34) -> 0 | AI34: ='TOTALS&AVERAGES'!N34 | AJ34: =AI34-AH34 -> 0
A35: =JAN!A35 -> Internet | AH35: =sum(B35:AF35) -> 0 | AI35: ='TOTALS&AVERAGES'!N35 | AJ35: =AI35-AH35 -> 0
A36: =JAN!A36 -> Electricity | B36: * | AH36: =sum(B36:AF36) -> 0 | AI36: ='TOTALS&AVERAGES'!N36 | AJ36: =AI36-AH36 -> 0
A37: =JAN!A37 -> Card Fees | AH37: =sum(B37:AF37) -> 0 | AI37: ='TOTALS&AVERAGES'!N37 | AJ37: =AI37-AH37 -> 0
A38: =JAN!A38 -> Moving | AH38: =sum(B38:AF38) -> 0 | AI38: ='TOTALS&AVERAGES'!N38 | AJ38: =AI38-AH38 -> 0
A39: =JAN!A39 -> Toiletries | B39: * | AH39: =sum(B39:AF39) -> 0 | AI39: ='TOTALS&AVERAGES'!N39 | AJ39: =AI39-AH39 -> 0
A40: =JAN!A40 -> Storage | B40: * | AH40: =sum(B40:AF40) -> 0 | AI40: ='TOTALS&AVERAGES'!N40 | AJ40: =AI40-AH40 -> 0
A41: =JAN!A41 -> MTA/Public Transportation | B41: * | AH41: =sum(B41:AF41) -> 0 | AI41: ='TOTALS&AVERAGES'!N41 | AJ41: =AI41-AH41 -> 0
A42: =JAN!A42 -> Health Care | AH42: =sum(B42:AF42) -> 0 | AI42: ='TOTALS&AVERAGES'!N42 | AJ42: =AI42-AH42 -> 0
A43: =JAN!A43 -> Repairs | AH43: =sum(B43:AF43) -> 0 | AI43: ='TOTALS&AVERAGES'!N43 | AJ43: =AI43-AH43 -> 0
A44: =JAN!A44 -> Wants | B44: =SUM(B45:B52) -> 0 | C44: =SUM(C45:C52) -> 0 | D44: =SUM(D45:D52) -> 0 | E44: =SUM(E45:E52) -> 0 | F44: =SUM(F45:F52) -> 0 | G44: =SUM(G45:G52) -> 0 | H44: =SUM(H45:H52) -> 0 | I44: =SUM(I45:I52) -> 0 | ... AJ44: =SUM(AJ45:AJ52) -> 0
A45: =JAN!A45 -> Clothes | AH45: =sum(B45:AF45) -> 0 | AI45: ='TOTALS&AVERAGES'!N45 | AJ45: =AI45-AH45 -> 0
A46: =JAN!A46 -> Haircuts | AH46: =sum(B46:AF46) -> 0 | AI46: ='TOTALS&AVERAGES'!N46 | AJ46: =AI46-AH46 -> 0
A47: =JAN!A47 -> Dining Out/Take out/Events | AH47: =sum(B47:AF47) -> 0 | AI47: ='TOTALS&AVERAGES'!N47 | AJ47: =AI47-AH47 -> 0
A48: =JAN!A48 -> Gym Membership | AH48: =sum(B48:AF48) -> 0 | AI48: ='TOTALS&AVERAGES'!N48 | AJ48: =AI48-AH48 -> 0
A49: =JAN!A49 -> Subscriptions Zoom/Paramount/Club Free/News Subsription | AH49: =sum(B49:AF49) -> 0 | AI49: ='TOTALS&AVERAGES'!N49 | AJ49: =AI49-AH49 -> 0
A50: =JAN!A50 -> Snacks | AH50: =sum(B50:AF50) -> 0 | AI50: ='TOTALS&AVERAGES'!N50 | AJ50: =AI50-AH50 -> 0
A51: =JAN!A51 -> Vacations/Trip to see Brother Bryant/Trip to NM/Trip to San Antonio | AH51: =sum(B51:AF51) -> 0 | AI51: ='TOTALS&AVERAGES'!N51 | AJ51: =AI51-AH51 -> 0
A52: =JAN!A52 -> Other/Misc | AH52: =sum(B52:AF52) -> 0 | AI52: ='TOTALS&AVERAGES'!N52 | AJ52: =AI52-AH52 -> 0
A53: =JAN!A53 -> Savings | B53: =SUM(B54:B67) -> 0 | C53: =SUM(C54:C67) -> 0 | D53: =SUM(D54:D67) -> 0 | E53: =SUM(E54:E67) -> 0 | F53: =SUM(F54:F67) -> 0 | G53: =SUM(G54:G67) -> 0 | H53: =SUM(H54:H67) -> 0 | I53: =SUM(I54:I67) -> 0 | ... AJ53: =SUM(AJ54:AJ67) -> 0
A54: =JAN!A54 -> High yield Savings | B54: * | AH54: =sum(B54:AF54) -> 0 | AI54: ='TOTALS&AVERAGES'!N54 | AJ54: =AI54-AH54 -> 0
A55: =JAN!A55 -> Emergency Fund | B55: * | AH55: =sum(B55:AF55) -> 0 | AI55: ='TOTALS&AVERAGES'!N55 | AJ55: =AI55-AH55 -> 0
A56: =JAN!A56 -> Stocks/Index Fund | B56: * | AH56: =sum(B56:AF56) -> 0 | AI56: ='TOTALS&AVERAGES'!N56 | AJ56: =AI56-AH56 -> 0
A57: =JAN!A57 -> Real Estate | AH57: =sum(B57:AF57) -> 0 | AI57: ='TOTALS&AVERAGES'!N57 | AJ57: =AI57-AH57 -> 0
A58: =JAN!A58 -> Extra Debt Payment | AH58: =sum(B58:AF58) -> 0 | AI58: ='TOTALS&AVERAGES'!N58 | AJ58: =AI58-AH58 -> 0
A59: =JAN!A59 -> Gold | AH59: =sum(B59:AF59) -> 0 | AI59: ='TOTALS&AVERAGES'!N59 | AJ59: =AI59-AH59 -> 0
A60: =JAN!A60 -> Retirement/Roth IRA | AH60: =sum(B60:AF60) -> 0 | AI60: ='TOTALS&AVERAGES'!N60 | AJ60: =AI60-AH60 -> 0
A61: =JAN!A61 -> Annuities | AH61: =sum(B61:AF61) -> 0 | AI61: ='TOTALS&AVERAGES'!N61 | AJ61: =AI61-AH61 -> 0
A62: =JAN!A62 -> Life Insurance | AH62: =sum(B62:AF62) -> 0 | AI62: ='TOTALS&AVERAGES'!N62 | AJ62: =AI62-AH62 -> 0
A63: =JAN!A63 -> Watch | AH63: =sum(B63:AF63) -> 0 | AI63: ='TOTALS&AVERAGES'!N63 | AJ63: =AI63-AH63 -> 0
A64: =JAN!A64 -> CD | AH64: =sum(B64:AF64) -> 0 | AI64: ='TOTALS&AVERAGES'!N64 | AJ64: =AI64-AH64 -> 0
A65: =JAN!A65 -> Taxes Savings | AH65: =sum(B65:AF65) -> 0 | AI65: ='TOTALS&AVERAGES'!N65 | AJ65: =AI65-AH65 -> 0
A66: =JAN!A66 -> HSA | AH66: =sum(B66:AF66) -> 0 | AI66: ='TOTALS&AVERAGES'!N66 | AJ66: =AI66-AH66 -> 0
A67: =JAN!A67 -> - | AH67: =sum(B67:AF67) -> 0 | AI67: ='TOTALS&AVERAGES'!N67 | AJ67: =AI67-AH67 -> 0
A68: =JAN!A68 -> Debts | B68: =SUM(B69:B79) -> 0 | C68: =SUM(C69:C79) -> 0 | D68: =SUM(D69:D79) -> 0 | E68: =SUM(E69:E79) -> 0 | F68: =SUM(F69:F79) -> 0 | G68: =SUM(G69:G79) -> 0 | H68: =SUM(H69:H79) -> 0 | I68: =SUM(I69:I79) -> 0 | ... AJ68: =SUM(AJ69:AJ79) -> 0
A69: =JAN!A69 -> NFCU Loan 1151 | AH69: =sum(B69:AF69) -> 0 | AI69: ='TOTALS&AVERAGES'!N69 | AJ69: =AI69-AH69 -> 0
A70: =JAN!A70 -> NFCU Credit Card 8743 | AH70: =sum(B70:AF70) -> 0 | AI70: ='TOTALS&AVERAGES'!N70 | AJ70: =AI70-AH70 -> 0
A71: =JAN!A71 -> Capital One Credit Card 1057 | AH71: =sum(B71:AF71) -> 0 | AI71: ='TOTALS&AVERAGES'!N71 | AJ71: =AI71-AH71 -> 0
A72: =JAN!A72 -> Blink Fitness Collections | AH72: =sum(B72:AF72) -> 0 | AI72: ='TOTALS&AVERAGES'!N72 | AJ72: =AI72-AH72 -> 0
A73: =JAN!A73 -> T-Mobile Phone Bill | AH73: =sum(B73:AF73) -> 0 | AI73: ='TOTALS&AVERAGES'!N73 | AJ73: =AI73-AH73 -> 0
A74: =JAN!A74 -> TD Bank Collections | AH74: =sum(B74:AF74) -> 0 | AI74: ='TOTALS&AVERAGES'!N74 | AJ74: =AI74-AH74 -> 0
A75: =JAN!A75 -> Safegaurd Operations Collections | AH75: =sum(B75:AF75) -> 0 | AI75: ='TOTALS&AVERAGES'!N75 | AJ75: =AI75-AH75 -> 0
A76: =JAN!A76 -> BMCC Loan 474.03 | AH76: =sum(B76:AF76) -> 0 | AI76: ='TOTALS&AVERAGES'!N76 | AJ76: =AI76-AH76 -> 0
A77: =JAN!A77 -> Han Personal Debt (Paid) | AH77: =sum(B77:AF77) -> 0 | AI77: ='TOTALS&AVERAGES'!N77 | AJ77: =AI77-AH77 -> 0
A78: =JAN!A78 | AH78: =sum(B78:AF78) -> 0 | AI78: ='TOTALS&AVERAGES'!N78 | AJ78: =AI78-AH78 -> 0
A79: =JAN!A79 -> Total Debt: 8,551.73 | AH79: =sum(B79:AF79) -> 0 | AI79: ='TOTALS&AVERAGES'!N79 | AJ79: =AI79-AH79 -> 0
A80: =JAN!A80 -> School | B80: =SUM(B81:B91) -> 0 | C80: =SUM(C81:C91) -> 0 | D80: =SUM(D81:D91) -> 0 | E80: =SUM(E81:E91) -> 0 | F80: =SUM(F81:F91) -> 0 | G80: =SUM(G81:G91) -> 0 | H80: =SUM(H81:H91) -> 0 | I80: =SUM(I81:I91) -> 0 | ... AJ80: =SUM(AJ81:AJ91) -> 0
A81: =JAN!A81 -> Tuition | AH81: =sum(B81:AF81) -> 0 | AI81: ='TOTALS&AVERAGES'!N81 | AJ81: =AI81-AH81 -> 0
A82: =JAN!A82 -> Books | AH82: =sum(B82:AF82) -> 0 | AI82: ='TOTALS&AVERAGES'!N82 | AJ82: =AI82-AH82 -> 0
A83: =JAN!A83 | AH83: =sum(B83:AF83) -> 0 | AI83: ='TOTALS&AVERAGES'!N83 | AJ83: =AI83-AH83 -> 0
A84: =JAN!A84 | AH84: =sum(B84:AF84) -> 0 | AI84: ='TOTALS&AVERAGES'!N84 | AJ84: =AI84-AH84 -> 0
A85: =JAN!A85 | AH85: =sum(B85:AF85) -> 0 | AI85: ='TOTALS&AVERAGES'!N85 | AJ85: =AI85-AH85 -> 0
A86: =JAN!A86 | AH86: =sum(B86:AF86) -> 0 | AI86: ='TOTALS&AVERAGES'!N86 | AJ86: =AI86-AH86 -> 0
A87: =JAN!A87 | AH87: =sum(B87:AF87) -> 0 | AI87: ='TOTALS&AVERAGES'!N87 | AJ87: =AI87-AH87 -> 0
A88: =JAN!A88 | AH88: =sum(B88:AF88) -> 0 | AI88: ='TOTALS&AVERAGES'!N88 | AJ88: =AI88-AH88 -> 0
A89: =JAN!A89 | AH89: =sum(B89:AF89) -> 0 | AI89: ='TOTALS&AVERAGES'!N89 | AJ89: =AI89-AH89 -> 0
A90: =JAN!A90 | AH90: =sum(B90:AF90) -> 0 | AI90: ='TOTALS&AVERAGES'!N90 | AJ90: =AI90-AH90 -> 0
A91: =JAN!A91 | AH91: =sum(B91:AF91) -> 0 | AI91: ='TOTALS&AVERAGES'!N91 | AJ91: =AI91-AH91 -> 0
A92: =JAN!A92 | B92: =SUM(B93:B106) -> 0 | C92: =SUM(C93:C106) -> 0 | D92: =SUM(D93:D106) -> 0 | E92: =SUM(E93:E106) -> 0 | F92: =SUM(F93:F106) -> 0 | G92: =SUM(G93:G106) -> 0 | H92: =SUM(H93:H106) -> 0 | I92: =SUM(I93:I106) -> 0 | ... AJ92: =SUM(AJ93:AJ106) -> 0
A93: =JAN!A93 | AH93: =sum(B93:AF93) -> 0 | AI93: ='TOTALS&AVERAGES'!N93 | AJ93: =AI93-AH93 -> 0
A94: =JAN!A94 | AH94: =sum(B94:AF94) -> 0 | AI94: ='TOTALS&AVERAGES'!N94 | AJ94: =AI94-AH94 -> 0
A95: =JAN!A95 | B95: * | AH95: =sum(B95:AF95) -> 0 | AI95: ='TOTALS&AVERAGES'!N95 | AJ95: =AI95-AH95 -> 0
A96: =JAN!A96 | AH96: =sum(B96:AF96) -> 0 | AI96: ='TOTALS&AVERAGES'!N96 | AJ96: =AI96-AH96 -> 0
A97: =JAN!A97 | AH97: =sum(B97:AF97) -> 0 | AI97: ='TOTALS&AVERAGES'!N97 | AJ97: =AI97-AH97 -> 0
A98: =JAN!A98 | AH98: =sum(B98:AF98) -> 0 | AI98: ='TOTALS&AVERAGES'!N98 | AJ98: =AI98-AH98 -> 0
A99: =JAN!A99 | B99: * | AH99: =sum(B99:AF99) -> 0 | AI99: ='TOTALS&AVERAGES'!N99 | AJ99: =AI99-AH99 -> 0
A100: =JAN!A100 | B100: * | AH100: =sum(B100:AF100) -> 0 | AI100: ='TOTALS&AVERAGES'!N100 | AJ100: =AI100-AH100 -> 0
...

Sheet OCT
A1: OCTOBER | B1: Monthly Regular Bills | C1: 46296 | D1: =C1+1 -> 46297 | E1: =D1+1 -> 46298 | F1: =E1+1 -> 46299 | G1: =F1+1 -> 46300 | H1: =G1+1 -> 46301 | I1: =H1+1 -> 46302 | J1: =I1+1 -> 46303 | K1: =J1+1 -> 46304 | ... AG1: =AF1+1 -> 46326 | AH1: TOTALS | AI1: SPENDING PLAN | AJ1: DIFFERENCE
A2: INCOME
A3: =JAN!A3 -> Main Job | AH3: =sum(B3:AF3) -> 0 | AI3: ='TOTALS&AVERAGES'!N3 | AJ3: =AI3-AH3 -> 0
A4: =JAN!A4 -> B Job | AH4: =sum(B4:AF4) -> 0 | AI4: ='TOTALS&AVERAGES'!N4 | AJ4: =AI4-AH4 -> 0
A5: =JAN!A5 -> Bonuses | AH5: =sum(B5:AF5) -> 0 | AI5: ='TOTALS&AVERAGES'!N5 | AJ5: =AI5-AH5 -> 0
A6: =JAN!A6 -> Gifts/Discounts | AH6: =sum(B6:AF6) -> 0 | AI6: ='TOTALS&AVERAGES'!N6 | AJ6: =AI6-AH6 -> 0
A7: =JAN!A7 -> Reimbursement | AH7: =sum(B7:AF7) -> 0 | AI7: ='TOTALS&AVERAGES'!N7 | AJ7: =AI7-AH7 -> 0
A8: =JAN!A8 -> Government Assistance | AH8: =sum(B8:AF8) -> 0 | AI8: ='TOTALS&AVERAGES'!N8 | AJ8: =AI8-AH8 -> 0
A9: =JAN!A9 -> Side Hustles | AH9: =sum(B9:AF9) -> 0 | AI9: ='TOTALS&AVERAGES'!N9 | AJ9: =AI9-AH9 -> 0
A10: =JAN!A10 -> Interest/Rewards | AH10: =sum(B10:AF10) -> 0 | AI10: ='TOTALS&AVERAGES'!N10 | AJ10: =AI10-AH10 -> 0
A11: =JAN!A11 -> VA Benefits | AH11: =sum(B11:AF11) -> 0 | AI11: ='TOTALS&AVERAGES'!N11 | AJ11: =AI11-AH11 -> 0
A12: =JAN!A12 -> Asset Cash Out | AH12: =sum(B12:AF12) -> 0 | AI12: ='TOTALS&AVERAGES'!N12 | AJ12: =AI12-AH12 -> 0
A13: =JAN!A13 -> Fed Tax Refund | AH13: =sum(B13:AF13) -> 0 | AI13: ='TOTALS&AVERAGES'!N13 | AJ13: =AI13-AH13 -> 0
A14: =JAN!A14 -> State Tax Refund | AH14: =sum(B14:AF14) -> 0 | AI14: ='TOTALS&AVERAGES'!N14 | AJ14: =AI14-AH14 -> 0
A15: TOTAL INCOME BEFORE TAXES | B15: =SUM(C3:AH14) -> 0 | C15: =SUM(C3:C14) -> 0 | D15: =SUM(D3:D14) -> 0 | E15: =SUM(E3:E14) -> 0 | F15: =SUM(F3:F14) -> 0 | G15: =SUM(G3:G14) -> 0 | H15: =SUM(H3:H14) -> 0 | I15: =SUM(I3:I14) -> 0 | J15: =SUM(J3:J14) -> 0 | ... AJ15: =SUM(AJ3:AJ14) -> 0
A16: EXPENSES BY D.A. CATEGORIES | B16: MONTHLY REGULAR BILLS
A17: 1 - SPIRITUAL | B17: =SUM(B18:B26) -> 0 | C17: =SUM(C18:C26) -> 0 | D17: =SUM(D18:D26) -> 0 | E17: =SUM(E18:E26) -> 0 | F17: =SUM(F18:F26) -> 0 | G17: =SUM(G18:G26) -> 0 | H17: =SUM(H18:H26) -> 0 | I17: =SUM(I18:I26) -> 0 | ... AJ17: =SUM(AJ18:AJ26) -> 0
A18: =JAN!A18 -> Tithing/Church Donation | AH18: =sum(B18:AF18) -> 0 | AI18: ='TOTALS&AVERAGES'!N18 | AJ18: =AI18-AH18 -> 0
A19: =JAN!A19 -> Books | AH19: =sum(B19:AF19) -> 0 | AI19: ='TOTALS&AVERAGES'!N19 | AJ19: =AI19-AH19 -> 0
A20: =JAN!A20 -> Charity | AH20: =sum(B20:AF20) -> 0 | AI20: ='TOTALS&AVERAGES'!N20 | AJ20: =AI20-AH20 -> 0
A21: =JAN!A21 -> Workshops | AH21: =sum(B21:AF21) -> 0 | AI21: ='TOTALS&AVERAGES'!N21 | AJ21: =AI21-AH21 -> 0
A22: =JAN!A22 -> Generosity | AH22: =sum(B22:AF22) -> 0 | AI22: ='TOTALS&AVERAGES'!N22 | AJ22: =AI22-AH22 -> 0
A23: =JAN!A23 -> Retreats / Seminars | AH23: =sum(B23:AF23) -> 0 | AI23: ='TOTALS&AVERAGES'!N23 | AJ23: =AI23-AH23 -> 0
A24: =JAN!A24 -> 7TH TRADITION / FELLOWSHIP/ PRG | AH24: =sum(B24:AF24) -> 0 | AI24: ='TOTALS&AVERAGES'!N24 | AJ24: =AI24-AH24 -> 0
A25: =JAN!A25 -> Conferences | AH25: =sum(B25:AF25) -> 0 | AI25: ='TOTALS&AVERAGES'!N25 | AJ25: =AI25-AH25 -> 0
A26: =JAN!A26 -> Career Investment | AH26: =sum(B26:AF26) -> 0 | AI26: ='TOTALS&AVERAGES'!N26 | AJ26: =AI26-AH26 -> 0
A27: =JAN!A27 -> Needs | B27: =SUM(B28:B43) -> 0 | C27: =SUM(C28:C43) -> 0 | D27: =SUM(D28:D43) -> 0 | E27: =SUM(E28:E43) -> 0 | F27: =SUM(F28:F43) -> 0 | G27: =SUM(G28:G43) -> 0 | H27: =SUM(H28:H43) -> 0 | I27: =SUM(I28:I43) -> 0 | ... AJ27: =SUM(AJ28:AJ43) -> 0
A28: =JAN!A28 -> Groceries | AH28: =sum(B28:AF28) -> 0 | AI28: ='TOTALS&AVERAGES'!N28 | AJ28: =AI28-AH28 -> 0
A29: =JAN!A29 -> Rent/Mortage | B29: * | AH29: =sum(B29:AF29) -> 0 | AI29: ='TOTALS&AVERAGES'!N29 | AJ29: =AI29-AH29 -> 0
A30: =JAN!A30 -> Cell Phone | B30: * | AH30: =sum(B30:AF30) -> 0 | AI30: ='TOTALS&AVERAGES'!N30 | AJ30: =AI30-AH30 -> 0
A31: =JAN!A31 -> Laundry/Cleaners | B31: * | AH31: =sum(B31:AF31) -> 0 | AI31: ='TOTALS&AVERAGES'!N31 | AJ31: =AI31-AH31 -> 0
A32: =JAN!A32 -> Car Fuel | B32: * | AH32: =sum(B32:AF32) -> 0 | AI32: ='TOTALS&AVERAGES'!N32 | AJ32: =AI32-AH32 -> 0
A33: =JAN!A33 -> Car Insurance | B33: * | AH33: =sum(B33:AF33) -> 0 | AI33: ='TOTALS&AVERAGES'!N33 | AJ33: =AI33-AH33 -> 0
A34: =JAN!A34 -> Home Items | B34: * | AH34: =sum(B34:AF34) -> 0 | AI34: ='TOTALS&AVERAGES'!N34 | AJ34: =AI34-AH34 -> 0
A35: =JAN!A35 -> Internet | AH35: =sum(B35:AF35) -> 0 | AI35: ='TOTALS&AVERAGES'!N35 | AJ35: =AI35-AH35 -> 0
A36: =JAN!A36 -> Electricity | B36: * | AH36: =sum(B36:AF36) -> 0 | AI36: ='TOTALS&AVERAGES'!N36 | AJ36: =AI36-AH36 -> 0
A37: =JAN!A37 -> Card Fees | AH37: =sum(B37:AF37) -> 0 | AI37: ='TOTALS&AVERAGES'!N37 | AJ37: =AI37-AH37 -> 0
A38: =JAN!A38 -> Moving | AH38: =sum(B38:AF38) -> 0 | AI38: ='TOTALS&AVERAGES'!N38 | AJ38: =AI38-AH38 -> 0
A39: =JAN!A39 -> Toiletries | B39: * | AH39: =sum(B39:AF39) -> 0 | AI39: ='TOTALS&AVERAGES'!N39 | AJ39: =AI39-AH39 -> 0
A40: =JAN!A40 -> Storage | B40: * | AH40: =sum(B40:AF40) -> 0 | AI40: ='TOTALS&AVERAGES'!N40 | AJ40: =AI40-AH40 -> 0
A41: =JAN!A41 -> MTA/Public Transportation | B41: * | AH41: =sum(B41:AF41) -> 0 | AI41: ='TOTALS&AVERAGES'!N41 | AJ41: =AI41-AH41 -> 0
A42: =JAN!A42 -> Health Care | AH42: =sum(B42:AF42) -> 0 | AI42: ='TOTALS&AVERAGES'!N42 | AJ42: =AI42-AH42 -> 0
A43: =JAN!A43 -> Repairs | AH43: =sum(B43:AF43) -> 0 | AI43: ='TOTALS&AVERAGES'!N43 | AJ43: =AI43-AH43 -> 0
A44: =JAN!A44 -> Wants | B44: =SUM(B45:B52) -> 0 | C44: =SUM(C45:C52) -> 0 | D44: =SUM(D45:D52) -> 0 | E44: =SUM(E45:E52) -> 0 | F44: =SUM(F45:F52) -> 0 | G44: =SUM(G45:G52) -> 0 | H44: =SUM(H45:H52) -> 0 | I44: =SUM(I45:I52) -> 0 | ... AJ44: =SUM(AJ45:AJ52) -> 0
A45: =JAN!A45 -> Clothes | AH45: =sum(B45:AF45) -> 0 | AI45: ='TOTALS&AVERAGES'!N45 | AJ45: =AI45-AH45 -> 0
A46: =JAN!A46 -> Haircuts | AH46: =sum(B46:AF46) -> 0 | AI46: ='TOTALS&AVERAGES'!N46 | AJ46: =AI46-AH46 -> 0
A47: =JAN!A47 -> Dining Out/Take out/Events | AH47: =sum(B47:AF47) -> 0 | AI47: ='TOTALS&AVERAGES'!N47 | AJ47: =AI47-AH47 -> 0
A48: =JAN!A48 -> Gym Membership | AH48: =sum(B48:AF48) -> 0 | AI48: ='TOTALS&AVERAGES'!N48 | AJ48: =AI48-AH48 -> 0
A49: =JAN!A49 -> Subscriptions Zoom/Paramount/Club Free/News Subsription | AH49: =sum(B49:AF49) -> 0 | AI49: ='TOTALS&AVERAGES'!N49 | AJ49: =AI49-AH49 -> 0
A50: =JAN!A50 -> Snacks | AH50: =sum(B50:AF50) -> 0 | AI50: ='TOTALS&AVERAGES'!N50 | AJ50: =AI50-AH50 -> 0
A51: =JAN!A51 -> Vacations/Trip to see Brother Bryant/Trip to NM/Trip to San Antonio | AH51: =sum(B51:AF51) -> 0 | AI51: ='TOTALS&AVERAGES'!N51 | AJ51: =AI51-AH51 -> 0
A52: =JAN!A52 -> Other/Misc | AH52: =sum(B52:AF52) -> 0 | AI52: ='TOTALS&AVERAGES'!N52 | AJ52: =AI52-AH52 -> 0
A53: =JAN!A53 -> Savings | B53: =SUM(B54:B67) -> 0 | C53: =SUM(C54:C67) -> 0 | D53: =SUM(D54:D67) -> 0 | E53: =SUM(E54:E67) -> 0 | F53: =SUM(F54:F67) -> 0 | G53: =SUM(G54:G67) -> 0 | H53: =SUM(H54:H67) -> 0 | I53: =SUM(I54:I67) -> 0 | ... AJ53: =SUM(AJ54:AJ67) -> 0
A54: =JAN!A54 -> High yield Savings | B54: * | AH54: =sum(B54:AF54) -> 0 | AI54: ='TOTALS&AVERAGES'!N54 | AJ54: =AI54-AH54 -> 0
A55: =JAN!A55 -> Emergency Fund | B55: * | AH55: =sum(B55:AF55) -> 0 | AI55: ='TOTALS&AVERAGES'!N55 | AJ55: =AI55-AH55 -> 0
A56: =JAN!A56 -> Stocks/Index Fund | B56: * | AH56: =sum(B56:AF56) -> 0 | AI56: ='TOTALS&AVERAGES'!N56 | AJ56: =AI56-AH56 -> 0
A57: =JAN!A57 -> Real Estate | AH57: =sum(B57:AF57) -> 0 | AI57: ='TOTALS&AVERAGES'!N57 | AJ57: =AI57-AH57 -> 0
A58: =JAN!A58 -> Extra Debt Payment | AH58: =sum(B58:AF58) -> 0 | AI58: ='TOTALS&AVERAGES'!N58 | AJ58: =AI58-AH58 -> 0
A59: =JAN!A59 -> Gold | AH59: =sum(B59:AF59) -> 0 | AI59: ='TOTALS&AVERAGES'!N59 | AJ59: =AI59-AH59 -> 0
A60: =JAN!A60 -> Retirement/Roth IRA | AH60: =sum(B60:AF60) -> 0 | AI60: ='TOTALS&AVERAGES'!N60 | AJ60: =AI60-AH60 -> 0
A61: =JAN!A61 -> Annuities | AH61: =sum(B61:AF61) -> 0 | AI61: ='TOTALS&AVERAGES'!N61 | AJ61: =AI61-AH61 -> 0
A62: =JAN!A62 -> Life Insurance | AH62: =sum(B62:AF62) -> 0 | AI62: ='TOTALS&AVERAGES'!N62 | AJ62: =AI62-AH62 -> 0
A63: =JAN!A63 -> Watch | AH63: =sum(B63:AF63) -> 0 | AI63: ='TOTALS&AVERAGES'!N63 | AJ63: =AI63-AH63 -> 0
A64: =JAN!A64 -> CD | AH64: =sum(B64:AF64) -> 0 | AI64: ='TOTALS&AVERAGES'!N64 | AJ64: =AI64-AH64 -> 0
A65: =JAN!A65 -> Taxes Savings | AH65: =sum(B65:AF65) -> 0 | AI65: ='TOTALS&AVERAGES'!N65 | AJ65: =AI65-AH65 -> 0
A66: =JAN!A66 -> HSA | AH66: =sum(B66:AF66) -> 0 | AI66: ='TOTALS&AVERAGES'!N66 | AJ66: =AI66-AH66 -> 0
A67: =JAN!A67 -> - | AH67: =sum(B67:AF67) -> 0 | AI67: ='TOTALS&AVERAGES'!N67 | AJ67: =AI67-AH67 -> 0
A68: =JAN!A68 -> Debts | B68: =SUM(B69:B79) -> 0 | C68: =SUM(C69:C79) -> 0 | D68: =SUM(D69:D79) -> 0 | E68: =SUM(E69:E79) -> 0 | F68: =SUM(F69:F79) -> 0 | G68: =SUM(G69:G79) -> 0 | H68: =SUM(H69:H79) -> 0 | I68: =SUM(I69:I79) -> 0 | ... AJ68: =SUM(AJ69:AJ79) -> 0
A69: =JAN!A69 -> NFCU Loan 1151 | AH69: =sum(B69:AF69) -> 0 | AI69: ='TOTALS&AVERAGES'!N69 | AJ69: =AI69-AH69 -> 0
A70: =JAN!A70 -> NFCU Credit Card 8743 | AH70: =sum(B70:AF70) -> 0 | AI70: ='TOTALS&AVERAGES'!N70 | AJ70: =AI70-AH70 -> 0
A71: =JAN!A71 -> Capital One Credit Card 1057 | AH71: =sum(B71:AF71) -> 0 | AI71: ='TOTALS&AVERAGES'!N71 | AJ71: =AI71-AH71 -> 0
A72: =JAN!A72 -> Blink Fitness Collections | AH72: =sum(B72:AF72) -> 0 | AI72: ='TOTALS&AVERAGES'!N72 | AJ72: =AI72-AH72 -> 0
A73: =JAN!A73 -> T-Mobile Phone Bill | AH73: =sum(B73:AF73) -> 0 | AI73: ='TOTALS&AVERAGES'!N73 | AJ73: =AI73-AH73 -> 0
A74: =JAN!A74 -> TD Bank Collections | AH74: =sum(B74:AF74) -> 0 | AI74: ='TOTALS&AVERAGES'!N74 | AJ74: =AI74-AH74 -> 0
A75: =JAN!A75 -> Safegaurd Operations Collections | AH75: =sum(B75:AF75) -> 0 | AI75: ='TOTALS&AVERAGES'!N75 | AJ75: =AI75-AH75 -> 0
A76: =JAN!A76 -> BMCC Loan 474.03 | AH76: =sum(B76:AF76) -> 0 | AI76: ='TOTALS&AVERAGES'!N76 | AJ76: =AI76-AH76 -> 0
A77: =JAN!A77 -> Han Personal Debt (Paid) | AH77: =sum(B77:AF77) -> 0 | AI77: ='TOTALS&AVERAGES'!N77 | AJ77: =AI77-AH77 -> 0
A78: =JAN!A78 | AH78: =sum(B78:AF78) -> 0 | AI78: ='TOTALS&AVERAGES'!N78 | AJ78: =AI78-AH78 -> 0
A79: =JAN!A79 -> Total Debt: 8,551.73 | AH79: =sum(B79:AF79) -> 0 | AI79: ='TOTALS&AVERAGES'!N79 | AJ79: =AI79-AH79 -> 0
A80: =JAN!A80 -> School | B80: =SUM(B81:B91) -> 0 | C80: =SUM(C81:C91) -> 0 | D80: =SUM(D81:D91) -> 0 | E80: =SUM(E81:E91) -> 0 | F80: =SUM(F81:F91) -> 0 | G80: =SUM(G81:G91) -> 0 | H80: =SUM(H81:H91) -> 0 | I80: =SUM(I81:I91) -> 0 | ... AJ80: =SUM(AJ81:AJ91) -> 0
A81: =JAN!A81 -> Tuition | AH81: =sum(B81:AF81) -> 0 | AI81: ='TOTALS&AVERAGES'!N81 | AJ81: =AI81-AH81 -> 0
A82: =JAN!A82 -> Books | AH82: =sum(B82:AF82) -> 0 | AI82: ='TOTALS&AVERAGES'!N82 | AJ82: =AI82-AH82 -> 0
A83: =JAN!A83 | AH83: =sum(B83:AF83) -> 0 | AI83: ='TOTALS&AVERAGES'!N83 | AJ83: =AI83-AH83 -> 0
A84: =JAN!A84 | AH84: =sum(B84:AF84) -> 0 | AI84: ='TOTALS&AVERAGES'!N84 | AJ84: =AI84-AH84 -> 0
A85: =JAN!A85 | AH85: =sum(B85:AF85) -> 0 | AI85: ='TOTALS&AVERAGES'!N85 | AJ85: =AI85-AH85 -> 0
A86: =JAN!A86 | AH86: =sum(B86:AF86) -> 0 | AI86: ='TOTALS&AVERAGES'!N86 | AJ86: =AI86-AH86 -> 0
A87: =JAN!A87 | AH87: =sum(B87:AF87) -> 0 | AI87: ='TOTALS&AVERAGES'!N87 | AJ87: =AI87-AH87 -> 0
A88: =JAN!A88 | AH88: =sum(B88:AF88) -> 0 | AI88: ='TOTALS&AVERAGES'!N88 | AJ88: =AI88-AH88 -> 0
A89: =JAN!A89 | AH89: =sum(B89:AF89) -> 0 | AI89: ='TOTALS&AVERAGES'!N89 | AJ89: =AI89-AH89 -> 0
A90: =JAN!A90 | AH90: =sum(B90:AF90) -> 0 | AI90: ='TOTALS&AVERAGES'!N90 | AJ90: =AI90-AH90 -> 0
A91: =JAN!A91 | AH91: =sum(B91:AF91) -> 0 | AI91: ='TOTALS&AVERAGES'!N91 | AJ91: =AI91-AH91 -> 0
A92: =JAN!A92 | B92: =SUM(B93:B106) -> 0 | C92: =SUM(C93:C106) -> 0 | D92: =SUM(D93:D106) -> 0 | E92: =SUM(E93:E106) -> 0 | F92: =SUM(F93:F106) -> 0 | G92: =SUM(G93:G106) -> 0 | H92: =SUM(H93:H106) -> 0 | I92: =SUM(I93:I106) -> 0 | ... AJ92: =SUM(AJ93:AJ106) -> 0
A93: =JAN!A93 | AH93: =sum(B93:AF93) -> 0 | AI93: ='TOTALS&AVERAGES'!N93 | AJ93: =AI93-AH93 -> 0
A94: =JAN!A94 | AH94: =sum(B94:AF94) -> 0 | AI94: ='TOTALS&AVERAGES'!N94 | AJ94: =AI94-AH94 -> 0
A95: =JAN!A95 | B95: * | AH95: =sum(B95:AF95) -> 0 | AI95: ='TOTALS&AVERAGES'!N95 | AJ95: =AI95-AH95 -> 0
A96: =JAN!A96 | AH96: =sum(B96:AF96) -> 0 | AI96: ='TOTALS&AVERAGES'!N96 | AJ96: =AI96-AH96 -> 0
A97: =JAN!A97 | AH97: =sum(B97:AF97) -> 0 | AI97: ='TOTALS&AVERAGES'!N97 | AJ97: =AI97-AH97 -> 0
A98: =JAN!A98 | AH98: =sum(B98:AF98) -> 0 | AI98: ='TOTALS&AVERAGES'!N98 | AJ98: =AI98-AH98 -> 0
A99: =JAN!A99 | B99: * | AH99: =sum(B99:AF99) -> 0 | AI99: ='TOTALS&AVERAGES'!N99 | AJ99: =AI99-AH99 -> 0
A100: =JAN!A100 | B100: * | AH100: =sum(B100:AF100) -> 0 | AI100: ='TOTALS&AVERAGES'!N100 | AJ100: =AI100-AH100 -> 0
...

Sheet NOV
A1: NOVEMBER | B1: Monthly Regular Bills | C1: 46327 | D1: =C1+1 -> 46328 | E1: =D1+1 -> 46329 | F1: =E1+1 -> 46330 | G1: =F1+1 -> 46331 | H1: =G1+1 -> 46332 | I1: =H1+1 -> 46333 | J1: =I1+1 -> 46334 | K1: =J1+1 -> 46335 | ... AG1: =AF1+1 -> 46357 | AH1: TOTALS | AI1: SPENDING PLAN | AJ1: DIFFERENCE
A2: INCOME
A3: =JAN!A3 -> Main Job | AH3: =sum(B3:AF3) -> 0 | AI3: ='TOTALS&AVERAGES'!N3 | AJ3: =AI3-AH3 -> 0
A4: =JAN!A4 -> B Job | AH4: =sum(B4:AF4) -> 0 | AI4: ='TOTALS&AVERAGES'!N4 | AJ4: =AI4-AH4 -> 0
A5: =JAN!A5 -> Bonuses | AH5: =sum(B5:AF5) -> 0 | AI5: ='TOTALS&AVERAGES'!N5 | AJ5: =AI5-AH5 -> 0
A6: =JAN!A6 -> Gifts/Discounts | AH6: =sum(B6:AF6) -> 0 | AI6: ='TOTALS&AVERAGES'!N6 | AJ6: =AI6-AH6 -> 0
A7: =JAN!A7 -> Reimbursement | AH7: =sum(B7:AF7) -> 0 | AI7: ='TOTALS&AVERAGES'!N7 | AJ7: =AI7-AH7 -> 0
A8: =JAN!A8 -> Government Assistance | AH8: =sum(B8:AF8) -> 0 | AI8: ='TOTALS&AVERAGES'!N8 | AJ8: =AI8-AH8 -> 0
A9: =JAN!A9 -> Side Hustles | AH9: =sum(B9:AF9) -> 0 | AI9: ='TOTALS&AVERAGES'!N9 | AJ9: =AI9-AH9 -> 0
A10: =JAN!A10 -> Interest/Rewards | AH10: =sum(B10:AF10) -> 0 | AI10: ='TOTALS&AVERAGES'!N10 | AJ10: =AI10-AH10 -> 0
A11: =JAN!A11 -> VA Benefits | AH11: =sum(B11:AF11) -> 0 | AI11: ='TOTALS&AVERAGES'!N11 | AJ11: =AI11-AH11 -> 0
A12: =JAN!A12 -> Asset Cash Out | AH12: =sum(B12:AF12) -> 0 | AI12: ='TOTALS&AVERAGES'!N12 | AJ12: =AI12-AH12 -> 0
A13: =JAN!A13 -> Fed Tax Refund | AH13: =sum(B13:AF13) -> 0 | AI13: ='TOTALS&AVERAGES'!N13 | AJ13: =AI13-AH13 -> 0
A14: =JAN!A14 -> State Tax Refund | AH14: =sum(B14:AF14) -> 0 | AI14: ='TOTALS&AVERAGES'!N14 | AJ14: =AI14-AH14 -> 0
A15: TOTAL INCOME BEFORE TAXES | B15: =SUM(C3:AH14) -> 0 | C15: =SUM(C3:C14) -> 0 | D15: =SUM(D3:D14) -> 0 | E15: =SUM(E3:E14) -> 0 | F15: =SUM(F3:F14) -> 0 | G15: =SUM(G3:G14) -> 0 | H15: =SUM(H3:H14) -> 0 | I15: =SUM(I3:I14) -> 0 | J15: =SUM(J3:J14) -> 0 | ... AJ15: =SUM(AJ3:AJ14) -> 0
A16: EXPENSES BY D.A. CATEGORIES | B16: MONTHLY REGULAR BILLS
A17: 1 - SPIRITUAL | B17: =SUM(B18:B26) -> 0 | C17: =SUM(C18:C26) -> 0 | D17: =SUM(D18:D26) -> 0 | E17: =SUM(E18:E26) -> 0 | F17: =SUM(F18:F26) -> 0 | G17: =SUM(G18:G26) -> 0 | H17: =SUM(H18:H26) -> 0 | I17: =SUM(I18:I26) -> 0 | ... AJ17: =SUM(AJ18:AJ26) -> 0
A18: =JAN!A18 -> Tithing/Church Donation | AH18: =sum(B18:AF18) -> 0 | AI18: ='TOTALS&AVERAGES'!N18 | AJ18: =AI18-AH18 -> 0
A19: =JAN!A19 -> Books | AH19: =sum(B19:AF19) -> 0 | AI19: ='TOTALS&AVERAGES'!N19 | AJ19: =AI19-AH19 -> 0
A20: =JAN!A20 -> Charity | AH20: =sum(B20:AF20) -> 0 | AI20: ='TOTALS&AVERAGES'!N20 | AJ20: =AI20-AH20 -> 0
A21: =JAN!A21 -> Workshops | AH21: =sum(B21:AF21) -> 0 | AI21: ='TOTALS&AVERAGES'!N21 | AJ21: =AI21-AH21 -> 0
A22: =JAN!A22 -> Generosity | AH22: =sum(B22:AF22) -> 0 | AI22: ='TOTALS&AVERAGES'!N22 | AJ22: =AI22-AH22 -> 0
A23: =JAN!A23 -> Retreats / Seminars | AH23: =sum(B23:AF23) -> 0 | AI23: ='TOTALS&AVERAGES'!N23 | AJ23: =AI23-AH23 -> 0
A24: =JAN!A24 -> 7TH TRADITION / FELLOWSHIP/ PRG | AH24: =sum(B24:AF24) -> 0 | AI24: ='TOTALS&AVERAGES'!N24 | AJ24: =AI24-AH24 -> 0
A25: =JAN!A25 -> Conferences | AH25: =sum(B25:AF25) -> 0 | AI25: ='TOTALS&AVERAGES'!N25 | AJ25: =AI25-AH25 -> 0
A26: =JAN!A26 -> Career Investment | AH26: =sum(B26:AF26) -> 0 | AI26: ='TOTALS&AVERAGES'!N26 | AJ26: =AI26-AH26 -> 0
A27: =JAN!A27 -> Needs | B27: =SUM(B28:B43) -> 0 | C27: =SUM(C28:C43) -> 0 | D27: =SUM(D28:D43) -> 0 | E27: =SUM(E28:E43) -> 0 | F27: =SUM(F28:F43) -> 0 | G27: =SUM(G28:G43) -> 0 | H27: =SUM(H28:H43) -> 0 | I27: =SUM(I28:I43) -> 0 | ... AJ27: =SUM(AJ28:AJ43) -> 0
A28: =JAN!A28 -> Groceries | AH28: =sum(B28:AF28) -> 0 | AI28: ='TOTALS&AVERAGES'!N28 | AJ28: =AI28-AH28 -> 0
A29: =JAN!A29 -> Rent/Mortage | B29: * | AH29: =sum(B29:AF29) -> 0 | AI29: ='TOTALS&AVERAGES'!N29 | AJ29: =AI29-AH29 -> 0
A30: =JAN!A30 -> Cell Phone | B30: * | AH30: =sum(B30:AF30) -> 0 | AI30: ='TOTALS&AVERAGES'!N30 | AJ30: =AI30-AH30 -> 0
A31: =JAN!A31 -> Laundry/Cleaners | B31: * | AH31: =sum(B31:AF31) -> 0 | AI31: ='TOTALS&AVERAGES'!N31 | AJ31: =AI31-AH31 -> 0
A32: =JAN!A32 -> Car Fuel | B32: * | AH32: =sum(B32:AF32) -> 0 | AI32: ='TOTALS&AVERAGES'!N32 | AJ32: =AI32-AH32 -> 0
A33: =JAN!A33 -> Car Insurance | B33: * | AH33: =sum(B33:AF33) -> 0 | AI33: ='TOTALS&AVERAGES'!N33 | AJ33: =AI33-AH33 -> 0
A34: =JAN!A34 -> Home Items | B34: * | AH34: =sum(B34:AF34) -> 0 | AI34: ='TOTALS&AVERAGES'!N34 | AJ34: =AI34-AH34 -> 0
A35: =JAN!A35 -> Internet | AH35: =sum(B35:AF35) -> 0 | AI35: ='TOTALS&AVERAGES'!N35 | AJ35: =AI35-AH35 -> 0
A36: =JAN!A36 -> Electricity | B36: * | AH36: =sum(B36:AF36) -> 0 | AI36: ='TOTALS&AVERAGES'!N36 | AJ36: =AI36-AH36 -> 0
A37: =JAN!A37 -> Card Fees | AH37: =sum(B37:AF37) -> 0 | AI37: ='TOTALS&AVERAGES'!N37 | AJ37: =AI37-AH37 -> 0
A38: =JAN!A38 -> Moving | AH38: =sum(B38:AF38) -> 0 | AI38: ='TOTALS&AVERAGES'!N38 | AJ38: =AI38-AH38 -> 0
A39: =JAN!A39 -> Toiletries | B39: * | AH39: =sum(B39:AF39) -> 0 | AI39: ='TOTALS&AVERAGES'!N39 | AJ39: =AI39-AH39 -> 0
A40: =JAN!A40 -> Storage | B40: * | AH40: =sum(B40:AF40) -> 0 | AI40: ='TOTALS&AVERAGES'!N40 | AJ40: =AI40-AH40 -> 0
A41: =JAN!A41 -> MTA/Public Transportation | B41: * | AH41: =sum(B41:AF41) -> 0 | AI41: ='TOTALS&AVERAGES'!N41 | AJ41: =AI41-AH41 -> 0
A42: =JAN!A42 -> Health Care | AH42: =sum(B42:AF42) -> 0 | AI42: ='TOTALS&AVERAGES'!N42 | AJ42: =AI42-AH42 -> 0
A43: =JAN!A43 -> Repairs | AH43: =sum(B43:AF43) -> 0 | AI43: ='TOTALS&AVERAGES'!N43 | AJ43: =AI43-AH43 -> 0
A44: =JAN!A44 -> Wants | B44: =SUM(B45:B52) -> 0 | C44: =SUM(C45:C52) -> 0 | D44: =SUM(D45:D52) -> 0 | E44: =SUM(E45:E52) -> 0 | F44: =SUM(F45:F52) -> 0 | G44: =SUM(G45:G52) -> 0 | H44: =SUM(H45:H52) -> 0 | I44: =SUM(I45:I52) -> 0 | ... AJ44: =SUM(AJ45:AJ52) -> 0
A45: =JAN!A45 -> Clothes | AH45: =sum(B45:AF45) -> 0 | AI45: ='TOTALS&AVERAGES'!N45 | AJ45: =AI45-AH45 -> 0
A46: =JAN!A46 -> Haircuts | AH46: =sum(B46:AF46) -> 0 | AI46: ='TOTALS&AVERAGES'!N46 | AJ46: =AI46-AH46 -> 0
A47: =JAN!A47 -> Dining Out/Take out/Events | AH47: =sum(B47:AF47) -> 0 | AI47: ='TOTALS&AVERAGES'!N47 | AJ47: =AI47-AH47 -> 0
A48: =JAN!A48 -> Gym Membership | AH48: =sum(B48:AF48) -> 0 | AI48: ='TOTALS&AVERAGES'!N48 | AJ48: =AI48-AH48 -> 0
A49: =JAN!A49 -> Subscriptions Zoom/Paramount/Club Free/News Subsription | AH49: =sum(B49:AF49) -> 0 | AI49: ='TOTALS&AVERAGES'!N49 | AJ49: =AI49-AH49 -> 0
A50: =JAN!A50 -> Snacks | AH50: =sum(B50:AF50) -> 0 | AI50: ='TOTALS&AVERAGES'!N50 | AJ50: =AI50-AH50 -> 0
A51: =JAN!A51 -> Vacations/Trip to see Brother Bryant/Trip to NM/Trip to San Antonio | AH51: =sum(B51:AF51) -> 0 | AI51: ='TOTALS&AVERAGES'!N51 | AJ51: =AI51-AH51 -> 0
A52: =JAN!A52 -> Other/Misc | AH52: =sum(B52:AF52) -> 0 | AI52: ='TOTALS&AVERAGES'!N52 | AJ52: =AI52-AH52 -> 0
A53: =JAN!A53 -> Savings | B53: =SUM(B54:B67) -> 0 | C53: =SUM(C54:C67) -> 0 | D53: =SUM(D54:D67) -> 0 | E53: =SUM(E54:E67) -> 0 | F53: =SUM(F54:F67) -> 0 | G53: =SUM(G54:G67) -> 0 | H53: =SUM(H54:H67) -> 0 | I53: =SUM(I54:I67) -> 0 | ... AJ53: =SUM(AJ54:AJ67) -> 0
A54: =JAN!A54 -> High yield Savings | B54: * | AH54: =sum(B54:AF54) -> 0 | AI54: ='TOTALS&AVERAGES'!N54 | AJ54: =AI54-AH54 -> 0
A55: =JAN!A55 -> Emergency Fund | B55: * | AH55: =sum(B55:AF55) -> 0 | AI55: ='TOTALS&AVERAGES'!N55 | AJ55: =AI55-AH55 -> 0
A56: =JAN!A56 -> Stocks/Index Fund | B56: * | AH56: =sum(B56:AF56) -> 0 | AI56: ='TOTALS&AVERAGES'!N56 | AJ56: =AI56-AH56 -> 0
A57: =JAN!A57 -> Real Estate | AH57: =sum(B57:AF57) -> 0 | AI57: ='TOTALS&AVERAGES'!N57 | AJ57: =AI57-AH57 -> 0
A58: =JAN!A58 -> Extra Debt Payment | AH58: =sum(B58:AF58) -> 0 | AI58: ='TOTALS&AVERAGES'!N58 | AJ58: =AI58-AH58 -> 0
A59: =JAN!A59 -> Gold | AH59: =sum(B59:AF59) -> 0 | AI59: ='TOTALS&AVERAGES'!N59 | AJ59: =AI59-AH59 -> 0
A60: =JAN!A60 -> Retirement/Roth IRA | AH60: =sum(B60:AF60) -> 0 | AI60: ='TOTALS&AVERAGES'!N60 | AJ60: =AI60-AH60 -> 0
A61: =JAN!A61 -> Annuities | AH61: =sum(B61:AF61) -> 0 | AI61: ='TOTALS&AVERAGES'!N61 | AJ61: =AI61-AH61 -> 0
A62: =JAN!A62 -> Life Insurance | AH62: =sum(B62:AF62) -> 0 | AI62: ='TOTALS&AVERAGES'!N62 | AJ62: =AI62-AH62 -> 0
A63: =JAN!A63 -> Watch | AH63: =sum(B63:AF63) -> 0 | AI63: ='TOTALS&AVERAGES'!N63 | AJ63: =AI63-AH63 -> 0
A64: =JAN!A64 -> CD | AH64: =sum(B64:AF64) -> 0 | AI64: ='TOTALS&AVERAGES'!N64 | AJ64: =AI64-AH64 -> 0
A65: =JAN!A65 -> Taxes Savings | AH65: =sum(B65:AF65) -> 0 | AI65: ='TOTALS&AVERAGES'!N65 | AJ65: =AI65-AH65 -> 0
A66: =JAN!A66 -> HSA | AH66: =sum(B66:AF66) -> 0 | AI66: ='TOTALS&AVERAGES'!N66 | AJ66: =AI66-AH66 -> 0
A67: =JAN!A67 -> - | AH67: =sum(B67:AF67) -> 0 | AI67: ='TOTALS&AVERAGES'!N67 | AJ67: =AI67-AH67 -> 0
A68: =JAN!A68 -> Debts | B68: =SUM(B69:B79) -> 0 | C68: =SUM(C69:C79) -> 0 | D68: =SUM(D69:D79) -> 0 | E68: =SUM(E69:E79) -> 0 | F68: =SUM(F69:F79) -> 0 | G68: =SUM(G69:G79) -> 0 | H68: =SUM(H69:H79) -> 0 | I68: =SUM(I69:I79) -> 0 | ... AJ68: =SUM(AJ69:AJ79) -> 0
A69: =JAN!A69 -> NFCU Loan 1151 | AH69: =sum(B69:AF69) -> 0 | AI69: ='TOTALS&AVERAGES'!N69 | AJ69: =AI69-AH69 -> 0
A70: =JAN!A70 -> NFCU Credit Card 8743 | AH70: =sum(B70:AF70) -> 0 | AI70: ='TOTALS&AVERAGES'!N70 | AJ70: =AI70-AH70 -> 0
A71: =JAN!A71 -> Capital One Credit Card 1057 | AH71: =sum(B71:AF71) -> 0 | AI71: ='TOTALS&AVERAGES'!N71 | AJ71: =AI71-AH71 -> 0
A72: =JAN!A72 -> Blink Fitness Collections | AH72: =sum(B72:AF72) -> 0 | AI72: ='TOTALS&AVERAGES'!N72 | AJ72: =AI72-AH72 -> 0
A73: =JAN!A73 -> T-Mobile Phone Bill | AH73: =sum(B73:AF73) -> 0 | AI73: ='TOTALS&AVERAGES'!N73 | AJ73: =AI73-AH73 -> 0
A74: =JAN!A74 -> TD Bank Collections | AH74: =sum(B74:AF74) -> 0 | AI74: ='TOTALS&AVERAGES'!N74 | AJ74: =AI74-AH74 -> 0
A75: =JAN!A75 -> Safegaurd Operations Collections | AH75: =sum(B75:AF75) -> 0 | AI75: ='TOTALS&AVERAGES'!N75 | AJ75: =AI75-AH75 -> 0
A76: =JAN!A76 -> BMCC Loan 474.03 | AH76: =sum(B76:AF76) -> 0 | AI76: ='TOTALS&AVERAGES'!N76 | AJ76: =AI76-AH76 -> 0
A77: =JAN!A77 -> Han Personal Debt (Paid) | AH77: =sum(B77:AF77) -> 0 | AI77: ='TOTALS&AVERAGES'!N77 | AJ77: =AI77-AH77 -> 0
A78: =JAN!A78 | AH78: =sum(B78:AF78) -> 0 | AI78: ='TOTALS&AVERAGES'!N78 | AJ78: =AI78-AH78 -> 0
A79: =JAN!A79 -> Total Debt: 8,551.73 | AH79: =sum(B79:AF79) -> 0 | AI79: ='TOTALS&AVERAGES'!N79 | AJ79: =AI79-AH79 -> 0
A80: =JAN!A80 -> School | B80: =SUM(B81:B91) -> 0 | C80: =SUM(C81:C91) -> 0 | D80: =SUM(D81:D91) -> 0 | E80: =SUM(E81:E91) -> 0 | F80: =SUM(F81:F91) -> 0 | G80: =SUM(G81:G91) -> 0 | H80: =SUM(H81:H91) -> 0 | I80: =SUM(I81:I91) -> 0 | ... AJ80: =SUM(AJ81:AJ91) -> 0
A81: =JAN!A81 -> Tuition | AH81: =sum(B81:AF81) -> 0 | AI81: ='TOTALS&AVERAGES'!N81 | AJ81: =AI81-AH81 -> 0
A82: =JAN!A82 -> Books | AH82: =sum(B82:AF82) -> 0 | AI82: ='TOTALS&AVERAGES'!N82 | AJ82: =AI82-AH82 -> 0
A83: =JAN!A83 | AH83: =sum(B83:AF83) -> 0 | AI83: ='TOTALS&AVERAGES'!N83 | AJ83: =AI83-AH83 -> 0
A84: =JAN!A84 | AH84: =sum(B84:AF84) -> 0 | AI84: ='TOTALS&AVERAGES'!N84 | AJ84: =AI84-AH84 -> 0
A85: =JAN!A85 | AH85: =sum(B85:AF85) -> 0 | AI85: ='TOTALS&AVERAGES'!N85 | AJ85: =AI85-AH85 -> 0
A86: =JAN!A86 | AH86: =sum(B86:AF86) -> 0 | AI86: ='TOTALS&AVERAGES'!N86 | AJ86: =AI86-AH86 -> 0
A87: =JAN!A87 | AH87: =sum(B87:AF87) -> 0 | AI87: ='TOTALS&AVERAGES'!N87 | AJ87: =AI87-AH87 -> 0
A88: =JAN!A88 | AH88: =sum(B88:AF88) -> 0 | AI88: ='TOTALS&AVERAGES'!N88 | AJ88: =AI88-AH88 -> 0
A89: =JAN!A89 | AH89: =sum(B89:AF89) -> 0 | AI89: ='TOTALS&AVERAGES'!N89 | AJ89: =AI89-AH89 -> 0
A90: =JAN!A90 | AH90: =sum(B90:AF90) -> 0 | AI90: ='TOTALS&AVERAGES'!N90 | AJ90: =AI90-AH90 -> 0
A91: =JAN!A91 | AH91: =sum(B91:AF91) -> 0 | AI91: ='TOTALS&AVERAGES'!N91 | AJ91: =AI91-AH91 -> 0
A92: =JAN!A92 | B92: =SUM(B93:B106) -> 0 | C92: =SUM(C93:C106) -> 0 | D92: =SUM(D93:D106) -> 0 | E92: =SUM(E93:E106) -> 0 | F92: =SUM(F93:F106) -> 0 | G92: =SUM(G93:G106) -> 0 | H92: =SUM(H93:H106) -> 0 | I92: =SUM(I93:I106) -> 0 | ... AJ92: =SUM(AJ93:AJ106) -> 0
A93: =JAN!A93 | AH93: =sum(B93:AF93) -> 0 | AI93: ='TOTALS&AVERAGES'!N93 | AJ93: =AI93-AH93 -> 0
A94: =JAN!A94 | AH94: =sum(B94:AF94) -> 0 | AI94: ='TOTALS&AVERAGES'!N94 | AJ94: =AI94-AH94 -> 0
A95: =JAN!A95 | B95: * | AH95: =sum(B95:AF95) -> 0 | AI95: ='TOTALS&AVERAGES'!N95 | AJ95: =AI95-AH95 -> 0
A96: =JAN!A96 | AH96: =sum(B96:AF96) -> 0 | AI96: ='TOTALS&AVERAGES'!N96 | AJ96: =AI96-AH96 -> 0
A97: =JAN!A97 | AH97: =sum(B97:AF97) -> 0 | AI97: ='TOTALS&AVERAGES'!N97 | AJ97: =AI97-AH97 -> 0
A98: =JAN!A98 | AH98: =sum(B98:AF98) -> 0 | AI98: ='TOTALS&AVERAGES'!N98 | AJ98: =AI98-AH98 -> 0
A99: =JAN!A99 | B99: * | AH99: =sum(B99:AF99) -> 0 | AI99: ='TOTALS&AVERAGES'!N99 | AJ99: =AI99-AH99 -> 0
A100: =JAN!A100 | B100: * | AH100: =sum(B100:AF100) -> 0 | AI100: ='TOTALS&AVERAGES'!N100 | AJ100: =AI100-AH100 -> 0
...

Sheet DEC
A1: DECEMBER | B1: Monthly Regular Bills | C1: 46357 | D1: =C1+1 -> 46358 | E1: =D1+1 -> 46359 | F1: =E1+1 -> 46360 | G1: =F1+1 -> 46361 | H1: =G1+1 -> 46362 | I1: =H1+1 -> 46363 | J1: =I1+1 -> 46364 | K1: =J1+1 -> 46365 | ... AG1: =AF1+1 -> 46387 | AH1: TOTALS | AI1: SPENDING PLAN | AJ1: DIFFERENCE
A2: INCOME
A3: =JAN!A3 -> Main Job | AH3: =sum(B3:AF3) -> 0 | AI3: ='TOTALS&AVERAGES'!N3 | AJ3: =AI3-AH3 -> 0
A4: =JAN!A4 -> B Job | AH4: =sum(B4:AF4) -> 0 | AI4: ='TOTALS&AVERAGES'!N4 | AJ4: =AI4-AH4 -> 0
A5: =JAN!A5 -> Bonuses | AH5: =sum(B5:AF5) -> 0 | AI5: ='TOTALS&AVERAGES'!N5 | AJ5: =AI5-AH5 -> 0
A6: =JAN!A6 -> Gifts/Discounts | AH6: =sum(B6:AF6) -> 0 | AI6: ='TOTALS&AVERAGES'!N6 | AJ6: =AI6-AH6 -> 0
A7: =JAN!A7 -> Reimbursement | AH7: =sum(B7:AF7) -> 0 | AI7: ='TOTALS&AVERAGES'!N7 | AJ7: =AI7-AH7 -> 0
A8: =JAN!A8 -> Government Assistance | AH8: =sum(B8:AF8) -> 0 | AI8: ='TOTALS&AVERAGES'!N8 | AJ8: =AI8-AH8 -> 0
A9: =JAN!A9 -> Side Hustles | AH9: =sum(B9:AF9) -> 0 | AI9: ='TOTALS&AVERAGES'!N9 | AJ9: =AI9-AH9 -> 0
A10: =JAN!A10 -> Interest/Rewards | AH10: =sum(B10:AF10) -> 0 | AI10: ='TOTALS&AVERAGES'!N10 | AJ10: =AI10-AH10 -> 0
A11: =JAN!A11 -> VA Benefits | AH11: =sum(B11:AF11) -> 0 | AI11: ='TOTALS&AVERAGES'!N11 | AJ11: =AI11-AH11 -> 0
A12: =JAN!A12 -> Asset Cash Out | AH12: =sum(B12:AF12) -> 0 | AI12: ='TOTALS&AVERAGES'!N12 | AJ12: =AI12-AH12 -> 0
A13: =JAN!A13 -> Fed Tax Refund | AH13: =sum(B13:AF13) -> 0 | AI13: ='TOTALS&AVERAGES'!N13 | AJ13: =AI13-AH13 -> 0
A14: =JAN!A14 -> State Tax Refund | AH14: =sum(B14:AF14) -> 0 | AI14: ='TOTALS&AVERAGES'!N14 | AJ14: =AI14-AH14 -> 0
A15: TOTAL INCOME BEFORE TAXES | B15: =SUM(C3:AH14) -> 0 | C15: =SUM(C3:C14) -> 0 | D15: =SUM(D3:D14) -> 0 | E15: =SUM(E3:E14) -> 0 | F15: =SUM(F3:F14) -> 0 | G15: =SUM(G3:G14) -> 0 | H15: =SUM(H3:H14) -> 0 | I15: =SUM(I3:I14) -> 0 | J15: =SUM(J3:J14) -> 0 | ... AJ15: =SUM(AJ3:AJ14) -> 0
A16: EXPENSES BY D.A. CATEGORIES | B16: MONTHLY REGULAR BILLS
A17: 1 - SPIRITUAL | B17: =SUM(B18:B26) -> 0 | C17: =SUM(C18:C26) -> 0 | D17: =SUM(D18:D26) -> 0 | E17: =SUM(E18:E26) -> 0 | F17: =SUM(F18:F26) -> 0 | G17: =SUM(G18:G26) -> 0 | H17: =SUM(H18:H26) -> 0 | I17: =SUM(I18:I26) -> 0 | ... AJ17: =SUM(AJ18:AJ26) -> 0
A18: =JAN!A18 -> Tithing/Church Donation | AH18: =sum(B18:AF18) -> 0 | AI18: ='TOTALS&AVERAGES'!N18 | AJ18: =AI18-AH18 -> 0
A19: =JAN!A19 -> Books | AH19: =sum(B19:AF19) -> 0 | AI19: ='TOTALS&AVERAGES'!N19 | AJ19: =AI19-AH19 -> 0
A20: =JAN!A20 -> Charity | AH20: =sum(B20:AF20) -> 0 | AI20: ='TOTALS&AVERAGES'!N20 | AJ20: =AI20-AH20 -> 0
A21: =JAN!A21 -> Workshops | AH21: =sum(B21:AF21) -> 0 | AI21: ='TOTALS&AVERAGES'!N21 | AJ21: =AI21-AH21 -> 0
A22: =JAN!A22 -> Generosity | AH22: =sum(B22:AF22) -> 0 | AI22: ='TOTALS&AVERAGES'!N22 | AJ22: =AI22-AH22 -> 0
A23: =JAN!A23 -> Retreats / Seminars | AH23: =sum(B23:AF23) -> 0 | AI23: ='TOTALS&AVERAGES'!N23 | AJ23: =AI23-AH23 -> 0
A24: =JAN!A24 -> 7TH TRADITION / FELLOWSHIP/ PRG | AH24: =sum(B24:AF24) -> 0 | AI24: ='TOTALS&AVERAGES'!N24 | AJ24: =AI24-AH24 -> 0
A25: =JAN!A25 -> Conferences | AH25: =sum(B25:AF25) -> 0 | AI25: ='TOTALS&AVERAGES'!N25 | AJ25: =AI25-AH25 -> 0
A26: =JAN!A26 -> Career Investment | AH26: =sum(B26:AF26) -> 0 | AI26: ='TOTALS&AVERAGES'!N26 | AJ26: =AI26-AH26 -> 0
A27: =JAN!A27 -> Needs | B27: =SUM(B28:B43) -> 0 | C27: =SUM(C28:C43) -> 0 | D27: =SUM(D28:D43) -> 0 | E27: =SUM(E28:E43) -> 0 | F27: =SUM(F28:F43) -> 0 | G27: =SUM(G28:G43) -> 0 | H27: =SUM(H28:H43) -> 0 | I27: =SUM(I28:I43) -> 0 | ... AJ27: =SUM(AJ28:AJ43) -> 0
A28: =JAN!A28 -> Groceries | AH28: =sum(B28:AF28) -> 0 | AI28: ='TOTALS&AVERAGES'!N28 | AJ28: =AI28-AH28 -> 0
A29: =JAN!A29 -> Rent/Mortage | B29: * | AH29: =sum(B29:AF29) -> 0 | AI29: ='TOTALS&AVERAGES'!N29 | AJ29: =AI29-AH29 -> 0
A30: =JAN!A30 -> Cell Phone | B30: * | AH30: =sum(B30:AF30) -> 0 | AI30: ='TOTALS&AVERAGES'!N30 | AJ30: =AI30-AH30 -> 0
A31: =JAN!A31 -> Laundry/Cleaners | B31: * | AH31: =sum(B31:AF31) -> 0 | AI31: ='TOTALS&AVERAGES'!N31 | AJ31: =AI31-AH31 -> 0
A32: =JAN!A32 -> Car Fuel | B32: * | AH32: =sum(B32:AF32) -> 0 | AI32: ='TOTALS&AVERAGES'!N32 | AJ32: =AI32-AH32 -> 0
A33: =JAN!A33 -> Car Insurance | B33: * | AH33: =sum(B33:AF33) -> 0 | AI33: ='TOTALS&AVERAGES'!N33 | AJ33: =AI33-AH33 -> 0
A34: =JAN!A34 -> Home Items | B34: * | AH34: =sum(B34:AF34) -> 0 | AI34: ='TOTALS&AVERAGES'!N34 | AJ34: =AI34-AH34 -> 0
A35: =JAN!A35 -> Internet | AH35: =sum(B35:AF35) -> 0 | AI35: ='TOTALS&AVERAGES'!N35 | AJ35: =AI35-AH35 -> 0
A36: =JAN!A36 -> Electricity | B36: * | AH36: =sum(B36:AF36) -> 0 | AI36: ='TOTALS&AVERAGES'!N36 | AJ36: =AI36-AH36 -> 0
A37: =JAN!A37 -> Card Fees | AH37: =sum(B37:AF37) -> 0 | AI37: ='TOTALS&AVERAGES'!N37 | AJ37: =AI37-AH37 -> 0
A38: =JAN!A38 -> Moving | AH38: =sum(B38:AF38) -> 0 | AI38: ='TOTALS&AVERAGES'!N38 | AJ38: =AI38-AH38 -> 0
A39: =JAN!A39 -> Toiletries | B39: * | AH39: =sum(B39:AF39) -> 0 | AI39: ='TOTALS&AVERAGES'!N39 | AJ39: =AI39-AH39 -> 0
A40: =JAN!A40 -> Storage | B40: * | AH40: =sum(B40:AF40) -> 0 | AI40: ='TOTALS&AVERAGES'!N40 | AJ40: =AI40-AH40 -> 0
A41: =JAN!A41 -> MTA/Public Transportation | B41: * | AH41: =sum(B41:AF41) -> 0 | AI41: ='TOTALS&AVERAGES'!N41 | AJ41: =AI41-AH41 -> 0
A42: =JAN!A42 -> Health Care | AH42: =sum(B42:AF42) -> 0 | AI42: ='TOTALS&AVERAGES'!N42 | AJ42: =AI42-AH42 -> 0
A43: =JAN!A43 -> Repairs | AH43: =sum(B43:AF43) -> 0 | AI43: ='TOTALS&AVERAGES'!N43 | AJ43: =AI43-AH43 -> 0
A44: =JAN!A44 -> Wants | B44: =SUM(B45:B52) -> 0 | C44: =SUM(C45:C52) -> 0 | D44: =SUM(D45:D52) -> 0 | E44: =SUM(E45:E52) -> 0 | F44: =SUM(F45:F52) -> 0 | G44: =SUM(G45:G52) -> 0 | H44: =SUM(H45:H52) -> 0 | I44: =SUM(I45:I52) -> 0 | ... AJ44: =SUM(AJ45:AJ52) -> 0
A45: =JAN!A45 -> Clothes | AH45: =sum(B45:AF45) -> 0 | AI45: ='TOTALS&AVERAGES'!N45 | AJ45: =AI45-AH45 -> 0
A46: =JAN!A46 -> Haircuts | AH46: =sum(B46:AF46) -> 0 | AI46: ='TOTALS&AVERAGES'!N46 | AJ46: =AI46-AH46 -> 0
A47: =JAN!A47 -> Dining Out/Take out/Events | AH47: =sum(B47:AF47) -> 0 | AI47: ='TOTALS&AVERAGES'!N47 | AJ47: =AI47-AH47 -> 0
A48: =JAN!A48 -> Gym Membership | AH48: =sum(B48:AF48) -> 0 | AI48: ='TOTALS&AVERAGES'!N48 | AJ48: =AI48-AH48 -> 0
A49: =JAN!A49 -> Subscriptions Zoom/Paramount/Club Free/News Subsription | AH49: =sum(B49:AF49) -> 0 | AI49: ='TOTALS&AVERAGES'!N49 | AJ49: =AI49-AH49 -> 0
A50: =JAN!A50 -> Snacks | AH50: =sum(B50:AF50) -> 0 | AI50: ='TOTALS&AVERAGES'!N50 | AJ50: =AI50-AH50 -> 0
A51: =JAN!A51 -> Vacations/Trip to see Brother Bryant/Trip to NM/Trip to San Antonio | AH51: =sum(B51:AF51) -> 0 | AI51: ='TOTALS&AVERAGES'!N51 | AJ51: =AI51-AH51 -> 0
A52: =JAN!A52 -> Other/Misc | AH52: =sum(B52:AF52) -> 0 | AI52: ='TOTALS&AVERAGES'!N52 | AJ52: =AI52-AH52 -> 0
A53: =JAN!A53 -> Savings | B53: =SUM(B54:B67) -> 0 | C53: =SUM(C54:C67) -> 0 | D53: =SUM(D54:D67) -> 0 | E53: =SUM(E54:E67) -> 0 | F53: =SUM(F54:F67) -> 0 | G53: =SUM(G54:G67) -> 0 | H53: =SUM(H54:H67) -> 0 | I53: =SUM(I54:I67) -> 0 | ... AJ53: =SUM(AJ54:AJ67) -> 0
A54: =JAN!A54 -> High yield Savings | B54: * | AH54: =sum(B54:AF54) -> 0 | AI54: ='TOTALS&AVERAGES'!N54 | AJ54: =AI54-AH54 -> 0
A55: =JAN!A55 -> Emergency Fund | B55: * | AH55: =sum(B55:AF55) -> 0 | AI55: ='TOTALS&AVERAGES'!N55 | AJ55: =AI55-AH55 -> 0
A56: =JAN!A56 -> Stocks/Index Fund | B56: * | AH56: =sum(B56:AF56) -> 0 | AI56: ='TOTALS&AVERAGES'!N56 | AJ56: =AI56-AH56 -> 0
A57: =JAN!A57 -> Real Estate | AH57: =sum(B57:AF57) -> 0 | AI57: ='TOTALS&AVERAGES'!N57 | AJ57: =AI57-AH57 -> 0
A58: =JAN!A58 -> Extra Debt Payment | AH58: =sum(B58:AF58) -> 0 | AI58: ='TOTALS&AVERAGES'!N58 | AJ58: =AI58-AH58 -> 0
A59: =JAN!A59 -> Gold | AH59: =sum(B59:AF59) -> 0 | AI59: ='TOTALS&AVERAGES'!N59 | AJ59: =AI59-AH59 -> 0
A60: =JAN!A60 -> Retirement/Roth IRA | AH60: =sum(B60:AF60) -> 0 | AI60: ='TOTALS&AVERAGES'!N60 | AJ60: =AI60-AH60 -> 0
A61: =JAN!A61 -> Annuities | AH61: =sum(B61:AF61) -> 0 | AI61: ='TOTALS&AVERAGES'!N61 | AJ61: =AI61-AH61 -> 0
A62: =JAN!A62 -> Life Insurance | AH62: =sum(B62:AF62) -> 0 | AI62: ='TOTALS&AVERAGES'!N62 | AJ62: =AI62-AH62 -> 0
A63: =JAN!A63 -> Watch | AH63: =sum(B63:AF63) -> 0 | AI63: ='TOTALS&AVERAGES'!N63 | AJ63: =AI63-AH63 -> 0
A64: =JAN!A64 -> CD | AH64: =sum(B64:AF64) -> 0 | AI64: ='TOTALS&AVERAGES'!N64 | AJ64: =AI64-AH64 -> 0
A65: =JAN!A65 -> Taxes Savings | AH65: =sum(B65:AF65) -> 0 | AI65: ='TOTALS&AVERAGES'!N65 | AJ65: =AI65-AH65 -> 0
A66: =JAN!A66 -> HSA | AH66: =sum(B66:AF66) -> 0 | AI66: ='TOTALS&AVERAGES'!N66 | AJ66: =AI66-AH66 -> 0
A67: =JAN!A67 -> - | AH67: =sum(B67:AF67) -> 0 | AI67: ='TOTALS&AVERAGES'!N67 | AJ67: =AI67-AH67 -> 0
A68: =JAN!A68 -> Debts | B68: =SUM(B69:B79) -> 0 | C68: =SUM(C69:C79) -> 0 | D68: =SUM(D69:D79) -> 0 | E68: =SUM(E69:E79) -> 0 | F68: =SUM(F69:F79) -> 0 | G68: =SUM(G69:G79) -> 0 | H68: =SUM(H69:H79) -> 0 | I68: =SUM(I69:I79) -> 0 | ... AJ68: =SUM(AJ69:AJ79) -> 0
A69: =JAN!A69 -> NFCU Loan 1151 | AH69: =sum(B69:AF69) -> 0 | AI69: ='TOTALS&AVERAGES'!N69 | AJ69: =AI69-AH69 -> 0
A70: =JAN!A70 -> NFCU Credit Card 8743 | AH70: =sum(B70:AF70) -> 0 | AI70: ='TOTALS&AVERAGES'!N70 | AJ70: =AI70-AH70 -> 0
A71: =JAN!A71 -> Capital One Credit Card 1057 | AH71: =sum(B71:AF71) -> 0 | AI71: ='TOTALS&AVERAGES'!N71 | AJ71: =AI71-AH71 -> 0
A72: =JAN!A72 -> Blink Fitness Collections | AH72: =sum(B72:AF72) -> 0 | AI72: ='TOTALS&AVERAGES'!N72 | AJ72: =AI72-AH72 -> 0
A73: =JAN!A73 -> T-Mobile Phone Bill | AH73: =sum(B73:AF73) -> 0 | AI73: ='TOTALS&AVERAGES'!N73 | AJ73: =AI73-AH73 -> 0
A74: =JAN!A74 -> TD Bank Collections | AH74: =sum(B74:AF74) -> 0 | AI74: ='TOTALS&AVERAGES'!N74 | AJ74: =AI74-AH74 -> 0
A75: =JAN!A75 -> Safegaurd Operations Collections | AH75: =sum(B75:AF75) -> 0 | AI75: ='TOTALS&AVERAGES'!N75 | AJ75: =AI75-AH75 -> 0
A76: =JAN!A76 -> BMCC Loan 474.03 | AH76: =sum(B76:AF76) -> 0 | AI76: ='TOTALS&AVERAGES'!N76 | AJ76: =AI76-AH76 -> 0
A77: =JAN!A77 -> Han Personal Debt (Paid) | AH77: =sum(B77:AF77) -> 0 | AI77: ='TOTALS&AVERAGES'!N77 | AJ77: =AI77-AH77 -> 0
A78: =JAN!A78 | AH78: =sum(B78:AF78) -> 0 | AI78: ='TOTALS&AVERAGES'!N78 | AJ78: =AI78-AH78 -> 0
A79: =JAN!A79 -> Total Debt: 8,551.73 | AH79: =sum(B79:AF79) -> 0 | AI79: ='TOTALS&AVERAGES'!N79 | AJ79: =AI79-AH79 -> 0
A80: =JAN!A80 -> School | B80: =SUM(B81:B91) -> 0 | C80: =SUM(C81:C91) -> 0 | D80: =SUM(D81:D91) -> 0 | E80: =SUM(E81:E91) -> 0 | F80: =SUM(F81:F91) -> 0 | G80: =SUM(G81:G91) -> 0 | H80: =SUM(H81:H91) -> 0 | I80: =SUM(I81:I91) -> 0 | ... AJ80: =SUM(AJ81:AJ91) -> 0
A81: =JAN!A81 -> Tuition | AH81: =sum(B81:AF81) -> 0 | AI81: ='TOTALS&AVERAGES'!N81 | AJ81: =AI81-AH81 -> 0
A82: =JAN!A82 -> Books | AH82: =sum(B82:AF82) -> 0 | AI82: ='TOTALS&AVERAGES'!N82 | AJ82: =AI82-AH82 -> 0
A83: =JAN!A83 | AH83: =sum(B83:AF83) -> 0 | AI83: ='TOTALS&AVERAGES'!N83 | AJ83: =AI83-AH83 -> 0
A84: =JAN!A84 | AH84: =sum(B84:AF84) -> 0 | AI84: ='TOTALS&AVERAGES'!N84 | AJ84: =AI84-AH84 -> 0
A85: =JAN!A85 | AH85: =sum(B85:AF85) -> 0 | AI85: ='TOTALS&AVERAGES'!N85 | AJ85: =AI85-AH85 -> 0
A86: =JAN!A86 | AH86: =sum(B86:AF86) -> 0 | AI86: ='TOTALS&AVERAGES'!N86 | AJ86: =AI86-AH86 -> 0
A87: =JAN!A87 | AH87: =sum(B87:AF87) -> 0 | AI87: ='TOTALS&AVERAGES'!N87 | AJ87: =AI87-AH87 -> 0
A88: =JAN!A88 | AH88: =sum(B88:AF88) -> 0 | AI88: ='TOTALS&AVERAGES'!N88 | AJ88: =AI88-AH88 -> 0
A89: =JAN!A89 | AH89: =sum(B89:AF89) -> 0 | AI89: ='TOTALS&AVERAGES'!N89 | AJ89: =AI89-AH89 -> 0
A90: =JAN!A90 | AH90: =sum(B90:AF90) -> 0 | AI90: ='TOTALS&AVERAGES'!N90 | AJ90: =AI90-AH90 -> 0
A91: =JAN!A91 | AH91: =sum(B91:AF91) -> 0 | AI91: ='TOTALS&AVERAGES'!N91 | AJ91: =AI91-AH91 -> 0
A92: =JAN!A92 | B92: =SUM(B93:B106) -> 0 | C92: =SUM(C93:C106) -> 0 | D92: =SUM(D93:D106) -> 0 | E92: =SUM(E93:E106) -> 0 | F92: =SUM(F93:F106) -> 0 | G92: =SUM(G93:G106) -> 0 | H92: =SUM(H93:H106) -> 0 | I92: =SUM(I93:I106) -> 0 | ... AJ92: =SUM(AJ93:AJ106) -> 0
A93: =JAN!A93 | AH93: =sum(B93:AF93) -> 0 | AI93: ='TOTALS&AVERAGES'!N93 | AJ93: =AI93-AH93 -> 0
A94: =JAN!A94 | AH94: =sum(B94:AF94) -> 0 | AI94: ='TOTALS&AVERAGES'!N94 | AJ94: =AI94-AH94 -> 0
A95: =JAN!A95 | B95: * | AH95: =sum(B95:AF95) -> 0 | AI95: ='TOTALS&AVERAGES'!N95 | AJ95: =AI95-AH95 -> 0
A96: =JAN!A96 | AH96: =sum(B96:AF96) -> 0 | AI96: ='TOTALS&AVERAGES'!N96 | AJ96: =AI96-AH96 -> 0
A97: =JAN!A97 | AH97: =sum(B97:AF97) -> 0 | AI97: ='TOTALS&AVERAGES'!N97 | AJ97: =AI97-AH97 -> 0
A98: =JAN!A98 | AH98: =sum(B98:AF98) -> 0 | AI98: ='TOTALS&AVERAGES'!N98 | AJ98: =AI98-AH98 -> 0
A99: =JAN!A99 | B99: * | AH99: =sum(B99:AF99) -> 0 | AI99: ='TOTALS&AVERAGES'!N99 | AJ99: =AI99-AH99 -> 0
A100: =JAN!A100 | B100: * | AH100: =sum(B100:AF100) -> 0 | AI100: ='TOTALS&AVERAGES'!N100 | AJ100: =AI100-AH100 -> 0
...

Sheet TOTALS&AVERAGES
A1: TOTALS & AVERAGES | B1: JAN | C1: FEB | D1: MAR | E1: APR | F1: MAY | G1: JUN | H1: JUL | I1: AUG | J1: SEPT | K1: OCT | L1: NOV | M1: DEC | N1: SPENDING PLAN 1 | O1: AVERAGES | P1: DEIFFERENCE
A2: INCOME
A3: =JAN!A3 -> Main Job | B3: =JAN!AH3 -> 0 | C3: =FEB!AE3 -> 0 | D3: =MAR!AH3 -> 0 | E3: =APR!AH3 -> 0 | F3: =MAY!AH3 -> 0 | G3: =JUN!AH3 -> 0 | H3: =JUL!AH3 -> 0 | I3: =AUG!AH3 -> 0 | J3: =SEP!AH3 -> 0 | K3: =OCT!AH3 -> 0 | L3: =NOV!AH3 -> 0 | M3: =DEC!AH3 -> 0 | O3: =AVERAGE(B3:N3) -> 0 | P3: =N3-O3 -> 0
A4: =JAN!A4 -> B Job | B4: =JAN!AH4 -> 0 | C4: =FEB!AE4 -> 0 | D4: =MAR!AH4 -> 0 | E4: =APR!AH4 -> 0 | F4: =MAY!AH4 -> 0 | G4: =JUN!AH4 -> 0 | H4: =JUL!AH4 -> 0 | I4: =AUG!AH4 -> 0 | J4: =SEP!AH4 -> 0 | K4: =OCT!AH4 -> 0 | L4: =NOV!AH4 -> 0 | M4: =DEC!AH4 -> 0 | O4: =AVERAGE(B4:M4) -> 0 | P4: =N4-O4 -> 0
A5: =JAN!A5 -> Bonuses | B5: =JAN!AH5 -> 0 | C5: =FEB!AE5 -> 0 | D5: =MAR!AH5 -> 0 | E5: =APR!AH5 -> 0 | F5: =MAY!AH5 -> 0 | G5: =JUN!AH5 -> 0 | H5: =JUL!AH5 -> 0 | I5: =AUG!AH5 -> 0 | J5: =SEP!AH5 -> 0 | K5: =OCT!AH5 -> 0 | L5: =NOV!AH5 -> 0 | M5: =DEC!AH5 -> 0 | O5: =AVERAGE(B5:M5) -> 0 | P5: =N5-O5 -> 0
A6: =JAN!A6 -> Gifts/Discounts | B6: =JAN!AH6 -> 0 | C6: =FEB!AE6 -> 0 | D6: =MAR!AH6 -> 0 | E6: =APR!AH6 -> 0 | F6: =MAY!AH6 -> 0 | G6: =JUN!AH6 -> 0 | H6: =JUL!AH6 -> 0 | I6: =AUG!AH6 -> 0 | J6: =SEP!AH6 -> 0 | K6: =OCT!AH6 -> 0 | L6: =NOV!AH6 -> 0 | M6: =DEC!AH6 -> 0 | O6: =AVERAGE(B6:M6) -> 0 | P6: =N6-O6 -> 0
A7: =JAN!A7 -> Reimbursement | B7: =JAN!AH7 -> 0 | C7: =FEB!AE7 -> 0 | D7: =MAR!AH7 -> 0 | E7: =APR!AH7 -> 0 | F7: =MAY!AH7 -> 0 | G7: =JUN!AH7 -> 0 | H7: =JUL!AH7 -> 0 | I7: =AUG!AH7 -> 0 | J7: =SEP!AH7 -> 0 | K7: =OCT!AH7 -> 0 | L7: =NOV!AH7 -> 0 | M7: =DEC!AH7 -> 0 | O7: =AVERAGE(B7:M7) -> 0 | P7: =N7-O7 -> 0
A8: =JAN!A8 -> Government Assistance | B8: =JAN!AH8 -> 0 | C8: =FEB!AE8 -> 0 | D8: =MAR!AH8 -> 0 | E8: =APR!AH8 -> 0 | F8: =MAY!AH8 -> 0 | G8: =JUN!AH8 -> 0 | H8: =JUL!AH8 -> 0 | I8: =AUG!AH8 -> 0 | J8: =SEP!AH8 -> 0 | K8: =OCT!AH8 -> 0 | L8: =NOV!AH8 -> 0 | M8: =DEC!AH8 -> 0 | O8: =AVERAGE(B8:N8) -> 0 | P8: =N8-O8 -> 0
A9: =JAN!A9 -> Side Hustles | B9: =JAN!AH9 -> 0 | C9: =FEB!AE9 -> 0 | D9: =MAR!AH9 -> 0 | E9: =APR!AH9 -> 0 | F9: =MAY!AH9 -> 0 | G9: =JUN!AH9 -> 0 | H9: =JUL!AH9 -> 0 | I9: =AUG!AH9 -> 0 | J9: =SEP!AH9 -> 0 | K9: =OCT!AH9 -> 0 | L9: =NOV!AH9 -> 0 | M9: =DEC!AH9 -> 0 | O9: =AVERAGE(B9:N9) -> 0 | P9: =N9-O9 -> 0
A10: =JAN!A10 -> Interest/Rewards | B10: =JAN!AH10 -> 0 | C10: =FEB!AE10 -> 0 | D10: =MAR!AH10 -> 0 | E10: =APR!AH10 -> 0 | F10: =MAY!AH10 -> 0 | G10: =JUN!AH10 -> 0 | H10: =JUL!AH10 -> 0 | I10: =AUG!AH10 -> 0 | J10: =SEP!AH10 -> 0 | K10: =OCT!AH10 -> 0 | L10: =NOV!AH10 -> 0 | M10: =DEC!AH10 -> 0 | O10: =AVERAGE(B10:M10) -> 0 | P10: =N10-O10 -> 0
A11: =JAN!A11 -> VA Benefits | B11: =JAN!AH11 -> 0 | C11: =FEB!AE11 -> 0 | D11: =MAR!AH11 -> 0 | E11: =APR!AH11 -> 0 | F11: =MAY!AH11 -> 0 | G11: =JUN!AH11 -> 0 | H11: =JUL!AH11 -> 0 | I11: =AUG!AH11 -> 0 | J11: =SEP!AH11 -> 0 | K11: =OCT!AH11 -> 0 | L11: =NOV!AH11 -> 0 | M11: =DEC!AH11 -> 0 | O11: =AVERAGE(B11:M11) -> 0 | P11: =N11-O11 -> 0
A12: =JAN!A12 -> Asset Cash Out | B12: =JAN!AH12 -> 0 | C12: =FEB!AE12 -> 0 | D12: =MAR!AH12 -> 0 | E12: =APR!AH12 -> 0 | F12: =MAY!AH12 -> 0 | G12: =JUN!AH12 -> 0 | H12: =JUL!AH12 -> 0 | I12: =AUG!AH12 -> 0 | J12: =SEP!AH12 -> 0 | K12: =OCT!AH12 -> 0 | L12: =NOV!AH12 -> 0 | M12: =DEC!AH12 -> 0 | O12: =AVERAGE(B12:M12) -> 0 | P12: =N12-O12 -> 0
A13: =JAN!A13 -> Fed Tax Refund | B13: =JAN!AH13 -> 0 | C13: =FEB!AE13 -> 0 | D13: =MAR!AH13 -> 0 | E13: =APR!AH13 -> 0 | F13: =MAY!AH13 -> 0 | G13: =JUN!AH13 -> 0 | H13: =JUL!AH13 -> 0 | I13: =AUG!AH13 -> 0 | J13: =SEP!AH13 -> 0 | K13: =OCT!AH13 -> 0 | L13: =NOV!AH13 -> 0 | M13: =DEC!AH13 -> 0 | O13: =AVERAGE(B13:M13) -> 0 | P13: =N13-O13 -> 0
A14: =JAN!A14 -> State Tax Refund | B14: =JAN!AH14 -> 0 | C14: =FEB!AE14 -> 0 | D14: =MAR!AH14 -> 0 | E14: =APR!AH14 -> 0 | F14: =MAY!AH14 -> 0 | G14: =JUN!AH14 -> 0 | H14: =JUL!AH14 -> 0 | I14: =AUG!AH14 -> 0 | J14: =SEP!AH14 -> 0 | K14: =OCT!AH14 -> 0 | L14: =NOV!AH14 -> 0 | M14: =DEC!AH14 -> 0 | O14: =AVERAGE(B14:M14) -> 0 | P14: =N14-O14 -> 0
A15: TOTAL INCOME BEFORE TAXES | B15: =SUM(B3:B14) -> 0 | C15: =SUM(C3:C14) -> 0 | D15: =SUM(D3:D14) -> 0 | E15: =SUM(E3:E14) -> 0 | F15: =SUM(F3:F14) -> 0 | G15: =SUM(G3:G14) -> 0 | H15: =SUM(H3:H14) -> 0 | I15: =SUM(I3:I14) -> 0 | ... P15: =SUM(P3:P14) -> 0
A16: EXPENSES BY D.A. CATEGORIES
A17: 1 - SPIRITUAL | B17: =SUM(B18:B26) -> 0 | C17: =SUM(C18:C26) -> 0 | D17: =SUM(D18:D26) -> 0 | E17: =SUM(E18:E26) -> 0 | F17: =SUM(F18:F26) -> 0 | G17: =SUM(G18:G26) -> 0 | H17: =SUM(H18:H26) -> 0 | I17: =SUM(I18:I26) -> 0 | ... P17: =SUM(P18:P26) -> 0
A18: =JAN!A18 -> Tithing/Church Donation | B18: =JAN!AH18 -> 0 | C18: =FEB!AE18 -> 0 | D18: =MAR!AH18 -> 0 | E18: =APR!AH18 -> 0 | F18: =MAY!AH18 -> 0 | G18: =JUN!AH18 -> 0 | H18: =JUL!AH18 -> 0 | I18: =AUG!AH18 -> 0 | J18: =SEP!AH18 -> 0 | K18: =OCT!AH18 -> 0 | L18: =NOV!AH18 -> 0 | M18: =DEC!AH18 -> 0 | O18: =AVERAGE(B18:N18) -> 0 | P18: =N18-O18 -> 0
A19: =JAN!A19 -> Books | B19: =JAN!AH19 -> 0 | C19: =FEB!AE19 -> 0 | D19: =MAR!AH19 -> 0 | E19: =APR!AH19 -> 0 | F19: =MAY!AH19 -> 0 | G19: =JUN!AH19 -> 0 | H19: =JUL!AH19 -> 0 | I19: =AUG!AH19 -> 0 | J19: =SEP!AH19 -> 0 | K19: =OCT!AH19 -> 0 | L19: =NOV!AH19 -> 0 | M19: =DEC!AH19 -> 0 | O19: =AVERAGE(B19:M19) -> 0 | P19: =N19-O19 -> 0
A20: =JAN!A20 -> Charity | B20: =JAN!AH20 -> 0 | C20: =FEB!AE20 -> 0 | D20: =MAR!AH20 -> 0 | E20: =APR!AH20 -> 0 | F20: =MAY!AH20 -> 0 | G20: =JUN!AH20 -> 0 | H20: =JUL!AH20 -> 0 | I20: =AUG!AH20 -> 0 | J20: =SEP!AH20 -> 0 | K20: =OCT!AH20 -> 0 | L20: =NOV!AH20 -> 0 | M20: =DEC!AH20 -> 0 | O20: =AVERAGE(B20:M20) -> 0 | P20: =N20-O20 -> 0
A21: =JAN!A21 -> Workshops | B21: =JAN!AH21 -> 0 | C21: =FEB!AE21 -> 0 | D21: =MAR!AH21 -> 0 | E21: =APR!AH21 -> 0 | F21: =MAY!AH21 -> 0 | G21: =JUN!AH21 -> 0 | H21: =JUL!AH21 -> 0 | I21: =AUG!AH21 -> 0 | J21: =SEP!AH21 -> 0 | K21: =OCT!AH21 -> 0 | L21: =NOV!AH21 -> 0 | M21: =DEC!AH21 -> 0 | O21: =AVERAGE(B21:M21) -> 0 | P21: =N21-O21 -> 0
A22: =JAN!A22 -> Generosity | B22: =JAN!AH22 -> 0 | C22: =FEB!AE22 -> 0 | D22: =MAR!AH22 -> 0 | E22: =APR!AH22 -> 0 | F22: =MAY!AH22 -> 0 | G22: =JUN!AH22 -> 0 | H22: =JUL!AH22 -> 0 | I22: =AUG!AH22 -> 0 | J22: =SEP!AH22 -> 0 | K22: =OCT!AH22 -> 0 | L22: =NOV!AH22 -> 0 | M22: =DEC!AH22 -> 0 | O22: =AVERAGE(B22:M22) -> 0 | P22: =N22-O22 -> 0
A23: =JAN!A23 -> Retreats / Seminars | B23: =JAN!AH23 -> 0 | C23: =FEB!AE23 -> 0 | D23: =MAR!AH23 -> 0 | E23: =APR!AH23 -> 0 | F23: =MAY!AH23 -> 0 | G23: =JUN!AH23 -> 0 | H23: =JUL!AH23 -> 0 | I23: =AUG!AH23 -> 0 | J23: =SEP!AH23 -> 0 | K23: =OCT!AH23 -> 0 | L23: =NOV!AH23 -> 0 | M23: =DEC!AH23 -> 0 | O23: =AVERAGE(B23:M23) -> 0 | P23: =N23-O23 -> 0
A24: =JAN!A24 -> 7TH TRADITION / FELLOWSHIP/ PRG | B24: =JAN!AH24 -> 0 | C24: =FEB!AE24 -> 0 | D24: =MAR!AH24 -> 0 | E24: =APR!AH24 -> 0 | F24: =MAY!AH24 -> 0 | G24: =JUN!AH24 -> 0 | H24: =JUL!AH24 -> 0 | I24: =AUG!AH24 -> 0 | J24: =SEP!AH24 -> 0 | K24: =OCT!AH24 -> 0 | L24: =NOV!AH24 -> 0 | M24: =DEC!AH24 -> 0 | O24: =AVERAGE(B24:M24) -> 0 | P24: =N24-O24 -> 0
A25: =JAN!A25 -> Conferences | B25: =JAN!AH25 -> 0 | C25: =FEB!AE25 -> 0 | D25: =MAR!AH25 -> 0 | E25: =APR!AH25 -> 0 | F25: =MAY!AH25 -> 0 | G25: =JUN!AH25 -> 0 | H25: =JUL!AH25 -> 0 | I25: =AUG!AH25 -> 0 | J25: =SEP!AH25 -> 0 | K25: =OCT!AH25 -> 0 | L25: =NOV!AH25 -> 0 | M25: =DEC!AH25 -> 0 | O25: =AVERAGE(B25:M25) -> 0 | P25: =N25-O25 -> 0
A26: =JAN!A26 -> Career Investment | B26: =JAN!AH26 -> 0 | C26: =FEB!AE26 -> 0 | D26: =MAR!AH26 -> 0 | E26: =APR!AH26 -> 0 | F26: =MAY!AH26 -> 0 | G26: =JUN!AH26 -> 0 | H26: =JUL!AH26 -> 0 | I26: =AUG!AH26 -> 0 | J26: =SEP!AH26 -> 0 | K26: =OCT!AH26 -> 0 | L26: =NOV!AH26 -> 0 | M26: =DEC!AH26 -> 0 | O26: =AVERAGE(B26:M26) -> 0 | P26: =N26-O26 -> 0
A27: =JAN!A27 -> Needs | B27: =SUM(B28:B43) -> 0 | C27: =SUM(C28:C43) -> 0 | D27: =SUM(D28:D43) -> 0 | E27: =SUM(E28:E43) -> 0 | F27: =SUM(F28:F43) -> 0 | G27: =SUM(G28:G43) -> 0 | H27: =SUM(H28:H43) -> 0 | I27: =SUM(I28:I43) -> 0 | ... P27: =SUM(P28:P43) -> 0
A28: =JAN!A28 -> Groceries | B28: =JAN!AH28 -> 0 | C28: =FEB!AE28 -> 0 | D28: =MAR!AH28 -> 0 | E28: =APR!AH28 -> 0 | F28: =MAY!AH28 -> 0 | G28: =JUN!AH28 -> 0 | H28: =JUL!AH28 -> 0 | I28: =AUG!AH28 -> 0 | J28: =SEP!AH28 -> 0 | K28: =OCT!AH28 -> 0 | L28: =NOV!AH28 -> 0 | M28: =DEC!AH28 -> 0 | O28: =AVERAGE(B28:M28) -> 0 | P28: =N28-O28 -> 0
A29: =JAN!A29 -> Rent/Mortage | B29: =JAN!AH29 -> 0 | C29: =FEB!AE29 -> 0 | D29: =MAR!AH29 -> 0 | E29: =APR!AH29 -> 0 | F29: =MAY!AH29 -> 0 | G29: =JUN!AH29 -> 0 | H29: =JUL!AH29 -> 0 | I29: =AUG!AH29 -> 0 | J29: =SEP!AH29 -> 0 | K29: =OCT!AH29 -> 0 | L29: =NOV!AH29 -> 0 | M29: =DEC!AH29 -> 0 | O29: =AVERAGE(B29:M29) -> 0 | P29: =N29-O29 -> 0
A30: =JAN!A30 -> Cell Phone | B30: =JAN!AH30 -> 0 | C30: =FEB!AE30 -> 0 | D30: =MAR!AH30 -> 0 | E30: =APR!AH30 -> 0 | F30: =MAY!AH30 -> 0 | G30: =JUN!AH30 -> 0 | H30: =JUL!AH30 -> 0 | I30: =AUG!AH30 -> 0 | J30: =SEP!AH30 -> 0 | K30: =OCT!AH30 -> 0 | L30: =NOV!AH30 -> 0 | M30: =DEC!AH30 -> 0 | O30: =AVERAGE(B30:M30) -> 0 | P30: =N30-O30 -> 0
A31: =JAN!A31 -> Laundry/Cleaners | B31: =JAN!AH31 -> 0 | C31: =FEB!AE31 -> 0 | D31: =MAR!AH31 -> 0 | E31: =APR!AH31 -> 0 | F31: =MAY!AH31 -> 0 | G31: =JUN!AH31 -> 0 | H31: =JUL!AH31 -> 0 | I31: =AUG!AH31 -> 0 | J31: =SEP!AH31 -> 0 | K31: =OCT!AH31 -> 0 | L31: =NOV!AH31 -> 0 | M31: =DEC!AH31 -> 0 | O31: =AVERAGE(B31:M31) -> 0 | P31: =N31-O31 -> 0
A32: =JAN!A32 -> Car Fuel | B32: =JAN!AH32 -> 0 | C32: =FEB!AE32 -> 0 | D32: =MAR!AH32 -> 0 | E32: =APR!AH32 -> 0 | F32: =MAY!AH32 -> 0 | G32: =JUN!AH32 -> 0 | H32: =JUL!AH32 -> 0 | I32: =AUG!AH32 -> 0 | J32: =SEP!AH32 -> 0 | K32: =OCT!AH32 -> 0 | L32: =NOV!AH32 -> 0 | M32: =DEC!AH32 -> 0 | O32: =AVERAGE(B32:M32) -> 0 | P32: =N32-O32 -> 0
A33: =JAN!A33 -> Car Insurance | B33: =JAN!AH33 -> 0 | C33: =FEB!AE33 -> 0 | D33: =MAR!AH33 -> 0 | E33: =APR!AH33 -> 0 | F33: =MAY!AH33 -> 0 | G33: =JUN!AH33 -> 0 | H33: =JUL!AH33 -> 0 | I33: =AUG!AH33 -> 0 | J33: =SEP!AH33 -> 0 | K33: =OCT!AH33 -> 0 | L33: =NOV!AH33 -> 0 | M33: =DEC!AH33 -> 0 | O33: =AVERAGE(B33:M33) -> 0 | P33: =N33-O33 -> 0
A34: =JAN!A34 -> Home Items | B34: =JAN!AH34 -> 0 | C34: =FEB!AE34 -> 0 | D34: =MAR!AH34 -> 0 | E34: =APR!AH34 -> 0 | F34: =MAY!AH34 -> 0 | G34: =JUN!AH34 -> 0 | H34: =JUL!AH34 -> 0 | I34: =AUG!AH34 -> 0 | J34: =SEP!AH34 -> 0 | K34: =OCT!AH34 -> 0 | L34: =NOV!AH34 -> 0 | M34: =DEC!AH34 -> 0 | O34: =AVERAGE(B34:M34) -> 0 | P34: =N34-O34 -> 0
A35: =JAN!A35 -> Internet | B35: =JAN!AH35 -> 0 | C35: =FEB!AE35 -> 0 | D35: =MAR!AH35 -> 0 | E35: =APR!AH35 -> 0 | F35: =MAY!AH35 -> 0 | G35: =JUN!AH35 -> 0 | H35: =JUL!AH35 -> 0 | I35: =AUG!AH35 -> 0 | J35: =SEP!AH35 -> 0 | K35: =OCT!AH35 -> 0 | L35: =NOV!AH35 -> 0 | M35: =DEC!AH35 -> 0 | O35: =AVERAGE(B35:M35) -> 0 | P35: =N35-O35 -> 0
A36: =JAN!A36 -> Electricity | B36: =JAN!AH36 -> 0 | C36: =FEB!AE36 -> 0 | D36: =MAR!AH36 -> 0 | E36: =APR!AH36 -> 0 | F36: =MAY!AH36 -> 0 | G36: =JUN!AH36 -> 0 | H36: =JUL!AH36 -> 0 | I36: =AUG!AH36 -> 0 | J36: =SEP!AH36 -> 0 | K36: =OCT!AH36 -> 0 | L36: =NOV!AH36 -> 0 | M36: =DEC!AH36 -> 0 | O36: =AVERAGE(B36:M36) -> 0 | P36: =N36-O36 -> 0
A37: =JAN!A37 -> Card Fees | B37: =JAN!AH37 -> 0 | C37: =FEB!AE37 -> 0 | D37: =MAR!AH37 -> 0 | E37: =APR!AH37 -> 0 | F37: =MAY!AH37 -> 0 | G37: =JUN!AH37 -> 0 | H37: =JUL!AH37 -> 0 | I37: =AUG!AH37 -> 0 | J37: =SEP!AH37 -> 0 | K37: =OCT!AH37 -> 0 | L37: =NOV!AH37 -> 0 | M37: =DEC!AH37 -> 0 | O37: =AVERAGE(B37:M37) -> 0 | P37: =N37-O37 -> 0
A38: =JAN!A38 -> Moving | B38: =JAN!AH38 -> 0 | C38: =FEB!AE38 -> 0 | D38: =MAR!AH38 -> 0 | E38: =APR!AH38 -> 0 | F38: =MAY!AH38 -> 0 | G38: =JUN!AH38 -> 0 | H38: =JUL!AH38 -> 0 | I38: =AUG!AH38 -> 0 | J38: =SEP!AH38 -> 0 | K38: =OCT!AH38 -> 0 | L38: =NOV!AH38 -> 0 | M38: =DEC!AH38 -> 0 | O38: =AVERAGE(B38:M38) -> 0 | P38: =N38-O38 -> 0
A39: =JAN!A39 -> Toiletries | B39: =JAN!AH39 -> 0 | C39: =FEB!AE39 -> 0 | D39: =MAR!AH39 -> 0 | E39: =APR!AH39 -> 0 | F39: =MAY!AH39 -> 0 | G39: =JUN!AH39 -> 0 | H39: =JUL!AH39 -> 0 | I39: =AUG!AH39 -> 0 | J39: =SEP!AH39 -> 0 | K39: =OCT!AH39 -> 0 | L39: =NOV!AH39 -> 0 | M39: =DEC!AH39 -> 0 | O39: =AVERAGE(B39:M39) -> 0 | P39: =N39-O39 -> 0
... A43: =JAN!A43 -> Repairs | B43: =JAN!AH43 -> 0 | C43: =FEB!AE43 -> 0 | D43: =MAR!AH43 -> 0 | E43: =APR!AH43 -> 0 | F43: =MAY!AH43 -> 0 | G43: =JUN!AH43 -> 0 | H43: =JUL!AH43 -> 0 | I43: =AUG!AH43 -> 0 | J43: =SEP!AH43 -> 0 | K43: =OCT!AH43 -> 0 | L43: =NOV!AH43 -> 0 | M43: =DEC!AH43 -> 0 | O43: =AVERAGE(B43:M43) -> 0 | P43: =N43-O43 -> 0
A44: =JAN!A44 -> Wants | B44: =SUM(B45:B52) -> 0 | C44: =SUM(C45:C60) -> 0 | D44: =SUM(D45:D60) -> 470.32 | E44: =SUM(E45:E60) -> 0 | F44: =SUM(F45:F60) -> 0 | G44: =SUM(G45:G60) -> 0 | H44: =SUM(H45:H60) -> 0 | I44: =SUM(I45:I60) -> 0 | J44: =SUM(J45:J60) -> 0 | ... L44: =SUM(L45:L60) -> 0 | M44: =DEC!H44 -> 0 | N44: =DEC!I44 -> 0 | O44: =DEC!J44 -> 0 | P44: =DEC!K44 -> 0
A45: =JAN!A45 -> Clothes | B45: =JAN!AH45 -> 0 | C45: =FEB!AE45 -> 0 | D45: =MAR!AH45 -> 0 | E45: =APR!AH45 -> 0 | F45: =MAY!AH45 -> 0 | G45: =JUN!AH45 -> 0 | H45: =JUL!AH45 -> 0 | I45: =AUG!AH45 -> 0 | J45: =SEP!AH45 -> 0 | K45: =OCT!AH45 -> 0 | L45: =NOV!AH45 -> 0 | M45: =DEC!AH45 -> 0 | O45: =AVERAGE(B45:M45) -> 0 | P45: =N45-O45 -> 0
A46: =JAN!A46 -> Haircuts | B46: =JAN!AH46 -> 0 | C46: =FEB!AE46 -> 0 | D46: =MAR!AH46 -> 0 | E46: =APR!AH46 -> 0 | F46: =MAY!AH46 -> 0 | G46: =JUN!AH46 -> 0 | H46: =JUL!AH46 -> 0 | I46: =AUG!AH46 -> 0 | J46: =SEP!AH46 -> 0 | K46: =OCT!AH46 -> 0 | L46: =NOV!AH46 -> 0 | M46: =DEC!AH46 -> 0 | O46: =AVERAGE(B46:M46) -> 0 | P46: =N46-O46 -> 0
A47: =JAN!A47 -> Dining Out/Take out/Events | B47: =JAN!AH47 -> 0 | C47: =FEB!AE47 -> 0 | D47: =MAR!AH47 -> 0 | E47: =APR!AH47 -> 0 | F47: =MAY!AH47 -> 0 | G47: =JUN!AH47 -> 0 | H47: =JUL!AH47 -> 0 | I47: =AUG!AH47 -> 0 | J47: =SEP!AH47 -> 0 | K47: =OCT!AH47 -> 0 | L47: =NOV!AH47 -> 0 | M47: =DEC!AH47 -> 0 | O47: =AVERAGE(B47:M47) -> 0 | P47: =N47-O47 -> 0
A48: =JAN!A48 -> Gym Membership | B48: =JAN!AH48 -> 0 | C48: =FEB!AE48 -> 0 | D48: =MAR!AH48 -> 0 | E48: =APR!AH48 -> 0 | F48: =MAY!AH48 -> 0 | G48: =JUN!AH48 -> 0 | H48: =JUL!AH48 -> 0 | I48: =AUG!AH48 -> 0 | J48: =SEP!AH48 -> 0 | K48: =OCT!AH48 -> 0 | L48: =NOV!AH48 -> 0 | M48: =DEC!AH48 -> 0 | O48: =AVERAGE(B48:M48) -> 0 | P48: =N48-O48 -> 0
A49: =JAN!A49 -> Subscriptions Zoom/Paramount/Club Free/News Subsription | B49: =JAN!AH49 -> 0 | C49: =FEB!AE49 -> 0 | D49: =MAR!AH49 -> 0 | E49: =APR!AH49 -> 0 | F49: =MAY!AH49 -> 0 | G49: =JUN!AH49 -> 0 | H49: =JUL!AH49 -> 0 | I49: =AUG!AH49 -> 0 | J49: =SEP!AH49 -> 0 | K49: =OCT!AH49 -> 0 | L49: =NOV!AH49 -> 0 | M49: =DEC!AH49 -> 0 | O49: =AVERAGE(B49:M49) -> 0 | P49: =N49-O49 -> 0
A50: =JAN!A50 -> Snacks | B50: =JAN!AH50 -> 0 | C50: =FEB!AE50 -> 0 | D50: =MAR!AH50 -> 0 | E50: =APR!AH50 -> 0 | F50: =MAY!AH50 -> 0 | G50: =JUN!AH50 -> 0 | H50: =JUL!AH50 -> 0 | I50: =AUG!AH50 -> 0 | J50: =SEP!AH50 -> 0 | K50: =OCT!AH50 -> 0 | L50: =NOV!AH50 -> 0 | M50: =DEC!AH50 -> 0 | O50: =AVERAGE(B50:M50) -> 0 | P50: =N50-O50 -> 0
A51: =JAN!A51 -> Vacations/Trip to see Brother Bryant/Trip to NM/Trip to San Antonio | B51: =JAN!AH51 -> 0 | C51: =FEB!AE51 -> 0 | D51: =MAR!AH51 -> 0 | E51: =APR!AH51 -> 0 | F51: =MAY!AH51 -> 0 | G51: =JUN!AH51 -> 0 | H51: =JUL!AH51 -> 0 | I51: =AUG!AH51 -> 0 | J51: =SEP!AH51 -> 0 | K51: =OCT!AH51 -> 0 | L51: =NOV!AH51 -> 0 | M51: =DEC!AH51 -> 0 | O51: =AVERAGE(B51:M51) -> 0 | P51: =N51-O51 -> 0
A52: =JAN!A52 -> Other/Misc | B52: =JAN!AH52 -> 0 | C52: =FEB!AE52 -> 0 | D52: =MAR!AH52 -> 0 | E52: =APR!AH52 -> 0 | F52: =MAY!AH52 -> 0 | G52: =JUN!AH52 -> 0 | H52: =JUL!AH52 -> 0 | I52: =AUG!AH52 -> 0 | J52: =SEP!AH52 -> 0 | K52: =OCT!AH52 -> 0 | L52: =NOV!AH52 -> 0 | M52: =DEC!AH52 -> 0 | O52: =AVERAGE(B52:M52) -> 0 | P52: =N52-O52 -> 0
A53: =JAN!A53 -> Savings | B53: =SUM(B54:B67) -> 0 | C53: =SUM(C54:C69) -> 0 | D53: =SUM(D54:D69) -> 235.16 | E53: =SUM(E54:E69) -> 0 | F53: =SUM(F54:F69) -> 0 | G53: =SUM(G54:G69) -> 0 | H53: =SUM(H54:H69) -> 0 | I53: =SUM(I54:I69) -> 0 | J53: =SUM(J54:J69) -> 0 | ... L53: =SUM(L54:L69) -> 0 | M53: =DEC!H53 -> 0 | N53: =DEC!I53 -> 0 | O53: =DEC!J53 -> 0 | P53: =DEC!K53 -> 0
A54: =JAN!A54 -> High yield Savings | B54: =JAN!AH54 -> 0 | C54: =FEB!AE54 -> 0 | D54: =MAR!AH54 -> 235.16 | E54: =APR!AH54 -> 0 | F54: =MAY!AH54 -> 0 | G54: =JUN!AH54 -> 0 | H54: =JUL!AH54 -> 0 | I54: =AUG!AH54 -> 0 | J54: =SEP!AH54 -> 0 | K54: =OCT!AH54 -> 0 | L54: =NOV!AH54 -> 0 | M54: =DEC!AH54 -> 0 | O54: =AVERAGE(B54:M54) -> 19.596667 | P54: =N54-O54 -> -19.596667
A55: =JAN!A55 -> Emergency Fund | B55: =JAN!AH55 -> 0 | C55: =FEB!AE55 -> 0 | D55: =MAR!AH55 -> 0 | E55: =APR!AH55 -> 0 | F55: =MAY!AH55 -> 0 | G55: =JUN!AH55 -> 0 | H55: =JUL!AH55 -> 0 | I55: =AUG!AH55 -> 0 | J55: =SEP!AH55 -> 0 | K55: =OCT!AH55 -> 0 | L55: =NOV!AH55 -> 0 | M55: =DEC!AH55 -> 0 | O55: =AVERAGE(B55:M55) -> 0 | P55: =N55-O55 -> 0
A56: =JAN!A56 -> Stocks/Index Fund | B56: =JAN!AH56 -> 0 | C56: =FEB!AE56 -> 0 | D56: =MAR!AH56 -> 0 | E56: =APR!AH56 -> 0 | F56: =MAY!AH56 -> 0 | G56: =JUN!AH56 -> 0 | H56: =JUL!AH56 -> 0 | I56: =AUG!AH56 -> 0 | J56: =SEP!AH56 -> 0 | K56: =OCT!AH56 -> 0 | L56: =NOV!AH56 -> 0 | M56: =DEC!AH56 -> 0 | O56: =AVERAGE(B56:M56) -> 0 | P56: =N56-O56 -> 0
A57: =JAN!A57 -> Real Estate | B57: =JAN!AH57 -> 0 | C57: =FEB!AE57 -> 0 | D57: =MAR!AH57 -> 0 | E57: =APR!AH57 -> 0 | F57: =MAY!AH57 -> 0 | G57: =JUN!AH57 -> 0 | H57: =JUL!AH57 -> 0 | I57: =AUG!AH57 -> 0 | J57: =SEP!AH57 -> 0 | K57: =OCT!AH57 -> 0 | L57: =NOV!AH57 -> 0 | M57: =DEC!AH57 -> 0 | O57: =AVERAGE(B57:M57) -> 0 | P57: =N57-O57 -> 0
A58: =JAN!A58 -> Extra Debt Payment | B58: =JAN!AH58 -> 0 | C58: =FEB!AE58 -> 0 | D58: =MAR!AH58 -> 0 | E58: =APR!AH58 -> 0 | F58: =MAY!AH58 -> 0 | G58: =JUN!AH58 -> 0 | H58: =JUL!AH58 -> 0 | I58: =AUG!AH58 -> 0 | J58: =SEP!AH58 -> 0 | K58: =OCT!AH58 -> 0 | L58: =NOV!AH58 -> 0 | M58: =DEC!AH58 -> 0 | O58: =AVERAGE(B58:M58) -> 0 | P58: =N58-O58 -> 0
A59: =JAN!A59 -> Gold | B59: =JAN!AH59 -> 0 | C59: =FEB!AE59 -> 0 | D59: =MAR!AH59 -> 0 | E59: =APR!AH59 -> 0 | F59: =MAY!AH59 -> 0 | G59: =JUN!AH59 -> 0 | H59: =JUL!AH59 -> 0 | I59: =AUG!AH59 -> 0 | J59: =SEP!AH59 -> 0 | K59: =OCT!AH59 -> 0 | L59: =NOV!AH59 -> 0 | M59: =DEC!AH59 -> 0 | O59: =AVERAGE(B59:M59) -> 0 | P59: =N59-O59 -> 0
A60: =JAN!A60 -> Retirement/Roth IRA | B60: =JAN!AH60 -> 0 | C60: =FEB!AE60 -> 0 | D60: =MAR!AH60 -> 0 | E60: =APR!AH60 -> 0 | F60: =MAY!AH60 -> 0 | G60: =JUN!AH60 -> 0 | H60: =JUL!AH60 -> 0 | I60: =AUG!AH60 -> 0 | J60: =SEP!AH60 -> 0 | K60: =OCT!AH60 -> 0 | L60: =NOV!AH60 -> 0 | M60: =DEC!AH60 -> 0 | O60: =AVERAGE(B60:M60) -> 0 | P60: =N60-O60 -> 0
A61: =JAN!A61 -> Annuities | B61: =JAN!AH61 -> 0 | C61: =FEB!AE61 -> 0 | D61: =MAR!AH61 -> 0 | E61: =APR!AH61 -> 0 | F61: =MAY!AH61 -> 0 | G61: =JUN!AH61 -> 0 | H61: =JUL!AH61 -> 0 | I61: =AUG!AH61 -> 0 | J61: =SEP!AH61 -> 0 | K61: =OCT!AH61 -> 0 | L61: =NOV!AH61 -> 0 | M61: =DEC!AH61 -> 0 | O61: =AVERAGE(B61:M61) -> 0 | P61: =N61-O61 -> 0
A62: =JAN!A62 -> Life Insurance | B62: =JAN!AH62 -> 0 | C62: =FEB!AE62 -> 0 | D62: =MAR!AH62 -> 0 | E62: =APR!AH62 -> 0 | F62: =MAY!AH62 -> 0 | G62: =JUN!AH62 -> 0 | H62: =JUL!AH62 -> 0 | I62: =AUG!AH62 -> 0 | J62: =SEP!AH62 -> 0 | K62: =OCT!AH62 -> 0 | L62: =NOV!AH62 -> 0 | M62: =DEC!AH62 -> 0 | O62: =AVERAGE(B62:M62) -> 0 | P62: =N62-O62 -> 0
A63: =JAN!A63 -> Watch | B63: =JAN!AH63 -> 0 | C63: =FEB!AE63 -> 0 | D63: =MAR!AH63 -> 0 | E63: =APR!AH63 -> 0 | F63: =MAY!AH63 -> 0 | G63: =JUN!AH63 -> 0 | H63: =JUL!AH63 -> 0 | I63: =AUG!AH63 -> 0 | J63: =SEP!AH63 -> 0 | K63: =OCT!AH63 -> 0 | L63: =NOV!AH63 -> 0 | M63: =DEC!AH63 -> 0 | O63: =AVERAGE(B63:M63) -> 0 | P63: =N63-O63 -> 0
A64: =JAN!A64 -> CD | B64: =JAN!AH64 -> 0 | C64: =FEB!AE64 -> 0 | D64: =MAR!AH64 -> 0 | E64: =APR!AH64 -> 0 | F64: =MAY!AH64 -> 0 | G64: =JUN!AH64 -> 0 | H64: =JUL!AH64 -> 0 | I64: =AUG!AH64 -> 0 | J64: =SEP!AH64 -> 0 | K64: =OCT!AH64 -> 0 | L64: =NOV!AH64 -> 0 | M64: =DEC!AH64 -> 0 | O64: =AVERAGE(B64:M64) -> 0 | P64: =N64-O64 -> 0
A65: =JAN!A65 -> Taxes Savings | B65: =JAN!AH65 -> 0 | C65: =FEB!AE65 -> 0 | D65: =MAR!AH65 -> 0 | E65: =APR!AH65 -> 0 | F65: =MAY!AH65 -> 0 | G65: =JUN!AH65 -> 0 | H65: =JUL!AH65 -> 0 | I65: =AUG!AH65 -> 0 | J65: =SEP!AH65 -> 0 | K65: =OCT!AH65 -> 0 | L65: =NOV!AH65 -> 0 | M65: =DEC!AH65 -> 0 | O65: =AVERAGE(B65:M65) -> 0 | P65: =N65-O65 -> 0
... A67: =JAN!A67 -> - | B67: =JAN!AH67 -> 0 | C67: =FEB!AE67 -> 0 | D67: =MAR!AH67 -> 0 | E67: =APR!AH67 -> 0 | F67: =MAY!AH67 -> 0 | G67: =JUN!AH67 -> 0 | H67: =JUL!AH67 -> 0 | I67: =AUG!AH67 -> 0 | J67: =SEP!AH67 -> 0 | K67: =OCT!AH67 -> 0 | L67: =NOV!AH67 -> 0 | M67: =DEC!AH67 -> 0 | O67: =AVERAGE(B67:M67) -> 0 | P67: =N67-O67 -> 0
A68: =JAN!A68 -> Debts | B68: =SUM(B69:B79) -> 0 | C68: =SUM(C69:C84) -> 0 | D68: =SUM(D69:D84) -> 0 | E68: =SUM(E69:E84) -> 0 | F68: =SUM(F69:F84) -> 0 | G68: =SUM(G69:G84) -> 0 | H68: =SUM(H69:H84) -> 0 | I68: =SUM(I69:I84) -> 0 | J68: =SUM(J69:J84) -> 0 | ... L68: =SUM(L69:L84) -> 0 | M68: =DEC!H68 -> 0 | N68: =DEC!I68 -> 0 | O68: =DEC!J68 -> 0 | P68: =DEC!K68 -> 0
A69: =JAN!A69 -> NFCU Loan 1151 | B69: =JAN!AH69 -> 0 | C69: =FEB!AE69 -> 0 | D69: =MAR!AH69 -> 0 | E69: =APR!AH69 -> 0 | F69: =MAY!AH69 -> 0 | G69: =JUN!AH69 -> 0 | H69: =JUL!AH69 -> 0 | I69: =AUG!AH69 -> 0 | J69: =SEP!AH69 -> 0 | K69: =OCT!AH69 -> 0 | L69: =NOV!AH69 -> 0 | M69: =DEC!AH69 -> 0 | O69: =AVERAGE(B69:M69) -> 0 | P69: =N69-O69 -> 0
A70: =JAN!A70 -> NFCU Credit Card 8743 | B70: =JAN!AH70 -> 0 | C70: =FEB!AE70 -> 0 | D70: =MAR!AH70 -> 0 | E70: =APR!AH70 -> 0 | F70: =MAY!AH70 -> 0 | G70: =JUN!AH70 -> 0 | H70: =JUL!AH70 -> 0 | I70: =AUG!AH70 -> 0 | J70: =SEP!AH70 -> 0 | K70: =OCT!AH70 -> 0 | L70: =NOV!AH70 -> 0 | M70: =DEC!AH70 -> 0 | O70: =AVERAGE(B70:M70) -> 0 | P70: =N70-O70 -> 0
A71: =JAN!A71 -> Capital One Credit Card 1057 | B71: =JAN!AH71 -> 0 | C71: =FEB!AE71 -> 0 | D71: =MAR!AH71 -> 0 | E71: =APR!AH71 -> 0 | F71: =MAY!AH71 -> 0 | G71: =JUN!AH71 -> 0 | H71: =JUL!AH71 -> 0 | I71: =AUG!AH71 -> 0 | J71: =SEP!AH71 -> 0 | K71: =OCT!AH71 -> 0 | L71: =NOV!AH71 -> 0 | M71: =DEC!AH71 -> 0 | O71: =AVERAGE(B71:M71) -> 0 | P71: =N71-O71 -> 0
A72: =JAN!A72 -> Blink Fitness Collections | B72: =JAN!AH72 -> 0 | C72: =FEB!AE72 -> 0 | D72: =MAR!AH72 -> 0 | E72: =APR!AH72 -> 0 | F72: =MAY!AH72 -> 0 | G72: =JUN!AH72 -> 0 | H72: =JUL!AH72 -> 0 | I72: =AUG!AH72 -> 0 | J72: =SEP!AH72 -> 0 | K72: =OCT!AH72 -> 0 | L72: =NOV!AH72 -> 0 | M72: =DEC!AH72 -> 0 | O72: =AVERAGE(B72:M72) -> 0 | P72: =N72-O72 -> 0
A73: =JAN!A73 -> T-Mobile Phone Bill | B73: =JAN!AH73 -> 0 | C73: =FEB!AE73 -> 0 | D73: =MAR!AH73 -> 0 | E73: =APR!AH73 -> 0 | F73: =MAY!AH73 -> 0 | G73: =JUN!AH73 -> 0 | H73: =JUL!AH73 -> 0 | I73: =AUG!AH73 -> 0 | J73: =SEP!AH73 -> 0 | K73: =OCT!AH73 -> 0 | L73: =NOV!AH73 -> 0 | M73: =DEC!AH73 -> 0 | O73: =AVERAGE(B73:M73) -> 0 | P73: =N73-O73 -> 0
A74: =JAN!A74 -> TD Bank Collections | B74: =JAN!AH74 -> 0 | C74: =FEB!AE74 -> 0 | D74: =MAR!AH74 -> 0 | E74: =APR!AH74 -> 0 | F74: =MAY!AH74 -> 0 | G74: =JUN!AH74 -> 0 | H74: =JUL!AH74 -> 0 | I74: =AUG!AH74 -> 0 | J74: =SEP!AH74 -> 0 | K74: =OCT!AH74 -> 0 | L74: =NOV!AH74 -> 0 | M74: =DEC!AH74 -> 0 | O74: =AVERAGE(B74:M74) -> 0 | P74: =N74-O74 -> 0
A75: =JAN!A75 -> Safegaurd Operations Collections | B75: =JAN!AH75 -> 0 | C75: =FEB!AE75 -> 0 | D75: =MAR!AH75 -> 0 | E75: =APR!AH75 -> 0 | F75: =MAY!AH75 -> 0 | G75: =JUN!AH75 -> 0 | H75: =JUL!AH75 -> 0 | I75: =AUG!AH75 -> 0 | J75: =SEP!AH75 -> 0 | K75: =OCT!AH75 -> 0 | L75: =NOV!AH75 -> 0 | M75: =DEC!AH75 -> 0 | O75: =AVERAGE(B75:M75) -> 0 | P75: =N75-O75 -> 0
A76: =JAN!A76 -> BMCC Loan 474.03 | B76: =JAN!AH76 -> 0 | C76: =FEB!AE76 -> 0 | D76: =MAR!AH76 -> 0 | E76: =APR!AH76 -> 0 | F76: =MAY!AH76 -> 0 | G76: =JUN!AH76 -> 0 | H76: =JUL!AH76 -> 0 | I76: =AUG!AH76 -> 0 | J76: =SEP!AH76 -> 0 | K76: =OCT!AH76 -> 0 | L76: =NOV!AH76 -> 0 | M76: =DEC!AH76 -> 0 | O76: =AVERAGE(B76:M76) -> 0 | P76: =N76-O76 -> 0
A77: =JAN!A77 -> Han Personal Debt (Paid) | B77: =JAN!AH77 -> 0 | C77: =FEB!AE77 -> 0 | D77: =MAR!AH77 -> 0 | E77: =APR!AH77 -> 0 | F77: =MAY!AH77 -> 0 | G77: =JUN!AH77 -> 0 | H77: =JUL!AH77 -> 0 | I77: =AUG!AH77 -> 0 | J77: =SEP!AH77 -> 0 | K77: =OCT!AH77 -> 0 | L77: =NOV!AH77 -> 0 | M77: =DEC!AH77 -> 0 | O77: =AVERAGE(B77:M77) -> 0 | P77: =N77-O77 -> 0
A78: =JAN!A78 | B78: =JAN!AH78 -> 0 | C78: =FEB!AE78 -> 0 | D78: =MAR!AH78 -> 0 | E78: =APR!AH78 -> 0 | F78: =MAY!AH78 -> 0 | G78: =JUN!AH78 -> 0 | H78: =JUL!AH78 -> 0 | I78: =AUG!AH78 -> 0 | J78: =SEP!AH78 -> 0 | K78: =OCT!AH78 -> 0 | L78: =NOV!AH78 -> 0 | M78: =DEC!AH78 -> 0 | O78: =AVERAGE(B78:M78) -> 0 | P78: =N78-O78 -> 0
A79: =JAN!A79 -> Total Debt: 8,551.73 | B79: =JAN!AH79 -> 0 | C79: =FEB!AE79 -> 0 | D79: =MAR!AH79 -> 0 | E79: =APR!AH79 -> 0 | F79: =MAY!AH79 -> 0 | G79: =JUN!AH79 -> 0 | H79: =JUL!AH79 -> 0 | I79: =AUG!AH79 -> 0 | J79: =SEP!AH79 -> 0 | K79: =OCT!AH79 -> 0 | L79: =NOV!AH79 -> 0 | M79: =DEC!AH79 -> 0 | O79: =AVERAGE(B79:M79) -> 0 | P79: =N79-O79 -> 0
A80: =JAN!A80 -> School | B80: =SUM(B81:B91) -> 0 | C80: =FEB!H80 -> 0 | D80: =MAR!H80 -> 0 | E80: =APR!H80 -> 0 | F80: =MAY!H80 -> 0 | G80: =JUN!H80 -> 0 | H80: =JUL!H80 -> 0 | I80: =AUG!H80 -> 0 | J80: =AUG!I80 -> 0 | K80: =AUG!J80 -> 0 | L80: =NOV!H80 -> 0 | M80: =DEC!H80 -> 0 | N80: =DEC!I80 -> 0 | O80: =DEC!J80 -> 0 | P80: =DEC!K80 -> 0
A81: =JAN!A81 -> Tuition | B81: =JAN!AH81 -> 0 | C81: =FEB!AE81 -> 0 | D81: =MAR!AH81 -> 0 | E81: =APR!AH81 -> 0 | F81: =MAY!AH81 -> 0 | G81: =JUN!AH81 -> 0 | H81: =JUL!AH81 -> 0 | I81: =AUG!AH81 -> 0 | J81: =SEP!AH81 -> 0 | K81: =OCT!AH81 -> 0 | L81: =NOV!AH81 -> 0 | M81: =DEC!AH81 -> 0 | O81: =AVERAGE(B81:M81) -> 0 | P81: =N81-O81 -> 0
A82: =JAN!A82 -> Books | B82: =JAN!AH82 -> 0 | C82: =FEB!AE82 -> 0 | D82: =MAR!AH82 -> 0 | E82: =APR!AH82 -> 0 | F82: =MAY!AH82 -> 0 | G82: =JUN!AH82 -> 0 | H82: =JUL!AH82 -> 0 | I82: =AUG!AH82 -> 0 | J82: =SEP!AH82 -> 0 | K82: =OCT!AH82 -> 0 | L82: =NOV!AH82 -> 0 | M82: =DEC!AH82 -> 0 | O82: =AVERAGE(B82:M82) -> 0 | P82: =N82-O82 -> 0
A83: =JAN!A83 | B83: =JAN!AH83 -> 0 | C83: =FEB!AE83 -> 0 | D83: =MAR!AH83 -> 0 | E83: =APR!AH83 -> 0 | F83: =MAY!AH83 -> 0 | G83: =JUN!AH83 -> 0 | H83: =JUL!AH83 -> 0 | I83: =AUG!AH83 -> 0 | J83: =SEP!AH83 -> 0 | K83: =OCT!AH83 -> 0 | L83: =NOV!AH83 -> 0 | M83: =DEC!AH83 -> 0 | O83: =AVERAGE(B83:M83) -> 0 | P83: =N83-O83 -> 0
A84: =JAN!A84 | B84: =JAN!AH84 -> 0 | C84: =FEB!AE84 -> 0 | D84: =MAR!AH84 -> 0 | E84: =APR!AH84 -> 0 | F84: =MAY!AH84 -> 0 | G84: =JUN!AH84 -> 0 | H84: =JUL!AH84 -> 0 | I84: =AUG!AH84 -> 0 | J84: =SEP!AH84 -> 0 | K84: =OCT!AH84 -> 0 | L84: =NOV!AH84 -> 0 | M84: =DEC!AH84 -> 0 | O84: =AVERAGE(B84:M84) -> 0 | P84: =N84-O84 -> 0
A85: =JAN!A85 | B85: =JAN!AH85 -> 0 | C85: =FEB!AE85 -> 0 | D85: =MAR!AH85 -> 0 | E85: =APR!AH85 -> 0 | F85: =MAY!AH85 -> 0 | G85: =JUN!AH85 -> 0 | H85: =JUL!AH85 -> 0 | I85: =AUG!AH85 -> 0 | J85: =SEP!AH85 -> 0 | K85: =OCT!AH85 -> 0 | L85: =NOV!AH85 -> 0 | M85: =DEC!AH85 -> 0 | O85: =AVERAGE(B85:M85) -> 0 | P85: =N85-O85 -> 0
A86: =JAN!A86 | B86: =JAN!AH86 -> 0 | C86: =FEB!AE86 -> 0 | D86: =MAR!AH86 -> 0 | E86: =APR!AH86 -> 0 | F86: =MAY!AH86 -> 0 | G86: =JUN!AH86 -> 0 | H86: =JUL!AH86 -> 0 | I86: =AUG!AH86 -> 0 | J86: =SEP!AH86 -> 0 | K86: =OCT!AH86 -> 0 | L86: =NOV!AH86 -> 0 | M86: =DEC!AH86 -> 0 | O86: =AVERAGE(B86:M86) -> 0 | P86: =N86-O86 -> 0
A87: =JAN!A87 | B87: =JAN!AH87 -> 0 | C87: =FEB!AE87 -> 0 | D87: =MAR!AH87 -> 0 | E87: =APR!AH87 -> 0 | F87: =MAY!AH87 -> 0 | G87: =JUN!AH87 -> 0 | H87: =JUL!AH87 -> 0 | I87: =AUG!AH87 -> 0 | J87: =SEP!AH87 -> 0 | K87: =OCT!AH87 -> 0 | L87: =NOV!AH87 -> 0 | M87: =DEC!AH87 -> 0 | O87: =AVERAGE(B87:M87) -> 0 | P87: =N87-O87 -> 0
A88: =JAN!A88 | B88: =JAN!AH88 -> 0 | C88: =FEB!AE88 -> 0 | D88: =MAR!AH88 -> 0 | E88: =APR!AH88 -> 0 | F88: =MAY!AH88 -> 0 | G88: =JUN!AH88 -> 0 | H88: =JUL!AH88 -> 0 | I88: =AUG!AH88 -> 0 | J88: =SEP!AH88 -> 0 | K88: =OCT!AH88 -> 0 | L88: =NOV!AH88 -> 0 | M88: =DEC!AH88 -> 0 | O88: =AVERAGE(B88:M88) -> 0 | P88: =N88-O88 -> 0
A89: =JAN!A89 | B89: =JAN!AH89 -> 0 | C89: =FEB!AE89 -> 0 | D89: =MAR!AH89 -> 0 | E89: =APR!AH89 -> 0 | F89: =MAY!AH89 -> 0 | G89: =JUN!AH89 -> 0 | H89: =JUL!AH89 -> 0 | I89: =AUG!AH89 -> 0 | J89: =SEP!AH89 -> 0 | K89: =OCT!AH89 -> 0 | L89: =NOV!AH89 -> 0 | M89: =DEC!AH89 -> 0 | O89: =AVERAGE(B89:M89) -> 0 | P89: =N89-O89 -> 0
A90: =JAN!A90 | B90: =JAN!AH90 -> 0 | C90: =FEB!AE90 -> 0 | D90: =MAR!AH90 -> 0 | E90: =APR!AH90 -> 0 | F90: =MAY!AH90 -> 0 | G90: =JUN!AH90 -> 0 | H90: =JUL!AH90 -> 0 | I90: =AUG!AH90 -> 0 | J90: =SEP!AH90 -> 0 | K90: =OCT!AH90 -> 0 | L90: =NOV!AH90 -> 0 | M90: =DEC!AH90 -> 0 | O90: =AVERAGE(B90:M90) -> 0 | P90: =N90-O90 -> 0
A91: =JAN!A91 | B91: =JAN!AH91 -> 0 | C91: =FEB!AE91 -> 0 | D91: =MAR!AH91 -> 0 | E91: =APR!AH91 -> 0 | F91: =MAY!AH91 -> 0 | G91: =JUN!AH91 -> 0 | H91: =JUL!AH91 -> 0 | I91: =AUG!AH91 -> 0 | J91: =SEP!AH91 -> 0 | K91: =OCT!AH91 -> 0 | L91: =NOV!AH91 -> 0 | M91: =DEC!AH91 -> 0 | O91: =AVERAGE(B91:M91) -> 0 | P91: =N91-O91 -> 0
B92: =SUM(B93:B106) -> 0 | C92: =FEB!H92 -> 0 | D92: =MAR!H92 -> 0 | E92: =APR!H92 -> 0 | F92: =MAY!H92 -> 0 | G92: =JUN!H92 -> 0 | H92: =JUL!H92 -> 0 | I92: =AUG!H92 -> 0 | J92: =AUG!I92 -> 0 | K92: =AUG!J92 -> 0 | L92: =NOV!H92 -> 0 | M92: =DEC!H92 -> 0 | N92: =DEC!I92 -> 0 | O92: =DEC!J92 -> 0 | P92: =DEC!K92 -> 0
A93: =JAN!A93 | B93: =JAN!AH93 -> 0 | C93: =FEB!AE93 -> 0 | D93: =MAR!AH93 -> 0 | E93: =APR!AH93 -> 0 | F93: =MAY!AH93 -> 0 | G93: =JUN!AH93 -> 0 | H93: =JUL!AH93 -> 0 | I93: =AUG!AH93 -> 0 | J93: =SEP!AH93 -> 0 | K93: =OCT!AH93 -> 0 | L93: =NOV!AH93 -> 0 | M93: =DEC!AH93 -> 0 | O93: =AVERAGE(B93:M93) -> 0 | P93: =N93-O93 -> 0
A94: =JAN!A94 | B94: =JAN!AH94 -> 0 | C94: =FEB!AE94 -> 0 | D94: =MAR!AH94 -> 0 | E94: =APR!AH94 -> 0 | F94: =MAY!AH94 -> 0 | G94: =JUN!AH94 -> 0 | H94: =JUL!AH94 -> 0 | I94: =AUG!AH94 -> 0 | J94: =SEP!AH94 -> 0 | K94: =OCT!AH94 -> 0 | L94: =NOV!AH94 -> 0 | M94: =DEC!AH94 -> 0 | O94: =AVERAGE(B94:M94) -> 0 | P94: =N94-O94 -> 0
A95: =JAN!A95 | B95: =JAN!AH95 -> 0 | C95: =FEB!AE95 -> 0 | D95: =MAR!AH95 -> 0 | E95: =APR!AH95 -> 0 | F95: =MAY!AH95 -> 0 | G95: =JUN!AH95 -> 0 | H95: =JUL!AH95 -> 0 | I95: =AUG!AH95 -> 0 | J95: =SEP!AH95 -> 0 | K95: =OCT!AH95 -> 0 | L95: =NOV!AH95 -> 0 | M95: =DEC!AH95 -> 0 | O95: =AVERAGE(B95:M95) -> 0 | P95: =N95-O95 -> 0
A96: =JAN!A96 | B96: =JAN!AH96 -> 0 | C96: =FEB!AE96 -> 0 | D96: =MAR!AH96 -> 0 | E96: =APR!AH96 -> 0 | F96: =MAY!AH96 -> 0 | G96: =JUN!AH96 -> 0 | H96: =JUL!AH96 -> 0 | I96: =AUG!AH96 -> 0 | J96: =SEP!AH96 -> 0 | K96: =OCT!AH96 -> 0 | L96: =NOV!AH96 -> 0 | M96: =DEC!AH96 -> 0 | O96: =AVERAGE(B96:M96) -> 0 | P96: =N96-O96 -> 0
A97: =JAN!A97 | B97: =JAN!AH97 -> 0 | C97: =FEB!AE97 -> 0 | D97: =MAR!AH97 -> 0 | E97: =APR!AH97 -> 0 | F97: =MAY!AH97 -> 0 | G97: =JUN!AH97 -> 0 | H97: =JUL!AH97 -> 0 | I97: =AUG!AH97 -> 0 | J97: =SEP!AH97 -> 0 | K97: =OCT!AH97 -> 0 | L97: =NOV!AH97 -> 0 | M97: =DEC!AH97 -> 0 | O97: =AVERAGE(B97:M97) -> 0 | P97: =N97-O97 -> 0
A98: =JAN!A98 | B98: =JAN!AH98 -> 0 | C98: =FEB!AE98 -> 0 | D98: =MAR!AH98 -> 0 | E98: =APR!AH98 -> 0 | F98: =MAY!AH98 -> 0 | G98: =JUN!AH98 -> 0 | H98: =JUL!AH98 -> 0 | I98: =AUG!AH98 -> 0 | J98: =SEP!AH98 -> 0 | K98: =OCT!AH98 -> 0 | L98: =NOV!AH98 -> 0 | M98: =DEC!AH98 -> 0 | O98: =AVERAGE(B98:M98) -> 0 | P98: =N98-O98 -> 0
A99: =JAN!A99 | B99: =JAN!AH99 -> 0 | C99: =FEB!AE99 -> 0 | D99: =MAR!AH99 -> 0 | E99: =APR!AH99 -> 0 | F99: =MAY!AH99 -> 0 | G99: =JUN!AH99 -> 0 | H99: =JUL!AH99 -> 0 | I99: =AUG!AH99 -> 0 | J99: =SEP!AH99 -> 0 | K99: =OCT!AH99 -> 0 | L99: =NOV!AH99 -> 0 | M99: =DEC!AH99 -> 0 | O99: =AVERAGE(B99:M99) -> 0 | P99: =N99-O99 -> 0
A100: =JAN!A100 | B100: =JAN!AH100 -> 0 | C100: =FEB!AE100 -> 0 | D100: =MAR!AH100 -> 0 | E100: =APR!AH100 -> 0 | F100: =MAY!AH100 -> 0 | G100: =JUN!AH100 -> 0 | H100: =JUL!AH100 -> 0 | I100: =AUG!AH100 -> 0 | J100: =SEP!AH100 -> 0 | K100: =OCT!AH100 -> 0 | L100: =NOV!AH100 -> 0 | M100: =DEC!AH100 -> 0 | O100: =AVERAGE(B100:M100) -> 0 | P100: =N100-O100 -> 0
A101: =JAN!A101 | B101: =JAN!AH101 -> 0 | C101: =FEB!AE101 -> 0 | D101: =MAR!AH101 -> 0 | E101: =APR!AH101 -> 0 | F101: =MAY!AH101 -> 0 | G101: =JUN!AH101 -> 0 | H101: =JUL!AH101 -> 0 | I101: =AUG!AH101 -> 0 | J101: =SEP!AH101 -> 0 | K101: =OCT!AH101 -> 0 | L101: =NOV!AH101 -> 0 | M101: =DEC!AH101 -> 0 | O101: =AVERAGE(B101:M101) -> 0 | P101: =N101-O101 -> 0
A102: =JAN!A102 | B102: =JAN!AH102 -> 0 | C102: =FEB!AE102 -> 0 | D102: =MAR!AH102 -> 0 | E102: =APR!AH102 -> 0 | F102: =MAY!AH102 -> 0 | G102: =JUN!AH102 -> 0 | H102: =JUL!AH102 -> 0 | I102: =AUG!AH102 -> 0 | J102: =SEP!AH102 -> 0 | K102: =OCT!AH102 -> 0 | L102: =NOV!AH102 -> 0 | M102: =DEC!AH102 -> 0 | O102: =AVERAGE(B102:M102) -> 0 | P102: =N102-O102 -> 0
A103: =JAN!A103 | B103: =JAN!AH103 -> 0 | C103: =FEB!AE103 -> 0 | D103: =MAR!AH103 -> 0 | E103: =APR!AH103 -> 0 | F103: =MAY!AH103 -> 0 | G103: =JUN!AH103 -> 0 | H103: =JUL!AH103 -> 0 | I103: =AUG!AH103 -> 0 | J103: =SEP!AH103 -> 0 | K103: =OCT!AH103 -> 0 | L103: =NOV!AH103 -> 0 | M103: =DEC!AH103 -> 0 | O103: =AVERAGE(B103:M103) -> 0 | P103: =N103-O103 -> 0
A104: =JAN!A104 | B104: =JAN!AH104 -> 0 | C104: =FEB!AE104 -> 0 | D104: =MAR!AH104 -> 0 | E104: =APR!AH104 -> 0 | F104: =MAY!AH104 -> 0 | G104: =JUN!AH104 -> 0 | H104: =JUL!AH104 -> 0 | I104: =AUG!AH104 -> 0 | J104: =SEP!AH104 -> 0 | K104: =OCT!AH104 -> 0 | L104: =NOV!AH104 -> 0 | M104: =DEC!AH104 -> 0 | O104: =AVERAGE(B104:M104) -> 0 | P104: =N104-O104 -> 0
...
